Workbook

Sheet 12-month forecast summary
A1: 12-month forecast summary
A2: Susanoo — 12-Month Forecast · Susanoo — Base
A4: Variable / dimension | B4: Value | C4: Value > Susanoo — Growth
A5: 12-month revenue | B5: =SUM(IF(IF(IF(AND('Model inputs'!Q21<=DATE(2026,11,1),DATE(2026,11,1)<=EDATE('Model inputs'!Q21,'Model inputs'!Q18-1*1))="",FALSE,AND('Model inputs'!Q21<=DATE(2026,11,1),DATE(2026,11,1)<=EDATE('Model inputs'!Q21,'Model inputs'!Q18-1*1))),'Monthly revenue cost and runway'!B5,"")="",0,IF(IF(AND('Model inputs'!Q21<=DATE(2026,11,1),DATE(2026,11,1)<=EDATE('Model inputs'!Q21,'Model inputs'!Q18-1*1))="",FALSE,AND('Model inputs'!Q21<=DATE(2026,11,1),DATE(2026,11,1)<=EDATE('Model inputs'!Q21,'Model inputs'!Q18-1*1))),'Monthly revenue cost and runway'!B5,"")),IF(IF(IF(AND('Model inputs'!Q21<=DATE(2026,12,1),DATE(2026,12,1)<=EDATE('Model inputs'!Q21,'Model inputs'!Q18-1*1))="",FALSE,AND('Model inputs'!Q21<=DATE(2026,12,1),DATE(2026,12,1)<=EDATE('Model inputs'!Q21,'Model inputs'!Q18-1*1))),'Monthly revenue cost and runway'!C5,"")="",0,IF(IF(AND('Model inputs'!Q21<=DATE(2026,12,1),DATE(2026,12,1)<=EDATE('Model inputs'!Q21,'Model inputs'!Q18-1*1))="",FALSE,AND('Model inputs'!Q21<=DATE(2026,12,1),DATE(2026,12,1)<=EDATE('Model inputs'!Q21,'Model inputs'!Q18-1*1))),'Monthly revenue cost and runway'!C5,"")),IF(IF(IF(AND('Model inputs'!Q21<=DATE(2027,1,1),DATE(2027,1,1)<=EDATE('Model inputs'!Q21,'Model inputs'!Q18-1*1))="",FALSE,AND('Model inputs'!Q21<=DATE(2027,1,1),DATE(2027,1,1)<=EDATE('Model inputs'!Q21,'Model inputs'!Q18-1*1))),'Monthly revenue cost and runway'!D5,"")="",0,IF(IF(AND('Model inputs'!Q21<=DATE(2027,1,1),DATE(2027,1,1)<=EDATE('Model inputs'!Q21,'Model inputs'!Q18-1*1))="",FALSE,AND('Model inputs'!Q21<=DATE(2027,1,1),DATE(2027,1,1)<=EDATE('Model inputs'!Q21,'Model inputs'!Q18-1*1))),'Monthly revenue cost and runway'!D5,"")),IF(IF(IF(AND('Model inputs'!Q21<=DATE(2027,2,1),DATE(2027,2,1)<=EDATE('Model inputs'!Q21,'Model inputs'!Q18-1*1))="",FALSE,AND('Model inputs'!Q21<=DATE(2027,2,1),DATE(2027,2,1)<=EDATE('Model inputs'!Q21,'Model inputs'!Q18-1*1))),'Monthly revenue cost and runway'!E5,"")="",0,IF(IF(AND('Model inputs'!Q21<=DATE(2027,2,1),DATE(2027,2,1)<=EDATE('Model inputs'!Q21,'Model inputs'!Q18-1*1))="",FALSE,AND('Model inputs'!Q21<=DATE(2027,2,1),DATE(2027,2,1)<=EDATE('Model inputs'!Q21,'Model inputs'!Q18-1*1))),'Monthly revenue cost and runway'!E5,"")),IF(IF(IF(AND('Model inputs'!Q21<=DATE(2027,3,1),DATE(2027,3,1)<=EDATE('Model inputs'!Q21,'Model inputs'!Q18-1*1))="",FALSE,AND('Model inputs'!Q21<=DATE(2027,3,1),DATE(2027,3,1)<=EDATE('Model inputs'!Q21,'Model inputs'!Q18-1*1))),'Monthly revenue cost and runway'!F5,"")="",0,IF(IF(AND('Model inputs'!Q21<=DATE(2027,3,1),DATE(2027,3,1)<=EDATE('Model inputs'!Q21,'Model inputs'!Q18-1*1))="",FALSE,AND('Model inputs'!Q21<=DATE(2027,3,1),DATE(2027,3,1)<=EDATE('Model inputs'!Q21,'Model inputs'!Q18-1*1))),'Monthly revenue cost and runway'!F5,"")),IF(IF(IF(AND('Model inputs'!Q21<=DATE(2027,4,1),DATE(2027,4,1)<=EDATE('Model inputs'!Q21,'Model inputs'!Q18-1*1))="",FALSE,AND('Model inputs'!Q21<=DATE(2027,4,1),DATE(2027,4,1)<=EDATE('Model inputs'!Q21,'Model inputs'!Q18-1*1))),'Monthly revenue cost and runway'!G5,"")="",0,IF(IF(AND('Model inputs'!Q21<=DATE(2027,4,1),DATE(2027,4,1)<=EDATE('Model inputs'!Q21,'Model inputs'!Q18-1*1))="",FALSE,AND('Model inputs'!Q21<=DATE(2027,4,1),DATE(2027,4,1)<=EDATE('Model inputs'!Q21,'Model inputs'!Q18-1*1))),'Monthly revenue cost and runway'!G5,"")),IF(IF(IF(AND('Model inputs'!Q21<=DATE(2027,5,1),DATE(2027,5,1)<=EDATE('Model inputs'!Q21,'Model inputs'!Q18-1*1))="",FALSE,AND('Model inputs'!Q21<=DATE(2027,5,1),DATE(2027,5,1)<=EDATE('Model inputs'!Q21,'Model inputs'!Q18-1*1))),'Monthly revenue cost and runway'!H5,"")="",0,IF(IF(AND('Model inputs'!Q21<=DATE(2027,5,1),DATE(2027,5,1)<=EDATE('Model inputs'!Q21,'Model inputs'!Q18-1*1))="",FALSE,AND('Model inputs'!Q21<=DATE(2027,5,1),DATE(2027,5,1)<=EDATE('Model inputs'!Q21,'Model inputs'!Q18-1*1))),'Monthly revenue cost and runway'!H5,"")),IF(IF(IF(AND('Model inputs'!Q21<=DATE(2027,6,1),DATE(2027,6,1)<=EDATE('Model inputs'!Q21,'Model inputs'!Q18-1*1))="",FALSE,AND('Model inputs'!Q21<=DATE(2027,6,1),DATE(2027,6,1)<=EDATE('Model inputs'!Q21,'Model inputs'!Q18-1*1))),'Monthly revenue cost and runway'!I5,"")="",0,IF(IF(AND('Model inputs'!Q21<=DATE(2027,6,1),DATE(2027,6,1)<=EDATE('Model inputs'!Q21,'Model inputs'!Q18-1*1))="",FALSE,AND('Model inputs'!Q21<=DATE(2027,6,1),DATE(2027,6,1)<=EDATE('Model inputs'!Q21,'Model inputs'!Q18-1*1))),'Monthly revenue cost and runway'!I5,"")),IF(IF(IF(AND('Model inputs'!Q21<=DATE(2027,7,1),DATE(2027,7,1)<=EDATE('Model inputs'!Q21,'Model inputs'!Q18-1*1))="",FALSE,AND('Model inputs'!Q21<=DATE(2027,7,1),DATE(2027,7,1)<=EDATE('Model inputs'!Q21,'Model inputs'!Q18-1*1))),'Monthly revenue cost and runway'!J5,"")="",0,IF(IF(AND('Model inputs'!Q21<=DATE(2027,7,1),DATE(2027,7,1)<=EDATE('Model inputs'!Q21,'Model inputs'!Q18-1*1))="",FALSE,AND('Model inputs'!Q21<=DATE(2027,7,1),DATE(2027,7,1)<=EDATE('Model inputs'!Q21,'Model inputs'!Q18-1*1))),'Monthly revenue cost and runway'!J5,"")),IF(IF(IF(AND('Model inputs'!Q21<=DATE(2027,8,1),DATE(2027,8,1)<=EDATE('Model inputs'!Q21,'Model inputs'!Q18-1*1))="",FALSE,AND('Model inputs'!Q21<=DATE(2027,8,1),DATE(2027,8,1)<=EDATE('Model inputs'!Q21,'Model inputs'!Q18-1*1))),'Monthly revenue cost and runway'!K5,"")="",0,IF(IF(AND('Model inputs'!Q21<=DATE(2027,8,1),DATE(2027,8,1)<=EDATE('Model inputs'!Q21,'Model inputs'!Q18-1*1))="",FALSE,AND('Model inputs'!Q21<=DATE(2027,8,1),DATE(2027,8,1)<=EDATE('Model inputs'!Q21,'Model inputs'!Q18-1*1))),'Monthly revenue cost and runway'!K5,"")),IF(IF(IF(AND('Model inputs'!Q21<=DATE(2027,9,1),DATE(2027,9,1)<=EDATE('Model inputs'!Q21,'Model inputs'!Q18-1*1))="",FALSE,AND('Model inputs'!Q21<=DATE(2027,9,1),DATE(2027,9,1)<=EDATE('Model inputs'!Q21,'Model inputs'!Q18-1*1))),'Monthly revenue cost and runway'!L5,"")="",0,IF(IF(AND('Model inputs'!Q21<=DATE(2027,9,1),DATE(2027,9,1)<=EDATE('Model inputs'!Q21,'Model inputs'!Q18-1*1))="",FALSE,AND('Model inputs'!Q21<=DATE(2027,9,1),DATE(2027,9,1)<=EDATE('Model inputs'!Q21,'Model inputs'!Q18-1*1))),'Monthly revenue cost and runway'!L5,"")),IF(IF(IF(AND('Model inputs'!Q21<=DATE(2027,10,1),DATE(2027,10,1)<=EDATE('Model inputs'!Q21,'Model inputs'!Q18-1*1))="",FALSE,AND('Model inputs'!Q21<=DATE(2027,10,1),DATE(2027,10,1)<=EDATE('Model inputs'!Q21,'Model inputs'!Q18-1*1))),'Monthly revenue cost and runway'!M5,"")="",0,IF(IF(AND('Model inputs'!Q21<=DATE(2027,10,1),DATE(2027,10,1)<=EDATE('Model inputs'!Q21,'Model inputs'!Q18-1*1))="",FALSE,AND('Model inputs'!Q21<=DATE(2027,10,1),DATE(2027,10,1)<=EDATE('Model inputs'!Q21,'Model inputs'!Q18-1*1))),'Monthly revenue cost and runway'!M5,"")),IF(IF(IF(AND('Model inputs'!Q21<=DATE(2026,9,1),DATE(2026,9,1)<=EDATE('Model inputs'!Q21,'Model inputs'!Q18-1*1))="",FALSE,AND('Model inputs'!Q21<=DATE(2026,9,1),DATE(2026,9,1)<=EDATE('Model inputs'!Q21,'Model inputs'!Q18-1*1))),'Model inputs'!C24,"")="",0,IF(IF(AND('Model inputs'!Q21<=DATE(2026,9,1),DATE(2026,9,1)<=EDATE('Model inputs'!Q21,'Model inputs'!Q18-1*1))="",FALSE,AND('Model inputs'!Q21<=DATE(2026,9,1),DATE(2026,9,1)<=EDATE('Model inputs'!Q21,'Model inputs'!Q18-1*1))),'Model inputs'!C24,"")),IF(IF(IF(AND('Model inputs'!Q21<=DATE(2026,10,1),DATE(2026,10,1)<=EDATE('Model inputs'!Q21,'Model inputs'!Q18-1*1))="",FALSE,AND('Model inputs'!Q21<=DATE(2026,10,1),DATE(2026,10,1)<=EDATE('Model inputs'!Q21,'Model inputs'!Q18-1*1))),'Model inputs'!D24,"")="",0,IF(IF(AND('Model inputs'!Q21<=DATE(2026,10,1),DATE(2026,10,1)<=EDATE('Model inputs'!Q21,'Model inputs'!Q18-1*1))="",FALSE,AND('Model inputs'!Q21<=DATE(2026,10,1),DATE(2026,10,1)<=EDATE('Model inputs'!Q21,'Model inputs'!Q18-1*1))),'Model inputs'!D24,""))) -> 25908 | C5: =SUM(IF(IF(IF(AND('Model inputs'!Q23<=DATE(2026,10,1),DATE(2026,10,1)<=EDATE('Model inputs'!Q23,'Model inputs'!Q20-1*1))="",FALSE,AND('Model inputs'!Q23<=DATE(2026,10,1),DATE(2026,10,1)<=EDATE('Model inputs'!Q23,'Model inputs'!Q20-1*1))),'Model inputs'!D29,"")="",0,IF(IF(AND('Model inputs'!Q23<=DATE(2026,10,1),DATE(2026,10,1)<=EDATE('Model inputs'!Q23,'Model inputs'!Q20-1*1))="",FALSE,AND('Model inputs'!Q23<=DATE(2026,10,1),DATE(2026,10,1)<=EDATE('Model inputs'!Q23,'Model inputs'!Q20-1*1))),'Model inputs'!D29,"")),IF(IF(IF(AND('Model inputs'!Q23<=DATE(2026,11,1),DATE(2026,11,1)<=EDATE('Model inputs'!Q23,'Model inputs'!Q20-1*1))="",FALSE,AND('Model inputs'!Q23<=DATE(2026,11,1),DATE(2026,11,1)<=EDATE('Model inputs'!Q23,'Model inputs'!Q20-1*1))),'Model inputs'!E29,"")="",0,IF(IF(AND('Model inputs'!Q23<=DATE(2026,11,1),DATE(2026,11,1)<=EDATE('Model inputs'!Q23,'Model inputs'!Q20-1*1))="",FALSE,AND('Model inputs'!Q23<=DATE(2026,11,1),DATE(2026,11,1)<=EDATE('Model inputs'!Q23,'Model inputs'!Q20-1*1))),'Model inputs'!E29,"")),IF(IF(IF(AND('Model inputs'!Q23<=DATE(2026,12,1),DATE(2026,12,1)<=EDATE('Model inputs'!Q23,'Model inputs'!Q20-1*1))="",FALSE,AND('Model inputs'!Q23<=DATE(2026,12,1),DATE(2026,12,1)<=EDATE('Model inputs'!Q23,'Model inputs'!Q20-1*1))),'Model inputs'!F29,"")="",0,IF(IF(AND('Model inputs'!Q23<=DATE(2026,12,1),DATE(2026,12,1)<=EDATE('Model inputs'!Q23,'Model inputs'!Q20-1*1))="",FALSE,AND('Model inputs'!Q23<=DATE(2026,12,1),DATE(2026,12,1)<=EDATE('Model inputs'!Q23,'Model inputs'!Q20-1*1))),'Model inputs'!F29,"")),IF(IF(IF(AND('Model inputs'!Q23<=DATE(2027,1,1),DATE(2027,1,1)<=EDATE('Model inputs'!Q23,'Model inputs'!Q20-1*1))="",FALSE,AND('Model inputs'!Q23<=DATE(2027,1,1),DATE(2027,1,1)<=EDATE('Model inputs'!Q23,'Model inputs'!Q20-1*1))),'Model inputs'!G29,"")="",0,IF(IF(AND('Model inputs'!Q23<=DATE(2027,1,1),DATE(2027,1,1)<=EDATE('Model inputs'!Q23,'Model inputs'!Q20-1*1))="",FALSE,AND('Model inputs'!Q23<=DATE(2027,1,1),DATE(2027,1,1)<=EDATE('Model inputs'!Q23,'Model inputs'!Q20-1*1))),'Model inputs'!G29,"")),IF(IF(IF(AND('Model inputs'!Q23<=DATE(2027,2,1),DATE(2027,2,1)<=EDATE('Model inputs'!Q23,'Model inputs'!Q20-1*1))="",FALSE,AND('Model inputs'!Q23<=DATE(2027,2,1),DATE(2027,2,1)<=EDATE('Model inputs'!Q23,'Model inputs'!Q20-1*1))),'Model inputs'!H29,"")="",0,IF(IF(AND('Model inputs'!Q23<=DATE(2027,2,1),DATE(2027,2,1)<=EDATE('Model inputs'!Q23,'Model inputs'!Q20-1*1))="",FALSE,AND('Model inputs'!Q23<=DATE(2027,2,1),DATE(2027,2,1)<=EDATE('Model inputs'!Q23,'Model inputs'!Q20-1*1))),'Model inputs'!H29,"")),IF(IF(IF(AND('Model inputs'!Q23<=DATE(2027,3,1),DATE(2027,3,1)<=EDATE('Model inputs'!Q23,'Model inputs'!Q20-1*1))="",FALSE,AND('Model inputs'!Q23<=DATE(2027,3,1),DATE(2027,3,1)<=EDATE('Model inputs'!Q23,'Model inputs'!Q20-1*1))),'Model inputs'!I29,"")="",0,IF(IF(AND('Model inputs'!Q23<=DATE(2027,3,1),DATE(2027,3,1)<=EDATE('Model inputs'!Q23,'Model inputs'!Q20-1*1))="",FALSE,AND('Model inputs'!Q23<=DATE(2027,3,1),DATE(2027,3,1)<=EDATE('Model inputs'!Q23,'Model inputs'!Q20-1*1))),'Model inputs'!I29,"")),IF(IF(IF(AND('Model inputs'!Q23<=DATE(2027,4,1),DATE(2027,4,1)<=EDATE('Model inputs'!Q23,'Model inputs'!Q20-1*1))="",FALSE,AND('Model inputs'!Q23<=DATE(2027,4,1),DATE(2027,4,1)<=EDATE('Model inputs'!Q23,'Model inputs'!Q20-1*1))),'Model inputs'!J29,"")="",0,IF(IF(AND('Model inputs'!Q23<=DATE(2027,4,1),DATE(2027,4,1)<=EDATE('Model inputs'!Q23,'Model inputs'!Q20-1*1))="",FALSE,AND('Model inputs'!Q23<=DATE(2027,4,1),DATE(2027,4,1)<=EDATE('Model inputs'!Q23,'Model inputs'!Q20-1*1))),'Model inputs'!J29,"")),IF(IF(IF(AND('Model inputs'!Q23<=DATE(2027,5,1),DATE(2027,5,1)<=EDATE('Model inputs'!Q23,'Model inputs'!Q20-1*1))="",FALSE,AND('Model inputs'!Q23<=DATE(2027,5,1),DATE(2027,5,1)<=EDATE('Model inputs'!Q23,'Model inputs'!Q20-1*1))),'Model inputs'!K29,"")="",0,IF(IF(AND('Model inputs'!Q23<=DATE(2027,5,1),DATE(2027,5,1)<=EDATE('Model inputs'!Q23,'Model inputs'!Q20-1*1))="",FALSE,AND('Model inputs'!Q23<=DATE(2027,5,1),DATE(2027,5,1)<=EDATE('Model inputs'!Q23,'Model inputs'!Q20-1*1))),'Model inputs'!K29,"")),IF(IF(IF(AND('Model inputs'!Q23<=DATE(2027,6,1),DATE(2027,6,1)<=EDATE('Model inputs'!Q23,'Model inputs'!Q20-1*1))="",FALSE,AND('Model inputs'!Q23<=DATE(2027,6,1),DATE(2027,6,1)<=EDATE('Model inputs'!Q23,'Model inputs'!Q20-1*1))),'Model inputs'!L29,"")="",0,IF(IF(AND('Model inputs'!Q23<=DATE(2027,6,1),DATE(2027,6,1)<=EDATE('Model inputs'!Q23,'Model inputs'!Q20-1*1))="",FALSE,AND('Model inputs'!Q23<=DATE(2027,6,1),DATE(2027,6,1)<=EDATE('Model inputs'!Q23,'Model inputs'!Q20-1*1))),'Model inputs'!L29,"")),IF(IF(IF(AND('Model inputs'!Q23<=DATE(2027,7,1),DATE(2027,7,1)<=EDATE('Model inputs'!Q23,'Model inputs'!Q20-1*1))="",FALSE,AND('Model inputs'!Q23<=DATE(2027,7,1),DATE(2027,7,1)<=EDATE('Model inputs'!Q23,'Model inputs'!Q20-1*1))),'Model inputs'!M29,"")="",0,IF(IF(AND('Model inputs'!Q23<=DATE(2027,7,1),DATE(2027,7,1)<=EDATE('Model inputs'!Q23,'Model inputs'!Q20-1*1))="",FALSE,AND('Model inputs'!Q23<=DATE(2027,7,1),DATE(2027,7,1)<=EDATE('Model inputs'!Q23,'Model inputs'!Q20-1*1))),'Model inputs'!M29,"")),IF(IF(IF(AND('Model inputs'!Q23<=DATE(2027,8,1),DATE(2027,8,1)<=EDATE('Model inputs'!Q23,'Model inputs'!Q20-1*1))="",FALSE,AND('Model inputs'!Q23<=DATE(2027,8,1),DATE(2027,8,1)<=EDATE('Model inputs'!Q23,'Model inputs'!Q20-1*1))),'Model inputs'!N29,"")="",0,IF(IF(AND('Model inputs'!Q23<=DATE(2027,8,1),DATE(2027,8,1)<=EDATE('Model inputs'!Q23,'Model inputs'!Q20-1*1))="",FALSE,AND('Model inputs'!Q23<=DATE(2027,8,1),DATE(2027,8,1)<=EDATE('Model inputs'!Q23,'Model inputs'!Q20-1*1))),'Model inputs'!N29,"")),IF(IF(IF(AND('Model inputs'!Q23<=DATE(2027,9,1),DATE(2027,9,1)<=EDATE('Model inputs'!Q23,'Model inputs'!Q20-1*1))="",FALSE,AND('Model inputs'!Q23<=DATE(2027,9,1),DATE(2027,9,1)<=EDATE('Model inputs'!Q23,'Model inputs'!Q20-1*1))),'Model inputs'!O29,"")="",0,IF(IF(AND('Model inputs'!Q23<=DATE(2027,9,1),DATE(2027,9,1)<=EDATE('Model inputs'!Q23,'Model inputs'!Q20-1*1))="",FALSE,AND('Model inputs'!Q23<=DATE(2027,9,1),DATE(2027,9,1)<=EDATE('Model inputs'!Q23,'Model inputs'!Q20-1*1))),'Model inputs'!O29,"")),IF(IF(IF(AND('Model inputs'!Q23<=DATE(2027,10,1),DATE(2027,10,1)<=EDATE('Model inputs'!Q23,'Model inputs'!Q20-1*1))="",FALSE,AND('Model inputs'!Q23<=DATE(2027,10,1),DATE(2027,10,1)<=EDATE('Model inputs'!Q23,'Model inputs'!Q20-1*1))),'Model inputs'!P29,"")="",0,IF(IF(AND('Model inputs'!Q23<=DATE(2027,10,1),DATE(2027,10,1)<=EDATE('Model inputs'!Q23,'Model inputs'!Q20-1*1))="",FALSE,AND('Model inputs'!Q23<=DATE(2027,10,1),DATE(2027,10,1)<=EDATE('Model inputs'!Q23,'Model inputs'!Q20-1*1))),'Model inputs'!P29,"")),IF(IF(IF(AND('Model inputs'!Q23<=DATE(2026,9,1),DATE(2026,9,1)<=EDATE('Model inputs'!Q23,'Model inputs'!Q20-1*1))="",FALSE,AND('Model inputs'!Q23<=DATE(2026,9,1),DATE(2026,9,1)<=EDATE('Model inputs'!Q23,'Model inputs'!Q20-1*1))),'Model inputs'!C104,"")="",0,IF(IF(AND('Model inputs'!Q23<=DATE(2026,9,1),DATE(2026,9,1)<=EDATE('Model inputs'!Q23,'Model inputs'!Q20-1*1))="",FALSE,AND('Model inputs'!Q23<=DATE(2026,9,1),DATE(2026,9,1)<=EDATE('Model inputs'!Q23,'Model inputs'!Q20-1*1))),'Model inputs'!C104,""))) -> 97470
A6: 12-month costs | B6: =SUM(IF(IF(IF(AND('Model inputs'!Q21<=DATE(2026,11,1),DATE(2026,11,1)<=EDATE('Model inputs'!Q21,'Model inputs'!Q18-1*1))="",FALSE,AND('Model inputs'!Q21<=DATE(2026,11,1),DATE(2026,11,1)<=EDATE('Model inputs'!Q21,'Model inputs'!Q18-1*1))),'Monthly revenue cost and runway'!B16,"")="",0,IF(IF(AND('Model inputs'!Q21<=DATE(2026,11,1),DATE(2026,11,1)<=EDATE('Model inputs'!Q21,'Model inputs'!Q18-1*1))="",FALSE,AND('Model inputs'!Q21<=DATE(2026,11,1),DATE(2026,11,1)<=EDATE('Model inputs'!Q21,'Model inputs'!Q18-1*1))),'Monthly revenue cost and runway'!B16,"")),IF(IF(IF(AND('Model inputs'!Q21<=DATE(2026,12,1),DATE(2026,12,1)<=EDATE('Model inputs'!Q21,'Model inputs'!Q18-1*1))="",FALSE,AND('Model inputs'!Q21<=DATE(2026,12,1),DATE(2026,12,1)<=EDATE('Model inputs'!Q21,'Model inputs'!Q18-1*1))),'Monthly revenue cost and runway'!C16,"")="",0,IF(IF(AND('Model inputs'!Q21<=DATE(2026,12,1),DATE(2026,12,1)<=EDATE('Model inputs'!Q21,'Model inputs'!Q18-1*1))="",FALSE,AND('Model inputs'!Q21<=DATE(2026,12,1),DATE(2026,12,1)<=EDATE('Model inputs'!Q21,'Model inputs'!Q18-1*1))),'Monthly revenue cost and runway'!C16,"")),IF(IF(IF(AND('Model inputs'!Q21<=DATE(2027,1,1),DATE(2027,1,1)<=EDATE('Model inputs'!Q21,'Model inputs'!Q18-1*1))="",FALSE,AND('Model inputs'!Q21<=DATE(2027,1,1),DATE(2027,1,1)<=EDATE('Model inputs'!Q21,'Model inputs'!Q18-1*1))),'Monthly revenue cost and runway'!D16,"")="",0,IF(IF(AND('Model inputs'!Q21<=DATE(2027,1,1),DATE(2027,1,1)<=EDATE('Model inputs'!Q21,'Model inputs'!Q18-1*1))="",FALSE,AND('Model inputs'!Q21<=DATE(2027,1,1),DATE(2027,1,1)<=EDATE('Model inputs'!Q21,'Model inputs'!Q18-1*1))),'Monthly revenue cost and runway'!D16,"")),IF(IF(IF(AND('Model inputs'!Q21<=DATE(2027,2,1),DATE(2027,2,1)<=EDATE('Model inputs'!Q21,'Model inputs'!Q18-1*1))="",FALSE,AND('Model inputs'!Q21<=DATE(2027,2,1),DATE(2027,2,1)<=EDATE('Model inputs'!Q21,'Model inputs'!Q18-1*1))),'Monthly revenue cost and runway'!E16,"")="",0,IF(IF(AND('Model inputs'!Q21<=DATE(2027,2,1),DATE(2027,2,1)<=EDATE('Model inputs'!Q21,'Model inputs'!Q18-1*1))="",FALSE,AND('Model inputs'!Q21<=DATE(2027,2,1),DATE(2027,2,1)<=EDATE('Model inputs'!Q21,'Model inputs'!Q18-1*1))),'Monthly revenue cost and runway'!E16,"")),IF(IF(IF(AND('Model inputs'!Q21<=DATE(2027,3,1),DATE(2027,3,1)<=EDATE('Model inputs'!Q21,'Model inputs'!Q18-1*1))="",FALSE,AND('Model inputs'!Q21<=DATE(2027,3,1),DATE(2027,3,1)<=EDATE('Model inputs'!Q21,'Model inputs'!Q18-1*1))),'Monthly revenue cost and runway'!F16,"")="",0,IF(IF(AND('Model inputs'!Q21<=DATE(2027,3,1),DATE(2027,3,1)<=EDATE('Model inputs'!Q21,'Model inputs'!Q18-1*1))="",FALSE,AND('Model inputs'!Q21<=DATE(2027,3,1),DATE(2027,3,1)<=EDATE('Model inputs'!Q21,'Model inputs'!Q18-1*1))),'Monthly revenue cost and runway'!F16,"")),IF(IF(IF(AND('Model inputs'!Q21<=DATE(2027,4,1),DATE(2027,4,1)<=EDATE('Model inputs'!Q21,'Model inputs'!Q18-1*1))="",FALSE,AND('Model inputs'!Q21<=DATE(2027,4,1),DATE(2027,4,1)<=EDATE('Model inputs'!Q21,'Model inputs'!Q18-1*1))),'Monthly revenue cost and runway'!G16,"")="",0,IF(IF(AND('Model inputs'!Q21<=DATE(2027,4,1),DATE(2027,4,1)<=EDATE('Model inputs'!Q21,'Model inputs'!Q18-1*1))="",FALSE,AND('Model inputs'!Q21<=DATE(2027,4,1),DATE(2027,4,1)<=EDATE('Model inputs'!Q21,'Model inputs'!Q18-1*1))),'Monthly revenue cost and runway'!G16,"")),IF(IF(IF(AND('Model inputs'!Q21<=DATE(2027,5,1),DATE(2027,5,1)<=EDATE('Model inputs'!Q21,'Model inputs'!Q18-1*1))="",FALSE,AND('Model inputs'!Q21<=DATE(2027,5,1),DATE(2027,5,1)<=EDATE('Model inputs'!Q21,'Model inputs'!Q18-1*1))),'Monthly revenue cost and runway'!H16,"")="",0,IF(IF(AND('Model inputs'!Q21<=DATE(2027,5,1),DATE(2027,5,1)<=EDATE('Model inputs'!Q21,'Model inputs'!Q18-1*1))="",FALSE,AND('Model inputs'!Q21<=DATE(2027,5,1),DATE(2027,5,1)<=EDATE('Model inputs'!Q21,'Model inputs'!Q18-1*1))),'Monthly revenue cost and runway'!H16,"")),IF(IF(IF(AND('Model inputs'!Q21<=DATE(2027,6,1),DATE(2027,6,1)<=EDATE('Model inputs'!Q21,'Model inputs'!Q18-1*1))="",FALSE,AND('Model inputs'!Q21<=DATE(2027,6,1),DATE(2027,6,1)<=EDATE('Model inputs'!Q21,'Model inputs'!Q18-1*1))),'Monthly revenue cost and runway'!I16,"")="",0,IF(IF(AND('Model inputs'!Q21<=DATE(2027,6,1),DATE(2027,6,1)<=EDATE('Model inputs'!Q21,'Model inputs'!Q18-1*1))="",FALSE,AND('Model inputs'!Q21<=DATE(2027,6,1),DATE(2027,6,1)<=EDATE('Model inputs'!Q21,'Model inputs'!Q18-1*1))),'Monthly revenue cost and runway'!I16,"")),IF(IF(IF(AND('Model inputs'!Q21<=DATE(2027,7,1),DATE(2027,7,1)<=EDATE('Model inputs'!Q21,'Model inputs'!Q18-1*1))="",FALSE,AND('Model inputs'!Q21<=DATE(2027,7,1),DATE(2027,7,1)<=EDATE('Model inputs'!Q21,'Model inputs'!Q18-1*1))),'Monthly revenue cost and runway'!J16,"")="",0,IF(IF(AND('Model inputs'!Q21<=DATE(2027,7,1),DATE(2027,7,1)<=EDATE('Model inputs'!Q21,'Model inputs'!Q18-1*1))="",FALSE,AND('Model inputs'!Q21<=DATE(2027,7,1),DATE(2027,7,1)<=EDATE('Model inputs'!Q21,'Model inputs'!Q18-1*1))),'Monthly revenue cost and runway'!J16,"")),IF(IF(IF(AND('Model inputs'!Q21<=DATE(2027,8,1),DATE(2027,8,1)<=EDATE('Model inputs'!Q21,'Model inputs'!Q18-1*1))="",FALSE,AND('Model inputs'!Q21<=DATE(2027,8,1),DATE(2027,8,1)<=EDATE('Model inputs'!Q21,'Model inputs'!Q18-1*1))),'Monthly revenue cost and runway'!K16,"")="",0,IF(IF(AND('Model inputs'!Q21<=DATE(2027,8,1),DATE(2027,8,1)<=EDATE('Model inputs'!Q21,'Model inputs'!Q18-1*1))="",FALSE,AND('Model inputs'!Q21<=DATE(2027,8,1),DATE(2027,8,1)<=EDATE('Model inputs'!Q21,'Model inputs'!Q18-1*1))),'Monthly revenue cost and runway'!K16,"")),IF(IF(IF(AND('Model inputs'!Q21<=DATE(2027,9,1),DATE(2027,9,1)<=EDATE('Model inputs'!Q21,'Model inputs'!Q18-1*1))="",FALSE,AND('Model inputs'!Q21<=DATE(2027,9,1),DATE(2027,9,1)<=EDATE('Model inputs'!Q21,'Model inputs'!Q18-1*1))),'Monthly revenue cost and runway'!L16,"")="",0,IF(IF(AND('Model inputs'!Q21<=DATE(2027,9,1),DATE(2027,9,1)<=EDATE('Model inputs'!Q21,'Model inputs'!Q18-1*1))="",FALSE,AND('Model inputs'!Q21<=DATE(2027,9,1),DATE(2027,9,1)<=EDATE('Model inputs'!Q21,'Model inputs'!Q18-1*1))),'Monthly revenue cost and runway'!L16,"")),IF(IF(IF(AND('Model inputs'!Q21<=DATE(2027,10,1),DATE(2027,10,1)<=EDATE('Model inputs'!Q21,'Model inputs'!Q18-1*1))="",FALSE,AND('Model inputs'!Q21<=DATE(2027,10,1),DATE(2027,10,1)<=EDATE('Model inputs'!Q21,'Model inputs'!Q18-1*1))),'Monthly revenue cost and runway'!M16,"")="",0,IF(IF(AND('Model inputs'!Q21<=DATE(2027,10,1),DATE(2027,10,1)<=EDATE('Model inputs'!Q21,'Model inputs'!Q18-1*1))="",FALSE,AND('Model inputs'!Q21<=DATE(2027,10,1),DATE(2027,10,1)<=EDATE('Model inputs'!Q21,'Model inputs'!Q18-1*1))),'Monthly revenue cost and runway'!M16,"")),IF(IF(IF(AND('Model inputs'!Q21<=DATE(2026,9,1),DATE(2026,9,1)<=EDATE('Model inputs'!Q21,'Model inputs'!Q18-1*1))="",FALSE,AND('Model inputs'!Q21<=DATE(2026,9,1),DATE(2026,9,1)<=EDATE('Model inputs'!Q21,'Model inputs'!Q18-1*1))),'Model inputs'!C42,"")="",0,IF(IF(AND('Model inputs'!Q21<=DATE(2026,9,1),DATE(2026,9,1)<=EDATE('Model inputs'!Q21,'Model inputs'!Q18-1*1))="",FALSE,AND('Model inputs'!Q21<=DATE(2026,9,1),DATE(2026,9,1)<=EDATE('Model inputs'!Q21,'Model inputs'!Q18-1*1))),'Model inputs'!C42,"")),IF(IF(IF(AND('Model inputs'!Q21<=DATE(2026,10,1),DATE(2026,10,1)<=EDATE('Model inputs'!Q21,'Model inputs'!Q18-1*1))="",FALSE,AND('Model inputs'!Q21<=DATE(2026,10,1),DATE(2026,10,1)<=EDATE('Model inputs'!Q21,'Model inputs'!Q18-1*1))),'Model inputs'!D42,"")="",0,IF(IF(AND('Model inputs'!Q21<=DATE(2026,10,1),DATE(2026,10,1)<=EDATE('Model inputs'!Q21,'Model inputs'!Q18-1*1))="",FALSE,AND('Model inputs'!Q21<=DATE(2026,10,1),DATE(2026,10,1)<=EDATE('Model inputs'!Q21,'Model inputs'!Q18-1*1))),'Model inputs'!D42,""))) -> 12420.2 | C6: =SUM(IF(IF(IF(AND('Model inputs'!Q23<=DATE(2026,10,1),DATE(2026,10,1)<=EDATE('Model inputs'!Q23,'Model inputs'!Q20-1*1))="",FALSE,AND('Model inputs'!Q23<=DATE(2026,10,1),DATE(2026,10,1)<=EDATE('Model inputs'!Q23,'Model inputs'!Q20-1*1))),'Model inputs'!D43,"")="",0,IF(IF(AND('Model inputs'!Q23<=DATE(2026,10,1),DATE(2026,10,1)<=EDATE('Model inputs'!Q23,'Model inputs'!Q20-1*1))="",FALSE,AND('Model inputs'!Q23<=DATE(2026,10,1),DATE(2026,10,1)<=EDATE('Model inputs'!Q23,'Model inputs'!Q20-1*1))),'Model inputs'!D43,"")),IF(IF(IF(AND('Model inputs'!Q23<=DATE(2026,11,1),DATE(2026,11,1)<=EDATE('Model inputs'!Q23,'Model inputs'!Q20-1*1))="",FALSE,AND('Model inputs'!Q23<=DATE(2026,11,1),DATE(2026,11,1)<=EDATE('Model inputs'!Q23,'Model inputs'!Q20-1*1))),'Model inputs'!E43,"")="",0,IF(IF(AND('Model inputs'!Q23<=DATE(2026,11,1),DATE(2026,11,1)<=EDATE('Model inputs'!Q23,'Model inputs'!Q20-1*1))="",FALSE,AND('Model inputs'!Q23<=DATE(2026,11,1),DATE(2026,11,1)<=EDATE('Model inputs'!Q23,'Model inputs'!Q20-1*1))),'Model inputs'!E43,"")),IF(IF(IF(AND('Model inputs'!Q23<=DATE(2026,12,1),DATE(2026,12,1)<=EDATE('Model inputs'!Q23,'Model inputs'!Q20-1*1))="",FALSE,AND('Model inputs'!Q23<=DATE(2026,12,1),DATE(2026,12,1)<=EDATE('Model inputs'!Q23,'Model inputs'!Q20-1*1))),'Model inputs'!F43,"")="",0,IF(IF(AND('Model inputs'!Q23<=DATE(2026,12,1),DATE(2026,12,1)<=EDATE('Model inputs'!Q23,'Model inputs'!Q20-1*1))="",FALSE,AND('Model inputs'!Q23<=DATE(2026,12,1),DATE(2026,12,1)<=EDATE('Model inputs'!Q23,'Model inputs'!Q20-1*1))),'Model inputs'!F43,"")),IF(IF(IF(AND('Model inputs'!Q23<=DATE(2027,1,1),DATE(2027,1,1)<=EDATE('Model inputs'!Q23,'Model inputs'!Q20-1*1))="",FALSE,AND('Model inputs'!Q23<=DATE(2027,1,1),DATE(2027,1,1)<=EDATE('Model inputs'!Q23,'Model inputs'!Q20-1*1))),'Model inputs'!G43,"")="",0,IF(IF(AND('Model inputs'!Q23<=DATE(2027,1,1),DATE(2027,1,1)<=EDATE('Model inputs'!Q23,'Model inputs'!Q20-1*1))="",FALSE,AND('Model inputs'!Q23<=DATE(2027,1,1),DATE(2027,1,1)<=EDATE('Model inputs'!Q23,'Model inputs'!Q20-1*1))),'Model inputs'!G43,"")),IF(IF(IF(AND('Model inputs'!Q23<=DATE(2027,2,1),DATE(2027,2,1)<=EDATE('Model inputs'!Q23,'Model inputs'!Q20-1*1))="",FALSE,AND('Model inputs'!Q23<=DATE(2027,2,1),DATE(2027,2,1)<=EDATE('Model inputs'!Q23,'Model inputs'!Q20-1*1))),'Model inputs'!H43,"")="",0,IF(IF(AND('Model inputs'!Q23<=DATE(2027,2,1),DATE(2027,2,1)<=EDATE('Model inputs'!Q23,'Model inputs'!Q20-1*1))="",FALSE,AND('Model inputs'!Q23<=DATE(2027,2,1),DATE(2027,2,1)<=EDATE('Model inputs'!Q23,'Model inputs'!Q20-1*1))),'Model inputs'!H43,"")),IF(IF(IF(AND('Model inputs'!Q23<=DATE(2027,3,1),DATE(2027,3,1)<=EDATE('Model inputs'!Q23,'Model inputs'!Q20-1*1))="",FALSE,AND('Model inputs'!Q23<=DATE(2027,3,1),DATE(2027,3,1)<=EDATE('Model inputs'!Q23,'Model inputs'!Q20-1*1))),'Model inputs'!I43,"")="",0,IF(IF(AND('Model inputs'!Q23<=DATE(2027,3,1),DATE(2027,3,1)<=EDATE('Model inputs'!Q23,'Model inputs'!Q20-1*1))="",FALSE,AND('Model inputs'!Q23<=DATE(2027,3,1),DATE(2027,3,1)<=EDATE('Model inputs'!Q23,'Model inputs'!Q20-1*1))),'Model inputs'!I43,"")),IF(IF(IF(AND('Model inputs'!Q23<=DATE(2027,4,1),DATE(2027,4,1)<=EDATE('Model inputs'!Q23,'Model inputs'!Q20-1*1))="",FALSE,AND('Model inputs'!Q23<=DATE(2027,4,1),DATE(2027,4,1)<=EDATE('Model inputs'!Q23,'Model inputs'!Q20-1*1))),'Model inputs'!J43,"")="",0,IF(IF(AND('Model inputs'!Q23<=DATE(2027,4,1),DATE(2027,4,1)<=EDATE('Model inputs'!Q23,'Model inputs'!Q20-1*1))="",FALSE,AND('Model inputs'!Q23<=DATE(2027,4,1),DATE(2027,4,1)<=EDATE('Model inputs'!Q23,'Model inputs'!Q20-1*1))),'Model inputs'!J43,"")),IF(IF(IF(AND('Model inputs'!Q23<=DATE(2027,5,1),DATE(2027,5,1)<=EDATE('Model inputs'!Q23,'Model inputs'!Q20-1*1))="",FALSE,AND('Model inputs'!Q23<=DATE(2027,5,1),DATE(2027,5,1)<=EDATE('Model inputs'!Q23,'Model inputs'!Q20-1*1))),'Model inputs'!K43,"")="",0,IF(IF(AND('Model inputs'!Q23<=DATE(2027,5,1),DATE(2027,5,1)<=EDATE('Model inputs'!Q23,'Model inputs'!Q20-1*1))="",FALSE,AND('Model inputs'!Q23<=DATE(2027,5,1),DATE(2027,5,1)<=EDATE('Model inputs'!Q23,'Model inputs'!Q20-1*1))),'Model inputs'!K43,"")),IF(IF(IF(AND('Model inputs'!Q23<=DATE(2027,6,1),DATE(2027,6,1)<=EDATE('Model inputs'!Q23,'Model inputs'!Q20-1*1))="",FALSE,AND('Model inputs'!Q23<=DATE(2027,6,1),DATE(2027,6,1)<=EDATE('Model inputs'!Q23,'Model inputs'!Q20-1*1))),'Model inputs'!L43,"")="",0,IF(IF(AND('Model inputs'!Q23<=DATE(2027,6,1),DATE(2027,6,1)<=EDATE('Model inputs'!Q23,'Model inputs'!Q20-1*1))="",FALSE,AND('Model inputs'!Q23<=DATE(2027,6,1),DATE(2027,6,1)<=EDATE('Model inputs'!Q23,'Model inputs'!Q20-1*1))),'Model inputs'!L43,"")),IF(IF(IF(AND('Model inputs'!Q23<=DATE(2027,7,1),DATE(2027,7,1)<=EDATE('Model inputs'!Q23,'Model inputs'!Q20-1*1))="",FALSE,AND('Model inputs'!Q23<=DATE(2027,7,1),DATE(2027,7,1)<=EDATE('Model inputs'!Q23,'Model inputs'!Q20-1*1))),'Model inputs'!M43,"")="",0,IF(IF(AND('Model inputs'!Q23<=DATE(2027,7,1),DATE(2027,7,1)<=EDATE('Model inputs'!Q23,'Model inputs'!Q20-1*1))="",FALSE,AND('Model inputs'!Q23<=DATE(2027,7,1),DATE(2027,7,1)<=EDATE('Model inputs'!Q23,'Model inputs'!Q20-1*1))),'Model inputs'!M43,"")),IF(IF(IF(AND('Model inputs'!Q23<=DATE(2027,8,1),DATE(2027,8,1)<=EDATE('Model inputs'!Q23,'Model inputs'!Q20-1*1))="",FALSE,AND('Model inputs'!Q23<=DATE(2027,8,1),DATE(2027,8,1)<=EDATE('Model inputs'!Q23,'Model inputs'!Q20-1*1))),'Model inputs'!N43,"")="",0,IF(IF(AND('Model inputs'!Q23<=DATE(2027,8,1),DATE(2027,8,1)<=EDATE('Model inputs'!Q23,'Model inputs'!Q20-1*1))="",FALSE,AND('Model inputs'!Q23<=DATE(2027,8,1),DATE(2027,8,1)<=EDATE('Model inputs'!Q23,'Model inputs'!Q20-1*1))),'Model inputs'!N43,"")),IF(IF(IF(AND('Model inputs'!Q23<=DATE(2027,9,1),DATE(2027,9,1)<=EDATE('Model inputs'!Q23,'Model inputs'!Q20-1*1))="",FALSE,AND('Model inputs'!Q23<=DATE(2027,9,1),DATE(2027,9,1)<=EDATE('Model inputs'!Q23,'Model inputs'!Q20-1*1))),'Model inputs'!O43,"")="",0,IF(IF(AND('Model inputs'!Q23<=DATE(2027,9,1),DATE(2027,9,1)<=EDATE('Model inputs'!Q23,'Model inputs'!Q20-1*1))="",FALSE,AND('Model inputs'!Q23<=DATE(2027,9,1),DATE(2027,9,1)<=EDATE('Model inputs'!Q23,'Model inputs'!Q20-1*1))),'Model inputs'!O43,"")),IF(IF(IF(AND('Model inputs'!Q23<=DATE(2027,10,1),DATE(2027,10,1)<=EDATE('Model inputs'!Q23,'Model inputs'!Q20-1*1))="",FALSE,AND('Model inputs'!Q23<=DATE(2027,10,1),DATE(2027,10,1)<=EDATE('Model inputs'!Q23,'Model inputs'!Q20-1*1))),'Model inputs'!P43,"")="",0,IF(IF(AND('Model inputs'!Q23<=DATE(2027,10,1),DATE(2027,10,1)<=EDATE('Model inputs'!Q23,'Model inputs'!Q20-1*1))="",FALSE,AND('Model inputs'!Q23<=DATE(2027,10,1),DATE(2027,10,1)<=EDATE('Model inputs'!Q23,'Model inputs'!Q20-1*1))),'Model inputs'!P43,"")),IF(IF(IF(AND('Model inputs'!Q23<=DATE(2026,9,1),DATE(2026,9,1)<=EDATE('Model inputs'!Q23,'Model inputs'!Q20-1*1))="",FALSE,AND('Model inputs'!Q23<=DATE(2026,9,1),DATE(2026,9,1)<=EDATE('Model inputs'!Q23,'Model inputs'!Q20-1*1))),'Model inputs'!C108,"")="",0,IF(IF(AND('Model inputs'!Q23<=DATE(2026,9,1),DATE(2026,9,1)<=EDATE('Model inputs'!Q23,'Model inputs'!Q20-1*1))="",FALSE,AND('Model inputs'!Q23<=DATE(2026,9,1),DATE(2026,9,1)<=EDATE('Model inputs'!Q23,'Model inputs'!Q20-1*1))),'Model inputs'!C108,""))) -> 96930.5
A7: 12-month net profit | B7: ='12-month forecast summary'!B5-'12-month forecast summary'!B6 -> 13487.8 | C7: ='12-month forecast summary'!C5-'12-month forecast summary'!C6 -> 539.5
A8: Forecast ending cash | B8: =IF(SUM(IF(IF('Model inputs'!B161="",0,1)="",0,IF('Model inputs'!B161="",0,1)),IF(IF('Model inputs'!B162="",0,1)="",0,IF('Model inputs'!B162="",0,1)),IF(IF('Model inputs'!B163="",0,1)="",0,IF('Model inputs'!B163="",0,1)),IF(IF('Model inputs'!B164="",0,1)="",0,IF('Model inputs'!B164="",0,1)),IF(IF('Model inputs'!B165="",0,1)="",0,IF('Model inputs'!B165="",0,1)),IF(IF('Model inputs'!B166="",0,1)="",0,IF('Model inputs'!B166="",0,1)),IF(IF('Model inputs'!B167="",0,1)="",0,IF('Model inputs'!B167="",0,1)),IF(IF('Model inputs'!B168="",0,1)="",0,IF('Model inputs'!B168="",0,1)),IF(IF('Model inputs'!B169="",0,1)="",0,IF('Model inputs'!B169="",0,1)),IF(IF('Model inputs'!B170="",0,1)="",0,IF('Model inputs'!B170="",0,1)),IF(IF('Model inputs'!B171="",0,1)="",0,IF('Model inputs'!B171="",0,1)),IF(IF('Model inputs'!B172="",0,1)="",0,IF('Model inputs'!B172="",0,1)),IF(IF('Model inputs'!B173="",0,1)="",0,IF('Model inputs'!B173="",0,1)),IF(IF('Model inputs'!B174="",0,1)="",0,IF('Model inputs'!B174="",0,1)))=0,"",SUM('Model inputs'!B161,'Model inputs'!B162,'Model inputs'!B163,'Model inputs'!B164,'Model inputs'!B165,'Model inputs'!B166,'Model inputs'!B167,'Model inputs'!B168,'Model inputs'!B169,'Model inputs'!B170,'Model inputs'!B171,'Model inputs'!B172,'Model inputs'!B173,'Model inputs'!B174)) -> 13487.8 | C8: =IF(SUM(IF(IF('Model inputs'!B175="",0,1)="",0,IF('Model inputs'!B175="",0,1)),IF(IF('Model inputs'!B176="",0,1)="",0,IF('Model inputs'!B176="",0,1)),IF(IF('Model inputs'!B177="",0,1)="",0,IF('Model inputs'!B177="",0,1)),IF(IF('Model inputs'!B178="",0,1)="",0,IF('Model inputs'!B178="",0,1)),IF(IF('Model inputs'!B179="",0,1)="",0,IF('Model inputs'!B179="",0,1)),IF(IF('Model inputs'!B180="",0,1)="",0,IF('Model inputs'!B180="",0,1)),IF(IF('Model inputs'!B181="",0,1)="",0,IF('Model inputs'!B181="",0,1)),IF(IF('Model inputs'!B182="",0,1)="",0,IF('Model inputs'!B182="",0,1)),IF(IF('Model inputs'!B183="",0,1)="",0,IF('Model inputs'!B183="",0,1)),IF(IF('Model inputs'!B184="",0,1)="",0,IF('Model inputs'!B184="",0,1)),IF(IF('Model inputs'!B185="",0,1)="",0,IF('Model inputs'!B185="",0,1)),IF(IF('Model inputs'!B186="",0,1)="",0,IF('Model inputs'!B186="",0,1)),IF(IF('Model inputs'!B187="",0,1)="",0,IF('Model inputs'!B187="",0,1)),IF(IF('Model inputs'!B188="",0,1)="",0,IF('Model inputs'!B188="",0,1)))=0,"",SUM('Model inputs'!B175,'Model inputs'!B176,'Model inputs'!B177,'Model inputs'!B178,'Model inputs'!B179,'Model inputs'!B180,'Model inputs'!B181,'Model inputs'!B182,'Model inputs'!B183,'Model inputs'!B184,'Model inputs'!B185,'Model inputs'!B186,'Model inputs'!B187,'Model inputs'!B188)) -> 539.5
A9: Minimum opening funding required | B9: =IF(SUM(IF(IF('Model inputs'!B189="",0,1)="",0,IF('Model inputs'!B189="",0,1)),IF(IF('Model inputs'!B190="",0,1)="",0,IF('Model inputs'!B190="",0,1)),IF(IF('Model inputs'!B191="",0,1)="",0,IF('Model inputs'!B191="",0,1)),IF(IF('Model inputs'!B192="",0,1)="",0,IF('Model inputs'!B192="",0,1)),IF(IF('Model inputs'!B193="",0,1)="",0,IF('Model inputs'!B193="",0,1)),IF(IF('Model inputs'!B194="",0,1)="",0,IF('Model inputs'!B194="",0,1)),IF(IF('Model inputs'!B195="",0,1)="",0,IF('Model inputs'!B195="",0,1)),IF(IF('Model inputs'!B196="",0,1)="",0,IF('Model inputs'!B196="",0,1)),IF(IF('Model inputs'!B197="",0,1)="",0,IF('Model inputs'!B197="",0,1)),IF(IF('Model inputs'!B198="",0,1)="",0,IF('Model inputs'!B198="",0,1)),IF(IF('Model inputs'!B199="",0,1)="",0,IF('Model inputs'!B199="",0,1)),IF(IF('Model inputs'!B200="",0,1)="",0,IF('Model inputs'!B200="",0,1)),IF(IF('Model inputs'!B201="",0,1)="",0,IF('Model inputs'!B201="",0,1)),IF(IF('Model inputs'!B202="",0,1)="",0,IF('Model inputs'!B202="",0,1)))=0,"",SUM('Model inputs'!B189,'Model inputs'!B190,'Model inputs'!B191,'Model inputs'!B192,'Model inputs'!B193,'Model inputs'!B194,'Model inputs'!B195,'Model inputs'!B196,'Model inputs'!B197,'Model inputs'!B198,'Model inputs'!B199,'Model inputs'!B200,'Model inputs'!B201,'Model inputs'!B202)) -> 45.7 | C9: =IF(SUM(IF(IF('Model inputs'!B203="",0,1)="",0,IF('Model inputs'!B203="",0,1)),IF(IF('Model inputs'!B204="",0,1)="",0,IF('Model inputs'!B204="",0,1)),IF(IF('Model inputs'!B205="",0,1)="",0,IF('Model inputs'!B205="",0,1)),IF(IF('Model inputs'!B206="",0,1)="",0,IF('Model inputs'!B206="",0,1)),IF(IF('Model inputs'!B207="",0,1)="",0,IF('Model inputs'!B207="",0,1)),IF(IF('Model inputs'!B208="",0,1)="",0,IF('Model inputs'!B208="",0,1)),IF(IF('Model inputs'!B209="",0,1)="",0,IF('Model inputs'!B209="",0,1)),IF(IF('Model inputs'!B210="",0,1)="",0,IF('Model inputs'!B210="",0,1)),IF(IF('Model inputs'!B211="",0,1)="",0,IF('Model inputs'!B211="",0,1)),IF(IF('Model inputs'!B212="",0,1)="",0,IF('Model inputs'!B212="",0,1)),IF(IF('Model inputs'!B213="",0,1)="",0,IF('Model inputs'!B213="",0,1)),IF(IF('Model inputs'!B214="",0,1)="",0,IF('Model inputs'!B214="",0,1)),IF(IF('Model inputs'!B215="",0,1)="",0,IF('Model inputs'!B215="",0,1)),IF(IF('Model inputs'!B216="",0,1)="",0,IF('Model inputs'!B216="",0,1)))=0,"",SUM('Model inputs'!B203,'Model inputs'!B204,'Model inputs'!B205,'Model inputs'!B206,'Model inputs'!B207,'Model inputs'!B208,'Model inputs'!B209,'Model inputs'!B210,'Model inputs'!B211,'Model inputs'!B212,'Model inputs'!B213,'Model inputs'!B214,'Model inputs'!B215,'Model inputs'!B216)) -> 4759.9773

Sheet Monthly revenue cost and runway
A1: Monthly revenue cost and runway
A2: Susanoo — 12-Month Forecast · Susanoo — Base
A4: Variable / dimension | B4: 2026-11 | C4: 2026-12 | D4: 2027-01 | E4: 2027-02 | F4: 2027-03 | G4: 2027-04 | H4: 2027-05 | I4: 2027-06 | J4: 2027-07 | K4: 2027-08 | L4: 2027-09 | M4: 2027-10
A5: Forecast subscription revenue | B5: =SUM('Customers revenue and run costs'!B11,'Customers revenue and run costs'!B12,'Customers revenue and run costs'!B13) -> 158 | C5: =SUM('Customers revenue and run costs'!C11,'Customers revenue and run costs'!C12,'Customers revenue and run costs'!C13) -> 430.90909 | D5: =SUM('Customers revenue and run costs'!D11,'Customers revenue and run costs'!D12,'Customers revenue and run costs'!D13) -> 703.81818 | E5: =SUM('Customers revenue and run costs'!E11,'Customers revenue and run costs'!E12,'Customers revenue and run costs'!E13) -> 976.72727 | F5: =SUM('Customers revenue and run costs'!F11,'Customers revenue and run costs'!F12,'Customers revenue and run costs'!F13) -> 1249.6364 | G5: =SUM('Customers revenue and run costs'!G11,'Customers revenue and run costs'!G12,'Customers revenue and run costs'!G13) -> 1522.5455 | H5: =SUM('Customers revenue and run costs'!H11,'Customers revenue and run costs'!H12,'Customers revenue and run costs'!H13) -> 1795.4545 | I5: =SUM('Customers revenue and run costs'!I11,'Customers revenue and run costs'!I12,'Customers revenue and run costs'!I13) -> 2068.3636 | ... M5: =SUM('Customers revenue and run costs'!M11,'Customers revenue and run costs'!M12,'Customers revenue and run costs'!M13) -> 4660
A6: Team revenue | B6: =IF('Customers revenue and run costs'!B13="","",'Customers revenue and run costs'!B13) -> 158 | C6: =IF('Customers revenue and run costs'!C13="","",'Customers revenue and run costs'!C13) -> 430.90909 | D6: =IF('Customers revenue and run costs'!D13="","",'Customers revenue and run costs'!D13) -> 703.81818 | E6: =IF('Customers revenue and run costs'!E13="","",'Customers revenue and run costs'!E13) -> 976.72727 | F6: =IF('Customers revenue and run costs'!F13="","",'Customers revenue and run costs'!F13) -> 1249.6364 | G6: =IF('Customers revenue and run costs'!G13="","",'Customers revenue and run costs'!G13) -> 1522.5455 | H6: =IF('Customers revenue and run costs'!H13="","",'Customers revenue and run costs'!H13) -> 1795.4545 | I6: =IF('Customers revenue and run costs'!I13="","",'Customers revenue and run costs'!I13) -> 2068.3636 | ... M6: =IF('Customers revenue and run costs'!M13="","",'Customers revenue and run costs'!M13) -> 3160
A7: Enterprise revenue | B7: =IF('Customers revenue and run costs'!B11="","",'Customers revenue and run costs'!B11) -> 0 | C7: =IF('Customers revenue and run costs'!C11="","",'Customers revenue and run costs'!C11) -> 0 | D7: =IF('Customers revenue and run costs'!D11="","",'Customers revenue and run costs'!D11) -> 0 | E7: =IF('Customers revenue and run costs'!E11="","",'Customers revenue and run costs'!E11) -> 0 | F7: =IF('Customers revenue and run costs'!F11="","",'Customers revenue and run costs'!F11) -> 0 | G7: =IF('Customers revenue and run costs'!G11="","",'Customers revenue and run costs'!G11) -> 0 | H7: =IF('Customers revenue and run costs'!H11="","",'Customers revenue and run costs'!H11) -> 0 | I7: =IF('Customers revenue and run costs'!I11="","",'Customers revenue and run costs'!I11) -> 0 | ... M7: =IF('Customers revenue and run costs'!M11="","",'Customers revenue and run costs'!M11) -> 1500
A8: Team run costs | B8: =IF('Customers revenue and run costs'!B17="","",'Customers revenue and run costs'!B17) -> 37.2 | C8: =IF('Customers revenue and run costs'!C17="","",'Customers revenue and run costs'!C17) -> 101.45455 | D8: =IF('Customers revenue and run costs'!D17="","",'Customers revenue and run costs'!D17) -> 165.70909 | E8: =IF('Customers revenue and run costs'!E17="","",'Customers revenue and run costs'!E17) -> 229.96364 | F8: =IF('Customers revenue and run costs'!F17="","",'Customers revenue and run costs'!F17) -> 294.21818 | G8: =IF('Customers revenue and run costs'!G17="","",'Customers revenue and run costs'!G17) -> 358.47273 | H8: =IF('Customers revenue and run costs'!H17="","",'Customers revenue and run costs'!H17) -> 422.72727 | I8: =IF('Customers revenue and run costs'!I17="","",'Customers revenue and run costs'!I17) -> 486.98182 | ... M8: =IF('Customers revenue and run costs'!M17="","",'Customers revenue and run costs'!M17) -> 744
A9: Enterprise run costs | B9: =IF('Customers revenue and run costs'!B15="","",'Customers revenue and run costs'!B15) -> 0 | C9: =IF('Customers revenue and run costs'!C15="","",'Customers revenue and run costs'!C15) -> 0 | D9: =IF('Customers revenue and run costs'!D15="","",'Customers revenue and run costs'!D15) -> 0 | E9: =IF('Customers revenue and run costs'!E15="","",'Customers revenue and run costs'!E15) -> 0 | F9: =IF('Customers revenue and run costs'!F15="","",'Customers revenue and run costs'!F15) -> 0 | G9: =IF('Customers revenue and run costs'!G15="","",'Customers revenue and run costs'!G15) -> 0 | H9: =IF('Customers revenue and run costs'!H15="","",'Customers revenue and run costs'!H15) -> 0 | I9: =IF('Customers revenue and run costs'!I15="","",'Customers revenue and run costs'!I15) -> 0 | ... M9: =IF('Customers revenue and run costs'!M15="","",'Customers revenue and run costs'!M15) -> 155
A10: Free run costs | B10: =IF('Customers revenue and run costs'!B16="","",'Customers revenue and run costs'!B16) -> 77.5 | C10: =IF('Customers revenue and run costs'!C16="","",'Customers revenue and run costs'!C16) -> 155 | D10: =IF('Customers revenue and run costs'!D16="","",'Customers revenue and run costs'!D16) -> 232.5 | E10: =IF('Customers revenue and run costs'!E16="","",'Customers revenue and run costs'!E16) -> 310 | F10: =IF('Customers revenue and run costs'!F16="","",'Customers revenue and run costs'!F16) -> 387.5 | G10: =IF('Customers revenue and run costs'!G16="","",'Customers revenue and run costs'!G16) -> 465 | H10: =IF('Customers revenue and run costs'!H16="","",'Customers revenue and run costs'!H16) -> 542.5 | I10: =IF('Customers revenue and run costs'!I16="","",'Customers revenue and run costs'!I16) -> 620 | ... M10: =IF('Customers revenue and run costs'!M16="","",'Customers revenue and run costs'!M16) -> 930
A11: Forecast run costs | B11: =SUM('Customers revenue and run costs'!B15,'Customers revenue and run costs'!B16,'Customers revenue and run costs'!B17) -> 114.7 | C11: =SUM('Customers revenue and run costs'!C15,'Customers revenue and run costs'!C16,'Customers revenue and run costs'!C17) -> 256.45455 | D11: =SUM('Customers revenue and run costs'!D15,'Customers revenue and run costs'!D16,'Customers revenue and run costs'!D17) -> 398.20909 | E11: =SUM('Customers revenue and run costs'!E15,'Customers revenue and run costs'!E16,'Customers revenue and run costs'!E17) -> 539.96364 | F11: =SUM('Customers revenue and run costs'!F15,'Customers revenue and run costs'!F16,'Customers revenue and run costs'!F17) -> 681.71818 | G11: =SUM('Customers revenue and run costs'!G15,'Customers revenue and run costs'!G16,'Customers revenue and run costs'!G17) -> 823.47273 | H11: =SUM('Customers revenue and run costs'!H15,'Customers revenue and run costs'!H16,'Customers revenue and run costs'!H17) -> 965.22727 | I11: =SUM('Customers revenue and run costs'!I15,'Customers revenue and run costs'!I16,'Customers revenue and run costs'!I17) -> 1106.9818 | ... M11: =SUM('Customers revenue and run costs'!M15,'Customers revenue and run costs'!M16,'Customers revenue and run costs'!M17) -> 1829
A12: Forecast gross profit | B12: ='Monthly revenue cost and runway'!B5-'Monthly revenue cost and runway'!B11 -> 43.3 | C12: ='Monthly revenue cost and runway'!C5-'Monthly revenue cost and runway'!C11 -> 174.45455 | D12: ='Monthly revenue cost and runway'!D5-'Monthly revenue cost and runway'!D11 -> 305.60909 | E12: ='Monthly revenue cost and runway'!E5-'Monthly revenue cost and runway'!E11 -> 436.76364 | F12: ='Monthly revenue cost and runway'!F5-'Monthly revenue cost and runway'!F11 -> 567.91818 | G12: ='Monthly revenue cost and runway'!G5-'Monthly revenue cost and runway'!G11 -> 699.07273 | H12: ='Monthly revenue cost and runway'!H5-'Monthly revenue cost and runway'!H11 -> 830.22727 | I12: ='Monthly revenue cost and runway'!I5-'Monthly revenue cost and runway'!I11 -> 961.38182 | ... M12: ='Monthly revenue cost and runway'!M5-'Monthly revenue cost and runway'!M11 -> 2831
A13: Forecast gross margin | B13: =IFERROR('Monthly revenue cost and runway'!B12/'Monthly revenue cost and runway'!B5,"") -> 0.27405063 | C13: =IFERROR('Monthly revenue cost and runway'!C12/'Monthly revenue cost and runway'!C5,"") -> 0.40485232 | D13: =IFERROR('Monthly revenue cost and runway'!D12/'Monthly revenue cost and runway'!D5,"") -> 0.43421596 | E13: =IFERROR('Monthly revenue cost and runway'!E12/'Monthly revenue cost and runway'!E5,"") -> 0.44717051 | F13: =IFERROR('Monthly revenue cost and runway'!F12/'Monthly revenue cost and runway'!F5,"") -> 0.45446675 | G13: =IFERROR('Monthly revenue cost and runway'!G12/'Monthly revenue cost and runway'!G5,"") -> 0.45914736 | H13: =IFERROR('Monthly revenue cost and runway'!H12/'Monthly revenue cost and runway'!H5,"") -> 0.46240506 | I13: =IFERROR('Monthly revenue cost and runway'!I12/'Monthly revenue cost and runway'!I5,"") -> 0.46480309 | ... M13: =IFERROR('Monthly revenue cost and runway'!M12/'Monthly revenue cost and runway'!M5,"") -> 0.60751073
A14: Forecast fixed costs | B14: =IF('Model inputs'!B15="","",'Model inputs'!B15) -> 89 | C14: =IF('Model inputs'!B15="","",'Model inputs'!B15) -> 89 | D14: =IF('Model inputs'!B15="","",'Model inputs'!B15) -> 89 | E14: =IF('Model inputs'!B15="","",'Model inputs'!B15) -> 89 | F14: =IF('Model inputs'!B15="","",'Model inputs'!B15) -> 89 | G14: =IF('Model inputs'!B15="","",'Model inputs'!B15) -> 89 | H14: =IF('Model inputs'!B15="","",'Model inputs'!B15) -> 89 | I14: =IF('Model inputs'!B15="","",'Model inputs'!B15) -> 89 | J14: =IF('Model inputs'!B15="","",'Model inputs'!B15) -> 89 | K14: =IF('Model inputs'!B15="","",'Model inputs'!B15) -> 89 | L14: =IF('Model inputs'!B15="","",'Model inputs'!B15) -> 89 | M14: =IF('Model inputs'!B15="","",'Model inputs'!B15) -> 89
A15: Forecast salaries | B15: =SUM('Monthly headcount and payroll'!B10,'Monthly headcount and payroll'!B11,'Monthly headcount and payroll'!B12) -> 0 | C15: =SUM('Monthly headcount and payroll'!C10,'Monthly headcount and payroll'!C11,'Monthly headcount and payroll'!C12) -> 0 | D15: =SUM('Monthly headcount and payroll'!D10,'Monthly headcount and payroll'!D11,'Monthly headcount and payroll'!D12) -> 0 | E15: =SUM('Monthly headcount and payroll'!E10,'Monthly headcount and payroll'!E11,'Monthly headcount and payroll'!E12) -> 0 | F15: =SUM('Monthly headcount and payroll'!F10,'Monthly headcount and payroll'!F11,'Monthly headcount and payroll'!F12) -> 0 | G15: =SUM('Monthly headcount and payroll'!G10,'Monthly headcount and payroll'!G11,'Monthly headcount and payroll'!G12) -> 0 | H15: =SUM('Monthly headcount and payroll'!H10,'Monthly headcount and payroll'!H11,'Monthly headcount and payroll'!H12) -> 0 | I15: =SUM('Monthly headcount and payroll'!I10,'Monthly headcount and payroll'!I11,'Monthly headcount and payroll'!I12) -> 0 | ... M15: =SUM('Monthly headcount and payroll'!M10,'Monthly headcount and payroll'!M11,'Monthly headcount and payroll'!M12) -> 0
A16: Total forecast costs | B16: ='Monthly revenue cost and runway'!B11+'Monthly revenue cost and runway'!B14+'Monthly revenue cost and runway'!B15 -> 203.7 | C16: ='Monthly revenue cost and runway'!C11+'Monthly revenue cost and runway'!C14+'Monthly revenue cost and runway'!C15 -> 345.45455 | D16: ='Monthly revenue cost and runway'!D11+'Monthly revenue cost and runway'!D14+'Monthly revenue cost and runway'!D15 -> 487.20909 | E16: ='Monthly revenue cost and runway'!E11+'Monthly revenue cost and runway'!E14+'Monthly revenue cost and runway'!E15 -> 628.96364 | F16: ='Monthly revenue cost and runway'!F11+'Monthly revenue cost and runway'!F14+'Monthly revenue cost and runway'!F15 -> 770.71818 | G16: ='Monthly revenue cost and runway'!G11+'Monthly revenue cost and runway'!G14+'Monthly revenue cost and runway'!G15 -> 912.47273 | H16: ='Monthly revenue cost and runway'!H11+'Monthly revenue cost and runway'!H14+'Monthly revenue cost and runway'!H15 -> 1054.2273 | I16: ='Monthly revenue cost and runway'!I11+'Monthly revenue cost and runway'!I14+'Monthly revenue cost and runway'!I15 -> 1195.9818 | ... M16: ='Monthly revenue cost and runway'!M11+'Monthly revenue cost and runway'!M14+'Monthly revenue cost and runway'!M15 -> 1918
A17: Net forecast profit | B17: ='Monthly revenue cost and runway'!B5-'Monthly revenue cost and runway'!B16 -> -45.7 | C17: ='Monthly revenue cost and runway'!C5-'Monthly revenue cost and runway'!C16 -> 85.454545 | D17: ='Monthly revenue cost and runway'!D5-'Monthly revenue cost and runway'!D16 -> 216.60909 | E17: ='Monthly revenue cost and runway'!E5-'Monthly revenue cost and runway'!E16 -> 347.76364 | F17: ='Monthly revenue cost and runway'!F5-'Monthly revenue cost and runway'!F16 -> 478.91818 | G17: ='Monthly revenue cost and runway'!G5-'Monthly revenue cost and runway'!G16 -> 610.07273 | H17: ='Monthly revenue cost and runway'!H5-'Monthly revenue cost and runway'!H16 -> 741.22727 | I17: ='Monthly revenue cost and runway'!I5-'Monthly revenue cost and runway'!I16 -> 872.38182 | ... M17: ='Monthly revenue cost and runway'!M5-'Monthly revenue cost and runway'!M16 -> 2742
A18: Net monthly burn | B18: =MAX(-'Monthly revenue cost and runway'!B17,0) -> 45.7 | C18: =MAX(-'Monthly revenue cost and runway'!C17,0) -> 0 | D18: =MAX(-'Monthly revenue cost and runway'!D17,0) -> 0 | E18: =MAX(-'Monthly revenue cost and runway'!E17,0) -> 0 | F18: =MAX(-'Monthly revenue cost and runway'!F17,0) -> 0 | G18: =MAX(-'Monthly revenue cost and runway'!G17,0) -> 0 | H18: =MAX(-'Monthly revenue cost and runway'!H17,0) -> 0 | I18: =MAX(-'Monthly revenue cost and runway'!I17,0) -> 0 | ... M18: =MAX(-'Monthly revenue cost and runway'!M17,0) -> 0
A19: Forecast cash balance | B19: =IF(IF(IF(IF(ISERROR('Customers revenue and run costs'!B5=1),'Customers revenue and run costs'!B5=1,IF('Customers revenue and run costs'!B5="","",'Customers revenue and run costs'!B5=1))="",FALSE,IF(ISERROR('Customers revenue and run costs'!B5=1),'Customers revenue and run costs'!B5=1,IF('Customers revenue and run costs'!B5="","",'Customers revenue and run costs'!B5=1))),IF('Model inputs'!B40="","",'Model inputs'!B40),IF('Model inputs'!D16="","",'Model inputs'!D16))="",0,IF(IF(IF(ISERROR('Customers revenue and run costs'!B5=1),'Customers revenue and run costs'!B5=1,IF('Customers revenue and run costs'!B5="","",'Customers revenue and run costs'!B5=1))="",FALSE,IF(ISERROR('Customers revenue and run costs'!B5=1),'Customers revenue and run costs'!B5=1,IF('Customers revenue and run costs'!B5="","",'Customers revenue and run costs'!B5=1))),IF('Model inputs'!B40="","",'Model inputs'!B40),IF('Model inputs'!D16="","",'Model inputs'!D16)))+'Monthly revenue cost and runway'!B17 -> -45.7 | C19: =IF(IF(IF(IF(ISERROR('Customers revenue and run costs'!C5=1),'Customers revenue and run costs'!C5=1,IF('Customers revenue and run costs'!C5="","",'Customers revenue and run costs'!C5=1))="",FALSE,IF(ISERROR('Customers revenue and run costs'!C5=1),'Customers revenue and run costs'!C5=1,IF('Customers revenue and run costs'!C5="","",'Customers revenue and run costs'!C5=1))),IF('Model inputs'!B40="","",'Model inputs'!B40),IF('Monthly revenue cost and runway'!B19="","",'Monthly revenue cost and runway'!B19))="",0,IF(IF(IF(ISERROR('Customers revenue and run costs'!C5=1),'Customers revenue and run costs'!C5=1,IF('Customers revenue and run costs'!C5="","",'Customers revenue and run costs'!C5=1))="",FALSE,IF(ISERROR('Customers revenue and run costs'!C5=1),'Customers revenue and run costs'!C5=1,IF('Customers revenue and run costs'!C5="","",'Customers revenue and run costs'!C5=1))),IF('Model inputs'!B40="","",'Model inputs'!B40),IF('Monthly revenue cost and runway'!B19="","",'Monthly revenue cost and runway'!B19)))+'Monthly revenue cost and runway'!C17 -> 39.754545 | D19: =IF(IF(IF(IF(ISERROR('Customers revenue and run costs'!D5=1),'Customers revenue and run costs'!D5=1,IF('Customers revenue and run costs'!D5="","",'Customers revenue and run costs'!D5=1))="",FALSE,IF(ISERROR('Customers revenue and run costs'!D5=1),'Customers revenue and run costs'!D5=1,IF('Customers revenue and run costs'!D5="","",'Customers revenue and run costs'!D5=1))),IF('Model inputs'!B40="","",'Model inputs'!B40),IF('Monthly revenue cost and runway'!C19="","",'Monthly revenue cost and runway'!C19))="",0,IF(IF(IF(ISERROR('Customers revenue and run costs'!D5=1),'Customers revenue and run costs'!D5=1,IF('Customers revenue and run costs'!D5="","",'Customers revenue and run costs'!D5=1))="",FALSE,IF(ISERROR('Customers revenue and run costs'!D5=1),'Customers revenue and run costs'!D5=1,IF('Customers revenue and run costs'!D5="","",'Customers revenue and run costs'!D5=1))),IF('Model inputs'!B40="","",'Model inputs'!B40),IF('Monthly revenue cost and runway'!C19="","",'Monthly revenue cost and runway'!C19)))+'Monthly revenue cost and runway'!D17 -> 256.36364 | E19: =IF(IF(IF(IF(ISERROR('Customers revenue and run costs'!E5=1),'Customers revenue and run costs'!E5=1,IF('Customers revenue and run costs'!E5="","",'Customers revenue and run costs'!E5=1))="",FALSE,IF(ISERROR('Customers revenue and run costs'!E5=1),'Customers revenue and run costs'!E5=1,IF('Customers revenue and run costs'!E5="","",'Customers revenue and run costs'!E5=1))),IF('Model inputs'!B40="","",'Model inputs'!B40),IF('Monthly revenue cost and runway'!D19="","",'Monthly revenue cost and runway'!D19))="",0,IF(IF(IF(ISERROR('Customers revenue and run costs'!E5=1),'Customers revenue and run costs'!E5=1,IF('Customers revenue and run costs'!E5="","",'Customers revenue and run costs'!E5=1))="",FALSE,IF(ISERROR('Customers revenue and run costs'!E5=1),'Customers revenue and run costs'!E5=1,IF('Customers revenue and run costs'!E5="","",'Customers revenue and run costs'!E5=1))),IF('Model inputs'!B40="","",'Model inputs'!B40),IF('Monthly revenue cost and runway'!D19="","",'Monthly revenue cost and runway'!D19)))+'Monthly revenue cost and runway'!E17 -> 604.12727 | F19: =IF(IF(IF(IF(ISERROR('Customers revenue and run costs'!F5=1),'Customers revenue and run costs'!F5=1,IF('Customers revenue and run costs'!F5="","",'Customers revenue and run costs'!F5=1))="",FALSE,IF(ISERROR('Customers revenue and run costs'!F5=1),'Customers revenue and run costs'!F5=1,IF('Customers revenue and run costs'!F5="","",'Customers revenue and run costs'!F5=1))),IF('Model inputs'!B40="","",'Model inputs'!B40),IF('Monthly revenue cost and runway'!E19="","",'Monthly revenue cost and runway'!E19))="",0,IF(IF(IF(ISERROR('Customers revenue and run costs'!F5=1),'Customers revenue and run costs'!F5=1,IF('Customers revenue and run costs'!F5="","",'Customers revenue and run costs'!F5=1))="",FALSE,IF(ISERROR('Customers revenue and run costs'!F5=1),'Customers revenue and run costs'!F5=1,IF('Customers revenue and run costs'!F5="","",'Customers revenue and run costs'!F5=1))),IF('Model inputs'!B40="","",'Model inputs'!B40),IF('Monthly revenue cost and runway'!E19="","",'Monthly revenue cost and runway'!E19)))+'Monthly revenue cost and runway'!F17 -> 1083.0455 | G19: =IF(IF(IF(IF(ISERROR('Customers revenue and run costs'!G5=1),'Customers revenue and run costs'!G5=1,IF('Customers revenue and run costs'!G5="","",'Customers revenue and run costs'!G5=1))="",FALSE,IF(ISERROR('Customers revenue and run costs'!G5=1),'Customers revenue and run costs'!G5=1,IF('Customers revenue and run costs'!G5="","",'Customers revenue and run costs'!G5=1))),IF('Model inputs'!B40="","",'Model inputs'!B40),IF('Monthly revenue cost and runway'!F19="","",'Monthly revenue cost and runway'!F19))="",0,IF(IF(IF(ISERROR('Customers revenue and run costs'!G5=1),'Customers revenue and run costs'!G5=1,IF('Customers revenue and run costs'!G5="","",'Customers revenue and run costs'!G5=1))="",FALSE,IF(ISERROR('Customers revenue and run costs'!G5=1),'Customers revenue and run costs'!G5=1,IF('Customers revenue and run costs'!G5="","",'Customers revenue and run costs'!G5=1))),IF('Model inputs'!B40="","",'Model inputs'!B40),IF('Monthly revenue cost and runway'!F19="","",'Monthly revenue cost and runway'!F19)))+'Monthly revenue cost and runway'!G17 -> 1693.1182 | H19: =IF(IF(IF(IF(ISERROR('Customers revenue and run costs'!H5=1),'Customers revenue and run costs'!H5=1,IF('Customers revenue and run costs'!H5="","",'Customers revenue and run costs'!H5=1))="",FALSE,IF(ISERROR('Customers revenue and run costs'!H5=1),'Customers revenue and run costs'!H5=1,IF('Customers revenue and run costs'!H5="","",'Customers revenue and run costs'!H5=1))),IF('Model inputs'!B40="","",'Model inputs'!B40),IF('Monthly revenue cost and runway'!G19="","",'Monthly revenue cost and runway'!G19))="",0,IF(IF(IF(ISERROR('Customers revenue and run costs'!H5=1),'Customers revenue and run costs'!H5=1,IF('Customers revenue and run costs'!H5="","",'Customers revenue and run costs'!H5=1))="",FALSE,IF(ISERROR('Customers revenue and run costs'!H5=1),'Customers revenue and run costs'!H5=1,IF('Customers revenue and run costs'!H5="","",'Customers revenue and run costs'!H5=1))),IF('Model inputs'!B40="","",'Model inputs'!B40),IF('Monthly revenue cost and runway'!G19="","",'Monthly revenue cost and runway'!G19)))+'Monthly revenue cost and runway'!H17 -> 2434.3455 | I19: =IF(IF(IF(IF(ISERROR('Customers revenue and run costs'!I5=1),'Customers revenue and run costs'!I5=1,IF('Customers revenue and run costs'!I5="","",'Customers revenue and run costs'!I5=1))="",FALSE,IF(ISERROR('Customers revenue and run costs'!I5=1),'Customers revenue and run costs'!I5=1,IF('Customers revenue and run costs'!I5="","",'Customers revenue and run costs'!I5=1))),IF('Model inputs'!B40="","",'Model inputs'!B40),IF('Monthly revenue cost and runway'!H19="","",'Monthly revenue cost and runway'!H19))="",0,IF(IF(IF(ISERROR('Customers revenue and run costs'!I5=1),'Customers revenue and run costs'!I5=1,IF('Customers revenue and run costs'!I5="","",'Customers revenue and run costs'!I5=1))="",FALSE,IF(ISERROR('Customers revenue and run costs'!I5=1),'Customers revenue and run costs'!I5=1,IF('Customers revenue and run costs'!I5="","",'Customers revenue and run costs'!I5=1))),IF('Model inputs'!B40="","",'Model inputs'!B40),IF('Monthly revenue cost and runway'!H19="","",'Monthly revenue cost and runway'!H19)))+'Monthly revenue cost and runway'!I17 -> 3306.7273 | J19: =IF(IF(IF(IF(ISERROR('Customers revenue and run costs'!J5=1),'Customers revenue and run costs'!J5=1,IF('Customers revenue and run costs'!J5="","",'Customers revenue and run costs'!J5=1))="",FALSE,IF(ISERROR('Customers revenue and run costs'!J5=1),'Customers revenue and run costs'!J5=1,IF('Customers revenue and run costs'!J5="","",'Customers revenue and run costs'!J5=1))),IF('Model inputs'!B40="","",'Model inputs'!B40),IF('Monthly revenue cost and runway'!I19="","",'Monthly revenue cost and runway'!I19))="",0,IF(IF(IF(ISERROR('Customers revenue and run costs'!J5=1),'Customers revenue and run costs'!J5=1,IF('Customers revenue and run costs'!J5="","",'Customers revenue and run costs'!J5=1))="",FALSE,IF(ISERROR('Customers revenue and run costs'!J5=1),'Customers revenue and run costs'!J5=1,IF('Customers revenue and run costs'!J5="","",'Customers revenue and run costs'!J5=1))),IF('Model inputs'!B40="","",'Model inputs'!B40),IF('Monthly revenue cost and runway'!I19="","",'Monthly revenue cost and runway'!I19)))+'Monthly revenue cost and runway'!J17 -> 5655.2636 | K19: =IF(IF(IF(IF(ISERROR('Customers revenue and run costs'!K5=1),'Customers revenue and run costs'!K5=1,IF('Customers revenue and run costs'!K5="","",'Customers revenue and run costs'!K5=1))="",FALSE,IF(ISERROR('Customers revenue and run costs'!K5=1),'Customers revenue and run costs'!K5=1,IF('Customers revenue and run costs'!K5="","",'Customers revenue and run costs'!K5=1))),IF('Model inputs'!B40="","",'Model inputs'!B40),IF('Monthly revenue cost and runway'!J19="","",'Monthly revenue cost and runway'!J19))="",0,IF(IF(IF(ISERROR('Customers revenue and run costs'!K5=1),'Customers revenue and run costs'!K5=1,IF('Customers revenue and run costs'!K5="","",'Customers revenue and run costs'!K5=1))="",FALSE,IF(ISERROR('Customers revenue and run costs'!K5=1),'Customers revenue and run costs'!K5=1,IF('Customers revenue and run costs'!K5="","",'Customers revenue and run costs'!K5=1))),IF('Model inputs'!B40="","",'Model inputs'!B40),IF('Monthly revenue cost and runway'!J19="","",'Monthly revenue cost and runway'!J19)))+'Monthly revenue cost and runway'!K17 -> 8134.9545 | L19: =IF(IF(IF(IF(ISERROR('Customers revenue and run costs'!L5=1),'Customers revenue and run costs'!L5=1,IF('Customers revenue and run costs'!L5="","",'Customers revenue and run costs'!L5=1))="",FALSE,IF(ISERROR('Customers revenue and run costs'!L5=1),'Customers revenue and run costs'!L5=1,IF('Customers revenue and run costs'!L5="","",'Customers revenue and run costs'!L5=1))),IF('Model inputs'!B40="","",'Model inputs'!B40),IF('Monthly revenue cost and runway'!K19="","",'Monthly revenue cost and runway'!K19))="",0,IF(IF(IF(ISERROR('Customers revenue and run costs'!L5=1),'Customers revenue and run costs'!L5=1,IF('Customers revenue and run costs'!L5="","",'Customers revenue and run costs'!L5=1))="",FALSE,IF(ISERROR('Customers revenue and run costs'!L5=1),'Customers revenue and run costs'!L5=1,IF('Customers revenue and run costs'!L5="","",'Customers revenue and run costs'!L5=1))),IF('Model inputs'!B40="","",'Model inputs'!B40),IF('Monthly revenue cost and runway'!K19="","",'Monthly revenue cost and runway'!K19)))+'Monthly revenue cost and runway'!L17 -> 10745.8 | M19: =IF(IF(IF(IF(ISERROR('Customers revenue and run costs'!M5=1),'Customers revenue and run costs'!M5=1,IF('Customers revenue and run costs'!M5="","",'Customers revenue and run costs'!M5=1))="",FALSE,IF(ISERROR('Customers revenue and run costs'!M5=1),'Customers revenue and run costs'!M5=1,IF('Customers revenue and run costs'!M5="","",'Customers revenue and run costs'!M5=1))),IF('Model inputs'!B40="","",'Model inputs'!B40),IF('Monthly revenue cost and runway'!L19="","",'Monthly revenue cost and runway'!L19))="",0,IF(IF(IF(ISERROR('Customers revenue and run costs'!M5=1),'Customers revenue and run costs'!M5=1,IF('Customers revenue and run costs'!M5="","",'Customers revenue and run costs'!M5=1))="",FALSE,IF(ISERROR('Customers revenue and run costs'!M5=1),'Customers revenue and run costs'!M5=1,IF('Customers revenue and run costs'!M5="","",'Customers revenue and run costs'!M5=1))),IF('Model inputs'!B40="","",'Model inputs'!B40),IF('Monthly revenue cost and runway'!L19="","",'Monthly revenue cost and runway'!L19)))+'Monthly revenue cost and runway'!M17 -> 13487.8
A20: Funding needed to date | B20: =MAX(IF(IF(IF(ISERROR('Customers revenue and run costs'!B5=1),'Customers revenue and run costs'!B5=1,IF('Customers revenue and run costs'!B5="","",'Customers revenue and run costs'!B5=1))="",FALSE,IF(ISERROR('Customers revenue and run costs'!B5=1),'Customers revenue and run costs'!B5=1,IF('Customers revenue and run costs'!B5="","",'Customers revenue and run costs'!B5=1))),0,IF('Model inputs'!D30="","",'Model inputs'!D30)),MAX(-'Monthly revenue cost and runway'!B19,0)) -> 45.7 | C20: =MAX(IF(IF(IF(ISERROR('Customers revenue and run costs'!C5=1),'Customers revenue and run costs'!C5=1,IF('Customers revenue and run costs'!C5="","",'Customers revenue and run costs'!C5=1))="",FALSE,IF(ISERROR('Customers revenue and run costs'!C5=1),'Customers revenue and run costs'!C5=1,IF('Customers revenue and run costs'!C5="","",'Customers revenue and run costs'!C5=1))),0,IF('Monthly revenue cost and runway'!B20="","",'Monthly revenue cost and runway'!B20)),MAX(-'Monthly revenue cost and runway'!C19,0)) -> 45.7 | D20: =MAX(IF(IF(IF(ISERROR('Customers revenue and run costs'!D5=1),'Customers revenue and run costs'!D5=1,IF('Customers revenue and run costs'!D5="","",'Customers revenue and run costs'!D5=1))="",FALSE,IF(ISERROR('Customers revenue and run costs'!D5=1),'Customers revenue and run costs'!D5=1,IF('Customers revenue and run costs'!D5="","",'Customers revenue and run costs'!D5=1))),0,IF('Monthly revenue cost and runway'!C20="","",'Monthly revenue cost and runway'!C20)),MAX(-'Monthly revenue cost and runway'!D19,0)) -> 45.7 | E20: =MAX(IF(IF(IF(ISERROR('Customers revenue and run costs'!E5=1),'Customers revenue and run costs'!E5=1,IF('Customers revenue and run costs'!E5="","",'Customers revenue and run costs'!E5=1))="",FALSE,IF(ISERROR('Customers revenue and run costs'!E5=1),'Customers revenue and run costs'!E5=1,IF('Customers revenue and run costs'!E5="","",'Customers revenue and run costs'!E5=1))),0,IF('Monthly revenue cost and runway'!D20="","",'Monthly revenue cost and runway'!D20)),MAX(-'Monthly revenue cost and runway'!E19,0)) -> 45.7 | F20: =MAX(IF(IF(IF(ISERROR('Customers revenue and run costs'!F5=1),'Customers revenue and run costs'!F5=1,IF('Customers revenue and run costs'!F5="","",'Customers revenue and run costs'!F5=1))="",FALSE,IF(ISERROR('Customers revenue and run costs'!F5=1),'Customers revenue and run costs'!F5=1,IF('Customers revenue and run costs'!F5="","",'Customers revenue and run costs'!F5=1))),0,IF('Monthly revenue cost and runway'!E20="","",'Monthly revenue cost and runway'!E20)),MAX(-'Monthly revenue cost and runway'!F19,0)) -> 45.7 | G20: =MAX(IF(IF(IF(ISERROR('Customers revenue and run costs'!G5=1),'Customers revenue and run costs'!G5=1,IF('Customers revenue and run costs'!G5="","",'Customers revenue and run costs'!G5=1))="",FALSE,IF(ISERROR('Customers revenue and run costs'!G5=1),'Customers revenue and run costs'!G5=1,IF('Customers revenue and run costs'!G5="","",'Customers revenue and run costs'!G5=1))),0,IF('Monthly revenue cost and runway'!F20="","",'Monthly revenue cost and runway'!F20)),MAX(-'Monthly revenue cost and runway'!G19,0)) -> 45.7 | H20: =MAX(IF(IF(IF(ISERROR('Customers revenue and run costs'!H5=1),'Customers revenue and run costs'!H5=1,IF('Customers revenue and run costs'!H5="","",'Customers revenue and run costs'!H5=1))="",FALSE,IF(ISERROR('Customers revenue and run costs'!H5=1),'Customers revenue and run costs'!H5=1,IF('Customers revenue and run costs'!H5="","",'Customers revenue and run costs'!H5=1))),0,IF('Monthly revenue cost and runway'!G20="","",'Monthly revenue cost and runway'!G20)),MAX(-'Monthly revenue cost and runway'!H19,0)) -> 45.7 | I20: =MAX(IF(IF(IF(ISERROR('Customers revenue and run costs'!I5=1),'Customers revenue and run costs'!I5=1,IF('Customers revenue and run costs'!I5="","",'Customers revenue and run costs'!I5=1))="",FALSE,IF(ISERROR('Customers revenue and run costs'!I5=1),'Customers revenue and run costs'!I5=1,IF('Customers revenue and run costs'!I5="","",'Customers revenue and run costs'!I5=1))),0,IF('Monthly revenue cost and runway'!H20="","",'Monthly revenue cost and runway'!H20)),MAX(-'Monthly revenue cost and runway'!I19,0)) -> 45.7 | J20: =MAX(IF(IF(IF(ISERROR('Customers revenue and run costs'!J5=1),'Customers revenue and run costs'!J5=1,IF('Customers revenue and run costs'!J5="","",'Customers revenue and run costs'!J5=1))="",FALSE,IF(ISERROR('Customers revenue and run costs'!J5=1),'Customers revenue and run costs'!J5=1,IF('Customers revenue and run costs'!J5="","",'Customers revenue and run costs'!J5=1))),0,IF('Monthly revenue cost and runway'!I20="","",'Monthly revenue cost and runway'!I20)),MAX(-'Monthly revenue cost and runway'!J19,0)) -> 45.7 | ... M20: =MAX(IF(IF(IF(ISERROR('Customers revenue and run costs'!M5=1),'Customers revenue and run costs'!M5=1,IF('Customers revenue and run costs'!M5="","",'Customers revenue and run costs'!M5=1))="",FALSE,IF(ISERROR('Customers revenue and run costs'!M5=1),'Customers revenue and run costs'!M5=1,IF('Customers revenue and run costs'!M5="","",'Customers revenue and run costs'!M5=1))),0,IF('Monthly revenue cost and runway'!L20="","",'Monthly revenue cost and runway'!L20)),MAX(-'Monthly revenue cost and runway'!M19,0)) -> 45.7
A21: Runway months | B21: =IF(IF(IF(ISERROR('Monthly revenue cost and runway'!B19<=0),'Monthly revenue cost and runway'!B19<=0,IF('Monthly revenue cost and runway'!B19="","",'Monthly revenue cost and runway'!B19<=0))="",FALSE,IF(ISERROR('Monthly revenue cost and runway'!B19<=0),'Monthly revenue cost and runway'!B19<=0,IF('Monthly revenue cost and runway'!B19="","",'Monthly revenue cost and runway'!B19<=0))),0,IF(IF(IF(ISERROR('Monthly revenue cost and runway'!B17<0),'Monthly revenue cost and runway'!B17<0,IF('Monthly revenue cost and runway'!B17="","",'Monthly revenue cost and runway'!B17<0))="",FALSE,IF(ISERROR('Monthly revenue cost and runway'!B17<0),'Monthly revenue cost and runway'!B17<0,IF('Monthly revenue cost and runway'!B17="","",'Monthly revenue cost and runway'!B17<0))),'Monthly revenue cost and runway'!B19/-'Monthly revenue cost and runway'!B17,"")) -> 0 | C21: =IF(IF(IF(ISERROR('Monthly revenue cost and runway'!C19<=0),'Monthly revenue cost and runway'!C19<=0,IF('Monthly revenue cost and runway'!C19="","",'Monthly revenue cost and runway'!C19<=0))="",FALSE,IF(ISERROR('Monthly revenue cost and runway'!C19<=0),'Monthly revenue cost and runway'!C19<=0,IF('Monthly revenue cost and runway'!C19="","",'Monthly revenue cost and runway'!C19<=0))),0,IF(IF(IF(ISERROR('Monthly revenue cost and runway'!C17<0),'Monthly revenue cost and runway'!C17<0,IF('Monthly revenue cost and runway'!C17="","",'Monthly revenue cost and runway'!C17<0))="",FALSE,IF(ISERROR('Monthly revenue cost and runway'!C17<0),'Monthly revenue cost and runway'!C17<0,IF('Monthly revenue cost and runway'!C17="","",'Monthly revenue cost and runway'!C17<0))),'Monthly revenue cost and runway'!C19/-'Monthly revenue cost and runway'!C17,"")) | D21: =IF(IF(IF(ISERROR('Monthly revenue cost and runway'!D19<=0),'Monthly revenue cost and runway'!D19<=0,IF('Monthly revenue cost and runway'!D19="","",'Monthly revenue cost and runway'!D19<=0))="",FALSE,IF(ISERROR('Monthly revenue cost and runway'!D19<=0),'Monthly revenue cost and runway'!D19<=0,IF('Monthly revenue cost and runway'!D19="","",'Monthly revenue cost and runway'!D19<=0))),0,IF(IF(IF(ISERROR('Monthly revenue cost and runway'!D17<0),'Monthly revenue cost and runway'!D17<0,IF('Monthly revenue cost and runway'!D17="","",'Monthly revenue cost and runway'!D17<0))="",FALSE,IF(ISERROR('Monthly revenue cost and runway'!D17<0),'Monthly revenue cost and runway'!D17<0,IF('Monthly revenue cost and runway'!D17="","",'Monthly revenue cost and runway'!D17<0))),'Monthly revenue cost and runway'!D19/-'Monthly revenue cost and runway'!D17,"")) | E21: =IF(IF(IF(ISERROR('Monthly revenue cost and runway'!E19<=0),'Monthly revenue cost and runway'!E19<=0,IF('Monthly revenue cost and runway'!E19="","",'Monthly revenue cost and runway'!E19<=0))="",FALSE,IF(ISERROR('Monthly revenue cost and runway'!E19<=0),'Monthly revenue cost and runway'!E19<=0,IF('Monthly revenue cost and runway'!E19="","",'Monthly revenue cost and runway'!E19<=0))),0,IF(IF(IF(ISERROR('Monthly revenue cost and runway'!E17<0),'Monthly revenue cost and runway'!E17<0,IF('Monthly revenue cost and runway'!E17="","",'Monthly revenue cost and runway'!E17<0))="",FALSE,IF(ISERROR('Monthly revenue cost and runway'!E17<0),'Monthly revenue cost and runway'!E17<0,IF('Monthly revenue cost and runway'!E17="","",'Monthly revenue cost and runway'!E17<0))),'Monthly revenue cost and runway'!E19/-'Monthly revenue cost and runway'!E17,"")) | F21: =IF(IF(IF(ISERROR('Monthly revenue cost and runway'!F19<=0),'Monthly revenue cost and runway'!F19<=0,IF('Monthly revenue cost and runway'!F19="","",'Monthly revenue cost and runway'!F19<=0))="",FALSE,IF(ISERROR('Monthly revenue cost and runway'!F19<=0),'Monthly revenue cost and runway'!F19<=0,IF('Monthly revenue cost and runway'!F19="","",'Monthly revenue cost and runway'!F19<=0))),0,IF(IF(IF(ISERROR('Monthly revenue cost and runway'!F17<0),'Monthly revenue cost and runway'!F17<0,IF('Monthly revenue cost and runway'!F17="","",'Monthly revenue cost and runway'!F17<0))="",FALSE,IF(ISERROR('Monthly revenue cost and runway'!F17<0),'Monthly revenue cost and runway'!F17<0,IF('Monthly revenue cost and runway'!F17="","",'Monthly revenue cost and runway'!F17<0))),'Monthly revenue cost and runway'!F19/-'Monthly revenue cost and runway'!F17,"")) | G21: =IF(IF(IF(ISERROR('Monthly revenue cost and runway'!G19<=0),'Monthly revenue cost and runway'!G19<=0,IF('Monthly revenue cost and runway'!G19="","",'Monthly revenue cost and runway'!G19<=0))="",FALSE,IF(ISERROR('Monthly revenue cost and runway'!G19<=0),'Monthly revenue cost and runway'!G19<=0,IF('Monthly revenue cost and runway'!G19="","",'Monthly revenue cost and runway'!G19<=0))),0,IF(IF(IF(ISERROR('Monthly revenue cost and runway'!G17<0),'Monthly revenue cost and runway'!G17<0,IF('Monthly revenue cost and runway'!G17="","",'Monthly revenue cost and runway'!G17<0))="",FALSE,IF(ISERROR('Monthly revenue cost and runway'!G17<0),'Monthly revenue cost and runway'!G17<0,IF('Monthly revenue cost and runway'!G17="","",'Monthly revenue cost and runway'!G17<0))),'Monthly revenue cost and runway'!G19/-'Monthly revenue cost and runway'!G17,"")) | H21: =IF(IF(IF(ISERROR('Monthly revenue cost and runway'!H19<=0),'Monthly revenue cost and runway'!H19<=0,IF('Monthly revenue cost and runway'!H19="","",'Monthly revenue cost and runway'!H19<=0))="",FALSE,IF(ISERROR('Monthly revenue cost and runway'!H19<=0),'Monthly revenue cost and runway'!H19<=0,IF('Monthly revenue cost and runway'!H19="","",'Monthly revenue cost and runway'!H19<=0))),0,IF(IF(IF(ISERROR('Monthly revenue cost and runway'!H17<0),'Monthly revenue cost and runway'!H17<0,IF('Monthly revenue cost and runway'!H17="","",'Monthly revenue cost and runway'!H17<0))="",FALSE,IF(ISERROR('Monthly revenue cost and runway'!H17<0),'Monthly revenue cost and runway'!H17<0,IF('Monthly revenue cost and runway'!H17="","",'Monthly revenue cost and runway'!H17<0))),'Monthly revenue cost and runway'!H19/-'Monthly revenue cost and runway'!H17,"")) | I21: =IF(IF(IF(ISERROR('Monthly revenue cost and runway'!I19<=0),'Monthly revenue cost and runway'!I19<=0,IF('Monthly revenue cost and runway'!I19="","",'Monthly revenue cost and runway'!I19<=0))="",FALSE,IF(ISERROR('Monthly revenue cost and runway'!I19<=0),'Monthly revenue cost and runway'!I19<=0,IF('Monthly revenue cost and runway'!I19="","",'Monthly revenue cost and runway'!I19<=0))),0,IF(IF(IF(ISERROR('Monthly revenue cost and runway'!I17<0),'Monthly revenue cost and runway'!I17<0,IF('Monthly revenue cost and runway'!I17="","",'Monthly revenue cost and runway'!I17<0))="",FALSE,IF(ISERROR('Monthly revenue cost and runway'!I17<0),'Monthly revenue cost and runway'!I17<0,IF('Monthly revenue cost and runway'!I17="","",'Monthly revenue cost and runway'!I17<0))),'Monthly revenue cost and runway'!I19/-'Monthly revenue cost and runway'!I17,"")) | ... M21: =IF(IF(IF(ISERROR('Monthly revenue cost and runway'!M19<=0),'Monthly revenue cost and runway'!M19<=0,IF('Monthly revenue cost and runway'!M19="","",'Monthly revenue cost and runway'!M19<=0))="",FALSE,IF(ISERROR('Monthly revenue cost and runway'!M19<=0),'Monthly revenue cost and runway'!M19<=0,IF('Monthly revenue cost and runway'!M19="","",'Monthly revenue cost and runway'!M19<=0))),0,IF(IF(IF(ISERROR('Monthly revenue cost and runway'!M17<0),'Monthly revenue cost and runway'!M17<0,IF('Monthly revenue cost and runway'!M17="","",'Monthly revenue cost and runway'!M17<0))="",FALSE,IF(ISERROR('Monthly revenue cost and runway'!M17<0),'Monthly revenue cost and runway'!M17<0,IF('Monthly revenue cost and runway'!M17="","",'Monthly revenue cost and runway'!M17<0))),'Monthly revenue cost and runway'!M19/-'Monthly revenue cost and runway'!M17,""))
A22: Cash runway status | B22: =IF(IF(IF(ISERROR('Monthly revenue cost and runway'!B19<0),'Monthly revenue cost and runway'!B19<0,IF('Monthly revenue cost and runway'!B19="","",'Monthly revenue cost and runway'!B19<0))="",FALSE,IF(ISERROR('Monthly revenue cost and runway'!B19<0),'Monthly revenue cost and runway'!B19<0,IF('Monthly revenue cost and runway'!B19="","",'Monthly revenue cost and runway'!B19<0))),"Funding required",IF(IF(IF(ISERROR('Monthly revenue cost and runway'!B17<0),'Monthly revenue cost and runway'!B17<0,IF('Monthly revenue cost and runway'!B17="","",'Monthly revenue cost and runway'!B17<0))="",FALSE,IF(ISERROR('Monthly revenue cost and runway'!B17<0),'Monthly revenue cost and runway'!B17<0,IF('Monthly revenue cost and runway'!B17="","",'Monthly revenue cost and runway'!B17<0))),"Burning cash","Cash-generating")) -> Funding required | C22: =IF(IF(IF(ISERROR('Monthly revenue cost and runway'!C19<0),'Monthly revenue cost and runway'!C19<0,IF('Monthly revenue cost and runway'!C19="","",'Monthly revenue cost and runway'!C19<0))="",FALSE,IF(ISERROR('Monthly revenue cost and runway'!C19<0),'Monthly revenue cost and runway'!C19<0,IF('Monthly revenue cost and runway'!C19="","",'Monthly revenue cost and runway'!C19<0))),"Funding required",IF(IF(IF(ISERROR('Monthly revenue cost and runway'!C17<0),'Monthly revenue cost and runway'!C17<0,IF('Monthly revenue cost and runway'!C17="","",'Monthly revenue cost and runway'!C17<0))="",FALSE,IF(ISERROR('Monthly revenue cost and runway'!C17<0),'Monthly revenue cost and runway'!C17<0,IF('Monthly revenue cost and runway'!C17="","",'Monthly revenue cost and runway'!C17<0))),"Burning cash","Cash-generating")) -> Cash-generating | D22: =IF(IF(IF(ISERROR('Monthly revenue cost and runway'!D19<0),'Monthly revenue cost and runway'!D19<0,IF('Monthly revenue cost and runway'!D19="","",'Monthly revenue cost and runway'!D19<0))="",FALSE,IF(ISERROR('Monthly revenue cost and runway'!D19<0),'Monthly revenue cost and runway'!D19<0,IF('Monthly revenue cost and runway'!D19="","",'Monthly revenue cost and runway'!D19<0))),"Funding required",IF(IF(IF(ISERROR('Monthly revenue cost and runway'!D17<0),'Monthly revenue cost and runway'!D17<0,IF('Monthly revenue cost and runway'!D17="","",'Monthly revenue cost and runway'!D17<0))="",FALSE,IF(ISERROR('Monthly revenue cost and runway'!D17<0),'Monthly revenue cost and runway'!D17<0,IF('Monthly revenue cost and runway'!D17="","",'Monthly revenue cost and runway'!D17<0))),"Burning cash","Cash-generating")) -> Cash-generating | E22: =IF(IF(IF(ISERROR('Monthly revenue cost and runway'!E19<0),'Monthly revenue cost and runway'!E19<0,IF('Monthly revenue cost and runway'!E19="","",'Monthly revenue cost and runway'!E19<0))="",FALSE,IF(ISERROR('Monthly revenue cost and runway'!E19<0),'Monthly revenue cost and runway'!E19<0,IF('Monthly revenue cost and runway'!E19="","",'Monthly revenue cost and runway'!E19<0))),"Funding required",IF(IF(IF(ISERROR('Monthly revenue cost and runway'!E17<0),'Monthly revenue cost and runway'!E17<0,IF('Monthly revenue cost and runway'!E17="","",'Monthly revenue cost and runway'!E17<0))="",FALSE,IF(ISERROR('Monthly revenue cost and runway'!E17<0),'Monthly revenue cost and runway'!E17<0,IF('Monthly revenue cost and runway'!E17="","",'Monthly revenue cost and runway'!E17<0))),"Burning cash","Cash-generating")) -> Cash-generating | F22: =IF(IF(IF(ISERROR('Monthly revenue cost and runway'!F19<0),'Monthly revenue cost and runway'!F19<0,IF('Monthly revenue cost and runway'!F19="","",'Monthly revenue cost and runway'!F19<0))="",FALSE,IF(ISERROR('Monthly revenue cost and runway'!F19<0),'Monthly revenue cost and runway'!F19<0,IF('Monthly revenue cost and runway'!F19="","",'Monthly revenue cost and runway'!F19<0))),"Funding required",IF(IF(IF(ISERROR('Monthly revenue cost and runway'!F17<0),'Monthly revenue cost and runway'!F17<0,IF('Monthly revenue cost and runway'!F17="","",'Monthly revenue cost and runway'!F17<0))="",FALSE,IF(ISERROR('Monthly revenue cost and runway'!F17<0),'Monthly revenue cost and runway'!F17<0,IF('Monthly revenue cost and runway'!F17="","",'Monthly revenue cost and runway'!F17<0))),"Burning cash","Cash-generating")) -> Cash-generating | G22: =IF(IF(IF(ISERROR('Monthly revenue cost and runway'!G19<0),'Monthly revenue cost and runway'!G19<0,IF('Monthly revenue cost and runway'!G19="","",'Monthly revenue cost and runway'!G19<0))="",FALSE,IF(ISERROR('Monthly revenue cost and runway'!G19<0),'Monthly revenue cost and runway'!G19<0,IF('Monthly revenue cost and runway'!G19="","",'Monthly revenue cost and runway'!G19<0))),"Funding required",IF(IF(IF(ISERROR('Monthly revenue cost and runway'!G17<0),'Monthly revenue cost and runway'!G17<0,IF('Monthly revenue cost and runway'!G17="","",'Monthly revenue cost and runway'!G17<0))="",FALSE,IF(ISERROR('Monthly revenue cost and runway'!G17<0),'Monthly revenue cost and runway'!G17<0,IF('Monthly revenue cost and runway'!G17="","",'Monthly revenue cost and runway'!G17<0))),"Burning cash","Cash-generating")) -> Cash-generating | H22: =IF(IF(IF(ISERROR('Monthly revenue cost and runway'!H19<0),'Monthly revenue cost and runway'!H19<0,IF('Monthly revenue cost and runway'!H19="","",'Monthly revenue cost and runway'!H19<0))="",FALSE,IF(ISERROR('Monthly revenue cost and runway'!H19<0),'Monthly revenue cost and runway'!H19<0,IF('Monthly revenue cost and runway'!H19="","",'Monthly revenue cost and runway'!H19<0))),"Funding required",IF(IF(IF(ISERROR('Monthly revenue cost and runway'!H17<0),'Monthly revenue cost and runway'!H17<0,IF('Monthly revenue cost and runway'!H17="","",'Monthly revenue cost and runway'!H17<0))="",FALSE,IF(ISERROR('Monthly revenue cost and runway'!H17<0),'Monthly revenue cost and runway'!H17<0,IF('Monthly revenue cost and runway'!H17="","",'Monthly revenue cost and runway'!H17<0))),"Burning cash","Cash-generating")) -> Cash-generating | I22: =IF(IF(IF(ISERROR('Monthly revenue cost and runway'!I19<0),'Monthly revenue cost and runway'!I19<0,IF('Monthly revenue cost and runway'!I19="","",'Monthly revenue cost and runway'!I19<0))="",FALSE,IF(ISERROR('Monthly revenue cost and runway'!I19<0),'Monthly revenue cost and runway'!I19<0,IF('Monthly revenue cost and runway'!I19="","",'Monthly revenue cost and runway'!I19<0))),"Funding required",IF(IF(IF(ISERROR('Monthly revenue cost and runway'!I17<0),'Monthly revenue cost and runway'!I17<0,IF('Monthly revenue cost and runway'!I17="","",'Monthly revenue cost and runway'!I17<0))="",FALSE,IF(ISERROR('Monthly revenue cost and runway'!I17<0),'Monthly revenue cost and runway'!I17<0,IF('Monthly revenue cost and runway'!I17="","",'Monthly revenue cost and runway'!I17<0))),"Burning cash","Cash-generating")) -> Cash-generating | ... M22: =IF(IF(IF(ISERROR('Monthly revenue cost and runway'!M19<0),'Monthly revenue cost and runway'!M19<0,IF('Monthly revenue cost and runway'!M19="","",'Monthly revenue cost and runway'!M19<0))="",FALSE,IF(ISERROR('Monthly revenue cost and runway'!M19<0),'Monthly revenue cost and runway'!M19<0,IF('Monthly revenue cost and runway'!M19="","",'Monthly revenue cost and runway'!M19<0))),"Funding required",IF(IF(IF(ISERROR('Monthly revenue cost and runway'!M17<0),'Monthly revenue cost and runway'!M17<0,IF('Monthly revenue cost and runway'!M17="","",'Monthly revenue cost and runway'!M17<0))="",FALSE,IF(ISERROR('Monthly revenue cost and runway'!M17<0),'Monthly revenue cost and runway'!M17<0,IF('Monthly revenue cost and runway'!M17="","",'Monthly revenue cost and runway'!M17<0))),"Burning cash","Cash-generating")) -> Cash-generating

Sheet Customers revenue and run costs
A1: Customers revenue and run costs
A2: Susanoo — 12-Month Forecast · Susanoo — Base
A4: Variable / dimension | B4: 2026-11 | C4: 2026-12 | D4: 2027-01 | E4: 2027-02 | F4: 2027-03 | G4: 2027-04 | H4: 2027-05 | I4: 2027-06 | J4: 2027-07 | K4: 2027-08 | L4: 2027-09 | M4: 2027-10
A5: Forecast month | B5: =DATEDIF('Model inputs'!Q21,DATE(2026,11,1),"M")+1 -> 1 | C5: =DATEDIF('Model inputs'!Q21,DATE(2026,12,1),"M")+1 -> 2 | D5: =DATEDIF('Model inputs'!Q21,DATE(2027,1,1),"M")+1 -> 3 | E5: =DATEDIF('Model inputs'!Q21,DATE(2027,2,1),"M")+1 -> 4 | F5: =DATEDIF('Model inputs'!Q21,DATE(2027,3,1),"M")+1 -> 5 | G5: =DATEDIF('Model inputs'!Q21,DATE(2027,4,1),"M")+1 -> 6 | H5: =DATEDIF('Model inputs'!Q21,DATE(2027,5,1),"M")+1 -> 7 | I5: =DATEDIF('Model inputs'!Q21,DATE(2027,6,1),"M")+1 -> 8 | J5: =DATEDIF('Model inputs'!Q21,DATE(2027,7,1),"M")+1 -> 9 | K5: =DATEDIF('Model inputs'!Q21,DATE(2027,8,1),"M")+1 -> 10 | L5: =DATEDIF('Model inputs'!Q21,DATE(2027,9,1),"M")+1 -> 11 | M5: =DATEDIF('Model inputs'!Q21,DATE(2027,10,1),"M")+1 -> 12
A6: Forecast customers | B6: =SUM('Customers revenue and run costs'!B7,'Customers revenue and run costs'!B8,'Customers revenue and run costs'!B9) -> 27 | C6: =SUM('Customers revenue and run costs'!C7,'Customers revenue and run costs'!C8,'Customers revenue and run costs'!C9) -> 55.454545 | D6: =SUM('Customers revenue and run costs'!D7,'Customers revenue and run costs'!D8,'Customers revenue and run costs'!D9) -> 83.909091 | E6: =SUM('Customers revenue and run costs'!E7,'Customers revenue and run costs'!E8,'Customers revenue and run costs'!E9) -> 112.36364 | F6: =SUM('Customers revenue and run costs'!F7,'Customers revenue and run costs'!F8,'Customers revenue and run costs'!F9) -> 140.81818 | G6: =SUM('Customers revenue and run costs'!G7,'Customers revenue and run costs'!G8,'Customers revenue and run costs'!G9) -> 169.27273 | H6: =SUM('Customers revenue and run costs'!H7,'Customers revenue and run costs'!H8,'Customers revenue and run costs'!H9) -> 197.72727 | I6: =SUM('Customers revenue and run costs'!I7,'Customers revenue and run costs'!I8,'Customers revenue and run costs'!I9) -> 226.18182 | ... M6: =SUM('Customers revenue and run costs'!M7,'Customers revenue and run costs'!M8,'Customers revenue and run costs'!M9) -> 341
A7: Enterprise | B7: =IF(EXACT("Enterprise","Enterprise"),IF(IF(IF(ISERROR('Customers revenue and run costs'!B5=1),'Customers revenue and run costs'!B5=1,IF('Customers revenue and run costs'!B5="","",'Customers revenue and run costs'!B5=1))="",FALSE,IF(ISERROR('Customers revenue and run costs'!B5=1),'Customers revenue and run costs'!B5=1,IF('Customers revenue and run costs'!B5="","",'Customers revenue and run costs'!B5=1))),IF('Model inputs'!E10="","",'Model inputs'!E10),'Model inputs'!D57+'Model inputs'!E10),'Model inputs'!B37+('Model inputs'!B7-'Model inputs'!B37)*('Customers revenue and run costs'!B5-1)/('Model inputs'!Q18-1)) -> 0 | C7: =IF(EXACT("Enterprise","Enterprise"),IF(IF(IF(ISERROR('Customers revenue and run costs'!C5=1),'Customers revenue and run costs'!C5=1,IF('Customers revenue and run costs'!C5="","",'Customers revenue and run costs'!C5=1))="",FALSE,IF(ISERROR('Customers revenue and run costs'!C5=1),'Customers revenue and run costs'!C5=1,IF('Customers revenue and run costs'!C5="","",'Customers revenue and run costs'!C5=1))),IF('Model inputs'!F10="","",'Model inputs'!F10),'Customers revenue and run costs'!B7+'Model inputs'!F10),'Model inputs'!B37+('Model inputs'!B7-'Model inputs'!B37)*('Customers revenue and run costs'!C5-1)/('Model inputs'!Q18-1)) -> 0 | D7: =IF(EXACT("Enterprise","Enterprise"),IF(IF(IF(ISERROR('Customers revenue and run costs'!D5=1),'Customers revenue and run costs'!D5=1,IF('Customers revenue and run costs'!D5="","",'Customers revenue and run costs'!D5=1))="",FALSE,IF(ISERROR('Customers revenue and run costs'!D5=1),'Customers revenue and run costs'!D5=1,IF('Customers revenue and run costs'!D5="","",'Customers revenue and run costs'!D5=1))),IF('Model inputs'!G10="","",'Model inputs'!G10),'Customers revenue and run costs'!C7+'Model inputs'!G10),'Model inputs'!B37+('Model inputs'!B7-'Model inputs'!B37)*('Customers revenue and run costs'!D5-1)/('Model inputs'!Q18-1)) -> 0 | E7: =IF(EXACT("Enterprise","Enterprise"),IF(IF(IF(ISERROR('Customers revenue and run costs'!E5=1),'Customers revenue and run costs'!E5=1,IF('Customers revenue and run costs'!E5="","",'Customers revenue and run costs'!E5=1))="",FALSE,IF(ISERROR('Customers revenue and run costs'!E5=1),'Customers revenue and run costs'!E5=1,IF('Customers revenue and run costs'!E5="","",'Customers revenue and run costs'!E5=1))),IF('Model inputs'!H10="","",'Model inputs'!H10),'Customers revenue and run costs'!D7+'Model inputs'!H10),'Model inputs'!B37+('Model inputs'!B7-'Model inputs'!B37)*('Customers revenue and run costs'!E5-1)/('Model inputs'!Q18-1)) -> 0 | F7: =IF(EXACT("Enterprise","Enterprise"),IF(IF(IF(ISERROR('Customers revenue and run costs'!F5=1),'Customers revenue and run costs'!F5=1,IF('Customers revenue and run costs'!F5="","",'Customers revenue and run costs'!F5=1))="",FALSE,IF(ISERROR('Customers revenue and run costs'!F5=1),'Customers revenue and run costs'!F5=1,IF('Customers revenue and run costs'!F5="","",'Customers revenue and run costs'!F5=1))),IF('Model inputs'!I10="","",'Model inputs'!I10),'Customers revenue and run costs'!E7+'Model inputs'!I10),'Model inputs'!B37+('Model inputs'!B7-'Model inputs'!B37)*('Customers revenue and run costs'!F5-1)/('Model inputs'!Q18-1)) -> 0 | G7: =IF(EXACT("Enterprise","Enterprise"),IF(IF(IF(ISERROR('Customers revenue and run costs'!G5=1),'Customers revenue and run costs'!G5=1,IF('Customers revenue and run costs'!G5="","",'Customers revenue and run costs'!G5=1))="",FALSE,IF(ISERROR('Customers revenue and run costs'!G5=1),'Customers revenue and run costs'!G5=1,IF('Customers revenue and run costs'!G5="","",'Customers revenue and run costs'!G5=1))),IF('Model inputs'!J10="","",'Model inputs'!J10),'Customers revenue and run costs'!F7+'Model inputs'!J10),'Model inputs'!B37+('Model inputs'!B7-'Model inputs'!B37)*('Customers revenue and run costs'!G5-1)/('Model inputs'!Q18-1)) -> 0 | H7: =IF(EXACT("Enterprise","Enterprise"),IF(IF(IF(ISERROR('Customers revenue and run costs'!H5=1),'Customers revenue and run costs'!H5=1,IF('Customers revenue and run costs'!H5="","",'Customers revenue and run costs'!H5=1))="",FALSE,IF(ISERROR('Customers revenue and run costs'!H5=1),'Customers revenue and run costs'!H5=1,IF('Customers revenue and run costs'!H5="","",'Customers revenue and run costs'!H5=1))),IF('Model inputs'!K10="","",'Model inputs'!K10),'Customers revenue and run costs'!G7+'Model inputs'!K10),'Model inputs'!B37+('Model inputs'!B7-'Model inputs'!B37)*('Customers revenue and run costs'!H5-1)/('Model inputs'!Q18-1)) -> 0 | I7: =IF(EXACT("Enterprise","Enterprise"),IF(IF(IF(ISERROR('Customers revenue and run costs'!I5=1),'Customers revenue and run costs'!I5=1,IF('Customers revenue and run costs'!I5="","",'Customers revenue and run costs'!I5=1))="",FALSE,IF(ISERROR('Customers revenue and run costs'!I5=1),'Customers revenue and run costs'!I5=1,IF('Customers revenue and run costs'!I5="","",'Customers revenue and run costs'!I5=1))),IF('Model inputs'!L10="","",'Model inputs'!L10),'Customers revenue and run costs'!H7+'Model inputs'!L10),'Model inputs'!B37+('Model inputs'!B7-'Model inputs'!B37)*('Customers revenue and run costs'!I5-1)/('Model inputs'!Q18-1)) -> 0 | J7: =IF(EXACT("Enterprise","Enterprise"),IF(IF(IF(ISERROR('Customers revenue and run costs'!J5=1),'Customers revenue and run costs'!J5=1,IF('Customers revenue and run costs'!J5="","",'Customers revenue and run costs'!J5=1))="",FALSE,IF(ISERROR('Customers revenue and run costs'!J5=1),'Customers revenue and run costs'!J5=1,IF('Customers revenue and run costs'!J5="","",'Customers revenue and run costs'!J5=1))),IF('Model inputs'!M10="","",'Model inputs'!M10),'Customers revenue and run costs'!I7+'Model inputs'!M10),'Model inputs'!B37+('Model inputs'!B7-'Model inputs'!B37)*('Customers revenue and run costs'!J5-1)/('Model inputs'!Q18-1)) -> 1 | K7: =IF(EXACT("Enterprise","Enterprise"),IF(IF(IF(ISERROR('Customers revenue and run costs'!K5=1),'Customers revenue and run costs'!K5=1,IF('Customers revenue and run costs'!K5="","",'Customers revenue and run costs'!K5=1))="",FALSE,IF(ISERROR('Customers revenue and run costs'!K5=1),'Customers revenue and run costs'!K5=1,IF('Customers revenue and run costs'!K5="","",'Customers revenue and run costs'!K5=1))),IF('Model inputs'!N10="","",'Model inputs'!N10),'Customers revenue and run costs'!J7+'Model inputs'!N10),'Model inputs'!B37+('Model inputs'!B7-'Model inputs'!B37)*('Customers revenue and run costs'!K5-1)/('Model inputs'!Q18-1)) -> 1 | L7: =IF(EXACT("Enterprise","Enterprise"),IF(IF(IF(ISERROR('Customers revenue and run costs'!L5=1),'Customers revenue and run costs'!L5=1,IF('Customers revenue and run costs'!L5="","",'Customers revenue and run costs'!L5=1))="",FALSE,IF(ISERROR('Customers revenue and run costs'!L5=1),'Customers revenue and run costs'!L5=1,IF('Customers revenue and run costs'!L5="","",'Customers revenue and run costs'!L5=1))),IF('Model inputs'!O10="","",'Model inputs'!O10),'Customers revenue and run costs'!K7+'Model inputs'!O10),'Model inputs'!B37+('Model inputs'!B7-'Model inputs'!B37)*('Customers revenue and run costs'!L5-1)/('Model inputs'!Q18-1)) -> 1 | M7: =IF(EXACT("Enterprise","Enterprise"),IF(IF(IF(ISERROR('Customers revenue and run costs'!M5=1),'Customers revenue and run costs'!M5=1,IF('Customers revenue and run costs'!M5="","",'Customers revenue and run costs'!M5=1))="",FALSE,IF(ISERROR('Customers revenue and run costs'!M5=1),'Customers revenue and run costs'!M5=1,IF('Customers revenue and run costs'!M5="","",'Customers revenue and run costs'!M5=1))),IF('Model inputs'!P10="","",'Model inputs'!P10),'Customers revenue and run costs'!L7+'Model inputs'!P10),'Model inputs'!B37+('Model inputs'!B7-'Model inputs'!B37)*('Customers revenue and run costs'!M5-1)/('Model inputs'!Q18-1)) -> 1
A8: Free | B8: =IF(EXACT("Free","Enterprise"),IF(IF(IF(ISERROR('Customers revenue and run costs'!B5=1),'Customers revenue and run costs'!B5=1,IF('Customers revenue and run costs'!B5="","",'Customers revenue and run costs'!B5=1))="",FALSE,IF(ISERROR('Customers revenue and run costs'!B5=1),'Customers revenue and run costs'!B5=1,IF('Customers revenue and run costs'!B5="","",'Customers revenue and run costs'!B5=1))),IF('Model inputs'!E10="","",'Model inputs'!E10),'Model inputs'!D58+'Model inputs'!E10),'Model inputs'!B38+('Model inputs'!B8-'Model inputs'!B38)*('Customers revenue and run costs'!B5-1)/('Model inputs'!Q18-1)) -> 25 | C8: =IF(EXACT("Free","Enterprise"),IF(IF(IF(ISERROR('Customers revenue and run costs'!C5=1),'Customers revenue and run costs'!C5=1,IF('Customers revenue and run costs'!C5="","",'Customers revenue and run costs'!C5=1))="",FALSE,IF(ISERROR('Customers revenue and run costs'!C5=1),'Customers revenue and run costs'!C5=1,IF('Customers revenue and run costs'!C5="","",'Customers revenue and run costs'!C5=1))),IF('Model inputs'!F10="","",'Model inputs'!F10),'Customers revenue and run costs'!B8+'Model inputs'!F10),'Model inputs'!B38+('Model inputs'!B8-'Model inputs'!B38)*('Customers revenue and run costs'!C5-1)/('Model inputs'!Q18-1)) -> 50 | D8: =IF(EXACT("Free","Enterprise"),IF(IF(IF(ISERROR('Customers revenue and run costs'!D5=1),'Customers revenue and run costs'!D5=1,IF('Customers revenue and run costs'!D5="","",'Customers revenue and run costs'!D5=1))="",FALSE,IF(ISERROR('Customers revenue and run costs'!D5=1),'Customers revenue and run costs'!D5=1,IF('Customers revenue and run costs'!D5="","",'Customers revenue and run costs'!D5=1))),IF('Model inputs'!G10="","",'Model inputs'!G10),'Customers revenue and run costs'!C8+'Model inputs'!G10),'Model inputs'!B38+('Model inputs'!B8-'Model inputs'!B38)*('Customers revenue and run costs'!D5-1)/('Model inputs'!Q18-1)) -> 75 | E8: =IF(EXACT("Free","Enterprise"),IF(IF(IF(ISERROR('Customers revenue and run costs'!E5=1),'Customers revenue and run costs'!E5=1,IF('Customers revenue and run costs'!E5="","",'Customers revenue and run costs'!E5=1))="",FALSE,IF(ISERROR('Customers revenue and run costs'!E5=1),'Customers revenue and run costs'!E5=1,IF('Customers revenue and run costs'!E5="","",'Customers revenue and run costs'!E5=1))),IF('Model inputs'!H10="","",'Model inputs'!H10),'Customers revenue and run costs'!D8+'Model inputs'!H10),'Model inputs'!B38+('Model inputs'!B8-'Model inputs'!B38)*('Customers revenue and run costs'!E5-1)/('Model inputs'!Q18-1)) -> 100 | F8: =IF(EXACT("Free","Enterprise"),IF(IF(IF(ISERROR('Customers revenue and run costs'!F5=1),'Customers revenue and run costs'!F5=1,IF('Customers revenue and run costs'!F5="","",'Customers revenue and run costs'!F5=1))="",FALSE,IF(ISERROR('Customers revenue and run costs'!F5=1),'Customers revenue and run costs'!F5=1,IF('Customers revenue and run costs'!F5="","",'Customers revenue and run costs'!F5=1))),IF('Model inputs'!I10="","",'Model inputs'!I10),'Customers revenue and run costs'!E8+'Model inputs'!I10),'Model inputs'!B38+('Model inputs'!B8-'Model inputs'!B38)*('Customers revenue and run costs'!F5-1)/('Model inputs'!Q18-1)) -> 125 | G8: =IF(EXACT("Free","Enterprise"),IF(IF(IF(ISERROR('Customers revenue and run costs'!G5=1),'Customers revenue and run costs'!G5=1,IF('Customers revenue and run costs'!G5="","",'Customers revenue and run costs'!G5=1))="",FALSE,IF(ISERROR('Customers revenue and run costs'!G5=1),'Customers revenue and run costs'!G5=1,IF('Customers revenue and run costs'!G5="","",'Customers revenue and run costs'!G5=1))),IF('Model inputs'!J10="","",'Model inputs'!J10),'Customers revenue and run costs'!F8+'Model inputs'!J10),'Model inputs'!B38+('Model inputs'!B8-'Model inputs'!B38)*('Customers revenue and run costs'!G5-1)/('Model inputs'!Q18-1)) -> 150 | H8: =IF(EXACT("Free","Enterprise"),IF(IF(IF(ISERROR('Customers revenue and run costs'!H5=1),'Customers revenue and run costs'!H5=1,IF('Customers revenue and run costs'!H5="","",'Customers revenue and run costs'!H5=1))="",FALSE,IF(ISERROR('Customers revenue and run costs'!H5=1),'Customers revenue and run costs'!H5=1,IF('Customers revenue and run costs'!H5="","",'Customers revenue and run costs'!H5=1))),IF('Model inputs'!K10="","",'Model inputs'!K10),'Customers revenue and run costs'!G8+'Model inputs'!K10),'Model inputs'!B38+('Model inputs'!B8-'Model inputs'!B38)*('Customers revenue and run costs'!H5-1)/('Model inputs'!Q18-1)) -> 175 | I8: =IF(EXACT("Free","Enterprise"),IF(IF(IF(ISERROR('Customers revenue and run costs'!I5=1),'Customers revenue and run costs'!I5=1,IF('Customers revenue and run costs'!I5="","",'Customers revenue and run costs'!I5=1))="",FALSE,IF(ISERROR('Customers revenue and run costs'!I5=1),'Customers revenue and run costs'!I5=1,IF('Customers revenue and run costs'!I5="","",'Customers revenue and run costs'!I5=1))),IF('Model inputs'!L10="","",'Model inputs'!L10),'Customers revenue and run costs'!H8+'Model inputs'!L10),'Model inputs'!B38+('Model inputs'!B8-'Model inputs'!B38)*('Customers revenue and run costs'!I5-1)/('Model inputs'!Q18-1)) -> 200 | J8: =IF(EXACT("Free","Enterprise"),IF(IF(IF(ISERROR('Customers revenue and run costs'!J5=1),'Customers revenue and run costs'!J5=1,IF('Customers revenue and run costs'!J5="","",'Customers revenue and run costs'!J5=1))="",FALSE,IF(ISERROR('Customers revenue and run costs'!J5=1),'Customers revenue and run costs'!J5=1,IF('Customers revenue and run costs'!J5="","",'Customers revenue and run costs'!J5=1))),IF('Model inputs'!M10="","",'Model inputs'!M10),'Customers revenue and run costs'!I8+'Model inputs'!M10),'Model inputs'!B38+('Model inputs'!B8-'Model inputs'!B38)*('Customers revenue and run costs'!J5-1)/('Model inputs'!Q18-1)) -> 225 | K8: =IF(EXACT("Free","Enterprise"),IF(IF(IF(ISERROR('Customers revenue and run costs'!K5=1),'Customers revenue and run costs'!K5=1,IF('Customers revenue and run costs'!K5="","",'Customers revenue and run costs'!K5=1))="",FALSE,IF(ISERROR('Customers revenue and run costs'!K5=1),'Customers revenue and run costs'!K5=1,IF('Customers revenue and run costs'!K5="","",'Customers revenue and run costs'!K5=1))),IF('Model inputs'!N10="","",'Model inputs'!N10),'Customers revenue and run costs'!J8+'Model inputs'!N10),'Model inputs'!B38+('Model inputs'!B8-'Model inputs'!B38)*('Customers revenue and run costs'!K5-1)/('Model inputs'!Q18-1)) -> 250 | L8: =IF(EXACT("Free","Enterprise"),IF(IF(IF(ISERROR('Customers revenue and run costs'!L5=1),'Customers revenue and run costs'!L5=1,IF('Customers revenue and run costs'!L5="","",'Customers revenue and run costs'!L5=1))="",FALSE,IF(ISERROR('Customers revenue and run costs'!L5=1),'Customers revenue and run costs'!L5=1,IF('Customers revenue and run costs'!L5="","",'Customers revenue and run costs'!L5=1))),IF('Model inputs'!O10="","",'Model inputs'!O10),'Customers revenue and run costs'!K8+'Model inputs'!O10),'Model inputs'!B38+('Model inputs'!B8-'Model inputs'!B38)*('Customers revenue and run costs'!L5-1)/('Model inputs'!Q18-1)) -> 275 | M8: =IF(EXACT("Free","Enterprise"),IF(IF(IF(ISERROR('Customers revenue and run costs'!M5=1),'Customers revenue and run costs'!M5=1,IF('Customers revenue and run costs'!M5="","",'Customers revenue and run costs'!M5=1))="",FALSE,IF(ISERROR('Customers revenue and run costs'!M5=1),'Customers revenue and run costs'!M5=1,IF('Customers revenue and run costs'!M5="","",'Customers revenue and run costs'!M5=1))),IF('Model inputs'!P10="","",'Model inputs'!P10),'Customers revenue and run costs'!L8+'Model inputs'!P10),'Model inputs'!B38+('Model inputs'!B8-'Model inputs'!B38)*('Customers revenue and run costs'!M5-1)/('Model inputs'!Q18-1)) -> 300
A9: Team | B9: =IF(EXACT("Team","Enterprise"),IF(IF(IF(ISERROR('Customers revenue and run costs'!B5=1),'Customers revenue and run costs'!B5=1,IF('Customers revenue and run costs'!B5="","",'Customers revenue and run costs'!B5=1))="",FALSE,IF(ISERROR('Customers revenue and run costs'!B5=1),'Customers revenue and run costs'!B5=1,IF('Customers revenue and run costs'!B5="","",'Customers revenue and run costs'!B5=1))),IF('Model inputs'!E10="","",'Model inputs'!E10),'Model inputs'!D59+'Model inputs'!E10),'Model inputs'!B39+('Model inputs'!B9-'Model inputs'!B39)*('Customers revenue and run costs'!B5-1)/('Model inputs'!Q18-1)) -> 2 | C9: =IF(EXACT("Team","Enterprise"),IF(IF(IF(ISERROR('Customers revenue and run costs'!C5=1),'Customers revenue and run costs'!C5=1,IF('Customers revenue and run costs'!C5="","",'Customers revenue and run costs'!C5=1))="",FALSE,IF(ISERROR('Customers revenue and run costs'!C5=1),'Customers revenue and run costs'!C5=1,IF('Customers revenue and run costs'!C5="","",'Customers revenue and run costs'!C5=1))),IF('Model inputs'!F10="","",'Model inputs'!F10),'Customers revenue and run costs'!B9+'Model inputs'!F10),'Model inputs'!B39+('Model inputs'!B9-'Model inputs'!B39)*('Customers revenue and run costs'!C5-1)/('Model inputs'!Q18-1)) -> 5.4545455 | D9: =IF(EXACT("Team","Enterprise"),IF(IF(IF(ISERROR('Customers revenue and run costs'!D5=1),'Customers revenue and run costs'!D5=1,IF('Customers revenue and run costs'!D5="","",'Customers revenue and run costs'!D5=1))="",FALSE,IF(ISERROR('Customers revenue and run costs'!D5=1),'Customers revenue and run costs'!D5=1,IF('Customers revenue and run costs'!D5="","",'Customers revenue and run costs'!D5=1))),IF('Model inputs'!G10="","",'Model inputs'!G10),'Customers revenue and run costs'!C9+'Model inputs'!G10),'Model inputs'!B39+('Model inputs'!B9-'Model inputs'!B39)*('Customers revenue and run costs'!D5-1)/('Model inputs'!Q18-1)) -> 8.9090909 | E9: =IF(EXACT("Team","Enterprise"),IF(IF(IF(ISERROR('Customers revenue and run costs'!E5=1),'Customers revenue and run costs'!E5=1,IF('Customers revenue and run costs'!E5="","",'Customers revenue and run costs'!E5=1))="",FALSE,IF(ISERROR('Customers revenue and run costs'!E5=1),'Customers revenue and run costs'!E5=1,IF('Customers revenue and run costs'!E5="","",'Customers revenue and run costs'!E5=1))),IF('Model inputs'!H10="","",'Model inputs'!H10),'Customers revenue and run costs'!D9+'Model inputs'!H10),'Model inputs'!B39+('Model inputs'!B9-'Model inputs'!B39)*('Customers revenue and run costs'!E5-1)/('Model inputs'!Q18-1)) -> 12.363636 | F9: =IF(EXACT("Team","Enterprise"),IF(IF(IF(ISERROR('Customers revenue and run costs'!F5=1),'Customers revenue and run costs'!F5=1,IF('Customers revenue and run costs'!F5="","",'Customers revenue and run costs'!F5=1))="",FALSE,IF(ISERROR('Customers revenue and run costs'!F5=1),'Customers revenue and run costs'!F5=1,IF('Customers revenue and run costs'!F5="","",'Customers revenue and run costs'!F5=1))),IF('Model inputs'!I10="","",'Model inputs'!I10),'Customers revenue and run costs'!E9+'Model inputs'!I10),'Model inputs'!B39+('Model inputs'!B9-'Model inputs'!B39)*('Customers revenue and run costs'!F5-1)/('Model inputs'!Q18-1)) -> 15.818182 | G9: =IF(EXACT("Team","Enterprise"),IF(IF(IF(ISERROR('Customers revenue and run costs'!G5=1),'Customers revenue and run costs'!G5=1,IF('Customers revenue and run costs'!G5="","",'Customers revenue and run costs'!G5=1))="",FALSE,IF(ISERROR('Customers revenue and run costs'!G5=1),'Customers revenue and run costs'!G5=1,IF('Customers revenue and run costs'!G5="","",'Customers revenue and run costs'!G5=1))),IF('Model inputs'!J10="","",'Model inputs'!J10),'Customers revenue and run costs'!F9+'Model inputs'!J10),'Model inputs'!B39+('Model inputs'!B9-'Model inputs'!B39)*('Customers revenue and run costs'!G5-1)/('Model inputs'!Q18-1)) -> 19.272727 | H9: =IF(EXACT("Team","Enterprise"),IF(IF(IF(ISERROR('Customers revenue and run costs'!H5=1),'Customers revenue and run costs'!H5=1,IF('Customers revenue and run costs'!H5="","",'Customers revenue and run costs'!H5=1))="",FALSE,IF(ISERROR('Customers revenue and run costs'!H5=1),'Customers revenue and run costs'!H5=1,IF('Customers revenue and run costs'!H5="","",'Customers revenue and run costs'!H5=1))),IF('Model inputs'!K10="","",'Model inputs'!K10),'Customers revenue and run costs'!G9+'Model inputs'!K10),'Model inputs'!B39+('Model inputs'!B9-'Model inputs'!B39)*('Customers revenue and run costs'!H5-1)/('Model inputs'!Q18-1)) -> 22.727273 | I9: =IF(EXACT("Team","Enterprise"),IF(IF(IF(ISERROR('Customers revenue and run costs'!I5=1),'Customers revenue and run costs'!I5=1,IF('Customers revenue and run costs'!I5="","",'Customers revenue and run costs'!I5=1))="",FALSE,IF(ISERROR('Customers revenue and run costs'!I5=1),'Customers revenue and run costs'!I5=1,IF('Customers revenue and run costs'!I5="","",'Customers revenue and run costs'!I5=1))),IF('Model inputs'!L10="","",'Model inputs'!L10),'Customers revenue and run costs'!H9+'Model inputs'!L10),'Model inputs'!B39+('Model inputs'!B9-'Model inputs'!B39)*('Customers revenue and run costs'!I5-1)/('Model inputs'!Q18-1)) -> 26.181818 | J9: =IF(EXACT("Team","Enterprise"),IF(IF(IF(ISERROR('Customers revenue and run costs'!J5=1),'Customers revenue and run costs'!J5=1,IF('Customers revenue and run costs'!J5="","",'Customers revenue and run costs'!J5=1))="",FALSE,IF(ISERROR('Customers revenue and run costs'!J5=1),'Customers revenue and run costs'!J5=1,IF('Customers revenue and run costs'!J5="","",'Customers revenue and run costs'!J5=1))),IF('Model inputs'!M10="","",'Model inputs'!M10),'Customers revenue and run costs'!I9+'Model inputs'!M10),'Model inputs'!B39+('Model inputs'!B9-'Model inputs'!B39)*('Customers revenue and run costs'!J5-1)/('Model inputs'!Q18-1)) -> 29.636364 | K9: =IF(EXACT("Team","Enterprise"),IF(IF(IF(ISERROR('Customers revenue and run costs'!K5=1),'Customers revenue and run costs'!K5=1,IF('Customers revenue and run costs'!K5="","",'Customers revenue and run costs'!K5=1))="",FALSE,IF(ISERROR('Customers revenue and run costs'!K5=1),'Customers revenue and run costs'!K5=1,IF('Customers revenue and run costs'!K5="","",'Customers revenue and run costs'!K5=1))),IF('Model inputs'!N10="","",'Model inputs'!N10),'Customers revenue and run costs'!J9+'Model inputs'!N10),'Model inputs'!B39+('Model inputs'!B9-'Model inputs'!B39)*('Customers revenue and run costs'!K5-1)/('Model inputs'!Q18-1)) -> 33.090909 | L9: =IF(EXACT("Team","Enterprise"),IF(IF(IF(ISERROR('Customers revenue and run costs'!L5=1),'Customers revenue and run costs'!L5=1,IF('Customers revenue and run costs'!L5="","",'Customers revenue and run costs'!L5=1))="",FALSE,IF(ISERROR('Customers revenue and run costs'!L5=1),'Customers revenue and run costs'!L5=1,IF('Customers revenue and run costs'!L5="","",'Customers revenue and run costs'!L5=1))),IF('Model inputs'!O10="","",'Model inputs'!O10),'Customers revenue and run costs'!K9+'Model inputs'!O10),'Model inputs'!B39+('Model inputs'!B9-'Model inputs'!B39)*('Customers revenue and run costs'!L5-1)/('Model inputs'!Q18-1)) -> 36.545455 | M9: =IF(EXACT("Team","Enterprise"),IF(IF(IF(ISERROR('Customers revenue and run costs'!M5=1),'Customers revenue and run costs'!M5=1,IF('Customers revenue and run costs'!M5="","",'Customers revenue and run costs'!M5=1))="",FALSE,IF(ISERROR('Customers revenue and run costs'!M5=1),'Customers revenue and run costs'!M5=1,IF('Customers revenue and run costs'!M5="","",'Customers revenue and run costs'!M5=1))),IF('Model inputs'!P10="","",'Model inputs'!P10),'Customers revenue and run costs'!L9+'Model inputs'!P10),'Model inputs'!B39+('Model inputs'!B9-'Model inputs'!B39)*('Customers revenue and run costs'!M5-1)/('Model inputs'!Q18-1)) -> 40
A10: Forecast subscription revenue | B10: =SUM('Customers revenue and run costs'!B11,'Customers revenue and run costs'!B12,'Customers revenue and run costs'!B13) -> 158 | C10: =SUM('Customers revenue and run costs'!C11,'Customers revenue and run costs'!C12,'Customers revenue and run costs'!C13) -> 430.90909 | D10: =SUM('Customers revenue and run costs'!D11,'Customers revenue and run costs'!D12,'Customers revenue and run costs'!D13) -> 703.81818 | E10: =SUM('Customers revenue and run costs'!E11,'Customers revenue and run costs'!E12,'Customers revenue and run costs'!E13) -> 976.72727 | F10: =SUM('Customers revenue and run costs'!F11,'Customers revenue and run costs'!F12,'Customers revenue and run costs'!F13) -> 1249.6364 | G10: =SUM('Customers revenue and run costs'!G11,'Customers revenue and run costs'!G12,'Customers revenue and run costs'!G13) -> 1522.5455 | H10: =SUM('Customers revenue and run costs'!H11,'Customers revenue and run costs'!H12,'Customers revenue and run costs'!H13) -> 1795.4545 | I10: =SUM('Customers revenue and run costs'!I11,'Customers revenue and run costs'!I12,'Customers revenue and run costs'!I13) -> 2068.3636 | ... M10: =SUM('Customers revenue and run costs'!M11,'Customers revenue and run costs'!M12,'Customers revenue and run costs'!M13) -> 4660
A11: Enterprise | B11: ='Customers revenue and run costs'!B7*'Model inputs'!B33 -> 0 | C11: ='Customers revenue and run costs'!C7*'Model inputs'!B33 -> 0 | D11: ='Customers revenue and run costs'!D7*'Model inputs'!B33 -> 0 | E11: ='Customers revenue and run costs'!E7*'Model inputs'!B33 -> 0 | F11: ='Customers revenue and run costs'!F7*'Model inputs'!B33 -> 0 | G11: ='Customers revenue and run costs'!G7*'Model inputs'!B33 -> 0 | H11: ='Customers revenue and run costs'!H7*'Model inputs'!B33 -> 0 | I11: ='Customers revenue and run costs'!I7*'Model inputs'!B33 -> 0 | J11: ='Customers revenue and run costs'!J7*'Model inputs'!B33 -> 1500 | K11: ='Customers revenue and run costs'!K7*'Model inputs'!B33 -> 1500 | L11: ='Customers revenue and run costs'!L7*'Model inputs'!B33 -> 1500 | M11: ='Customers revenue and run costs'!M7*'Model inputs'!B33 -> 1500
A12: Free | B12: ='Customers revenue and run costs'!B8*'Model inputs'!B34 -> 0 | C12: ='Customers revenue and run costs'!C8*'Model inputs'!B34 -> 0 | D12: ='Customers revenue and run costs'!D8*'Model inputs'!B34 -> 0 | E12: ='Customers revenue and run costs'!E8*'Model inputs'!B34 -> 0 | F12: ='Customers revenue and run costs'!F8*'Model inputs'!B34 -> 0 | G12: ='Customers revenue and run costs'!G8*'Model inputs'!B34 -> 0 | H12: ='Customers revenue and run costs'!H8*'Model inputs'!B34 -> 0 | I12: ='Customers revenue and run costs'!I8*'Model inputs'!B34 -> 0 | J12: ='Customers revenue and run costs'!J8*'Model inputs'!B34 -> 0 | K12: ='Customers revenue and run costs'!K8*'Model inputs'!B34 -> 0 | L12: ='Customers revenue and run costs'!L8*'Model inputs'!B34 -> 0 | M12: ='Customers revenue and run costs'!M8*'Model inputs'!B34 -> 0
A13: Team | B13: ='Customers revenue and run costs'!B9*'Model inputs'!B35 -> 158 | C13: ='Customers revenue and run costs'!C9*'Model inputs'!B35 -> 430.90909 | D13: ='Customers revenue and run costs'!D9*'Model inputs'!B35 -> 703.81818 | E13: ='Customers revenue and run costs'!E9*'Model inputs'!B35 -> 976.72727 | F13: ='Customers revenue and run costs'!F9*'Model inputs'!B35 -> 1249.6364 | G13: ='Customers revenue and run costs'!G9*'Model inputs'!B35 -> 1522.5455 | H13: ='Customers revenue and run costs'!H9*'Model inputs'!B35 -> 1795.4545 | I13: ='Customers revenue and run costs'!I9*'Model inputs'!B35 -> 2068.3636 | J13: ='Customers revenue and run costs'!J9*'Model inputs'!B35 -> 2341.2727 | K13: ='Customers revenue and run costs'!K9*'Model inputs'!B35 -> 2614.1818 | L13: ='Customers revenue and run costs'!L9*'Model inputs'!B35 -> 2887.0909 | M13: ='Customers revenue and run costs'!M9*'Model inputs'!B35 -> 3160
A14: Forecast run costs | B14: =SUM('Customers revenue and run costs'!B15,'Customers revenue and run costs'!B16,'Customers revenue and run costs'!B17) -> 114.7 | C14: =SUM('Customers revenue and run costs'!C15,'Customers revenue and run costs'!C16,'Customers revenue and run costs'!C17) -> 256.45455 | D14: =SUM('Customers revenue and run costs'!D15,'Customers revenue and run costs'!D16,'Customers revenue and run costs'!D17) -> 398.20909 | E14: =SUM('Customers revenue and run costs'!E15,'Customers revenue and run costs'!E16,'Customers revenue and run costs'!E17) -> 539.96364 | F14: =SUM('Customers revenue and run costs'!F15,'Customers revenue and run costs'!F16,'Customers revenue and run costs'!F17) -> 681.71818 | G14: =SUM('Customers revenue and run costs'!G15,'Customers revenue and run costs'!G16,'Customers revenue and run costs'!G17) -> 823.47273 | H14: =SUM('Customers revenue and run costs'!H15,'Customers revenue and run costs'!H16,'Customers revenue and run costs'!H17) -> 965.22727 | I14: =SUM('Customers revenue and run costs'!I15,'Customers revenue and run costs'!I16,'Customers revenue and run costs'!I17) -> 1106.9818 | ... M14: =SUM('Customers revenue and run costs'!M15,'Customers revenue and run costs'!M16,'Customers revenue and run costs'!M17) -> 1829
A15: Enterprise | B15: ='Customers revenue and run costs'!B7*'Model inputs'!B12*'Model inputs'!B41 -> 0 | C15: ='Customers revenue and run costs'!C7*'Model inputs'!B12*'Model inputs'!B41 -> 0 | D15: ='Customers revenue and run costs'!D7*'Model inputs'!B12*'Model inputs'!B41 -> 0 | E15: ='Customers revenue and run costs'!E7*'Model inputs'!B12*'Model inputs'!B41 -> 0 | F15: ='Customers revenue and run costs'!F7*'Model inputs'!B12*'Model inputs'!B41 -> 0 | G15: ='Customers revenue and run costs'!G7*'Model inputs'!B12*'Model inputs'!B41 -> 0 | H15: ='Customers revenue and run costs'!H7*'Model inputs'!B12*'Model inputs'!B41 -> 0 | I15: ='Customers revenue and run costs'!I7*'Model inputs'!B12*'Model inputs'!B41 -> 0 | J15: ='Customers revenue and run costs'!J7*'Model inputs'!B12*'Model inputs'!B41 -> 155 | K15: ='Customers revenue and run costs'!K7*'Model inputs'!B12*'Model inputs'!B41 -> 155 | L15: ='Customers revenue and run costs'!L7*'Model inputs'!B12*'Model inputs'!B41 -> 155 | M15: ='Customers revenue and run costs'!M7*'Model inputs'!B12*'Model inputs'!B41 -> 155
A16: Free | B16: ='Customers revenue and run costs'!B8*'Model inputs'!B13*'Model inputs'!B41 -> 77.5 | C16: ='Customers revenue and run costs'!C8*'Model inputs'!B13*'Model inputs'!B41 -> 155 | D16: ='Customers revenue and run costs'!D8*'Model inputs'!B13*'Model inputs'!B41 -> 232.5 | E16: ='Customers revenue and run costs'!E8*'Model inputs'!B13*'Model inputs'!B41 -> 310 | F16: ='Customers revenue and run costs'!F8*'Model inputs'!B13*'Model inputs'!B41 -> 387.5 | G16: ='Customers revenue and run costs'!G8*'Model inputs'!B13*'Model inputs'!B41 -> 465 | H16: ='Customers revenue and run costs'!H8*'Model inputs'!B13*'Model inputs'!B41 -> 542.5 | I16: ='Customers revenue and run costs'!I8*'Model inputs'!B13*'Model inputs'!B41 -> 620 | J16: ='Customers revenue and run costs'!J8*'Model inputs'!B13*'Model inputs'!B41 -> 697.5 | K16: ='Customers revenue and run costs'!K8*'Model inputs'!B13*'Model inputs'!B41 -> 775 | L16: ='Customers revenue and run costs'!L8*'Model inputs'!B13*'Model inputs'!B41 -> 852.5 | M16: ='Customers revenue and run costs'!M8*'Model inputs'!B13*'Model inputs'!B41 -> 930
A17: Team | B17: ='Customers revenue and run costs'!B9*'Model inputs'!B14*'Model inputs'!B41 -> 37.2 | C17: ='Customers revenue and run costs'!C9*'Model inputs'!B14*'Model inputs'!B41 -> 101.45455 | D17: ='Customers revenue and run costs'!D9*'Model inputs'!B14*'Model inputs'!B41 -> 165.70909 | E17: ='Customers revenue and run costs'!E9*'Model inputs'!B14*'Model inputs'!B41 -> 229.96364 | F17: ='Customers revenue and run costs'!F9*'Model inputs'!B14*'Model inputs'!B41 -> 294.21818 | G17: ='Customers revenue and run costs'!G9*'Model inputs'!B14*'Model inputs'!B41 -> 358.47273 | H17: ='Customers revenue and run costs'!H9*'Model inputs'!B14*'Model inputs'!B41 -> 422.72727 | I17: ='Customers revenue and run costs'!I9*'Model inputs'!B14*'Model inputs'!B41 -> 486.98182 | J17: ='Customers revenue and run costs'!J9*'Model inputs'!B14*'Model inputs'!B41 -> 551.23636 | K17: ='Customers revenue and run costs'!K9*'Model inputs'!B14*'Model inputs'!B41 -> 615.49091 | L17: ='Customers revenue and run costs'!L9*'Model inputs'!B14*'Model inputs'!B41 -> 679.74545 | M17: ='Customers revenue and run costs'!M9*'Model inputs'!B14*'Model inputs'!B41 -> 744

Sheet Monthly headcount and payroll
A1: Monthly headcount and payroll
A2: Susanoo — 12-Month Forecast · Susanoo — Base
A4: Variable / dimension | B4: 2026-11 | C4: 2026-12 | D4: 2027-01 | E4: 2027-02 | F4: 2027-03 | G4: 2027-04 | H4: 2027-05 | I4: 2027-06 | J4: 2027-07 | K4: 2027-08 | L4: 2027-09 | M4: 2027-10
A5: Forecast headcount | B5: =SUM('Monthly headcount and payroll'!B6,'Monthly headcount and payroll'!B7,'Monthly headcount and payroll'!B8) -> 2 | C5: =SUM('Monthly headcount and payroll'!C6,'Monthly headcount and payroll'!C7,'Monthly headcount and payroll'!C8) -> 2 | D5: =SUM('Monthly headcount and payroll'!D6,'Monthly headcount and payroll'!D7,'Monthly headcount and payroll'!D8) -> 2 | E5: =SUM('Monthly headcount and payroll'!E6,'Monthly headcount and payroll'!E7,'Monthly headcount and payroll'!E8) -> 2 | F5: =SUM('Monthly headcount and payroll'!F6,'Monthly headcount and payroll'!F7,'Monthly headcount and payroll'!F8) -> 2 | G5: =SUM('Monthly headcount and payroll'!G6,'Monthly headcount and payroll'!G7,'Monthly headcount and payroll'!G8) -> 2 | H5: =SUM('Monthly headcount and payroll'!H6,'Monthly headcount and payroll'!H7,'Monthly headcount and payroll'!H8) -> 2 | I5: =SUM('Monthly headcount and payroll'!I6,'Monthly headcount and payroll'!I7,'Monthly headcount and payroll'!I8) -> 2 | ... M5: =SUM('Monthly headcount and payroll'!M6,'Monthly headcount and payroll'!M7,'Monthly headcount and payroll'!M8) -> 2
A6: Founder 1 | B6: ='Model inputs'!B45*IF(IF(IF(IF(ISERROR('Customers revenue and run costs'!B5>='Model inputs'!B53),'Customers revenue and run costs'!B5>='Model inputs'!B53,IF(OR('Customers revenue and run costs'!B5="",'Model inputs'!B53=""),"",'Customers revenue and run costs'!B5>='Model inputs'!B53))="",FALSE,IF(ISERROR('Customers revenue and run costs'!B5>='Model inputs'!B53),'Customers revenue and run costs'!B5>='Model inputs'!B53,IF(OR('Customers revenue and run costs'!B5="",'Model inputs'!B53=""),"",'Customers revenue and run costs'!B5>='Model inputs'!B53))),1,0)="",0,IF(IF(IF(ISERROR('Customers revenue and run costs'!B5>='Model inputs'!B53),'Customers revenue and run costs'!B5>='Model inputs'!B53,IF(OR('Customers revenue and run costs'!B5="",'Model inputs'!B53=""),"",'Customers revenue and run costs'!B5>='Model inputs'!B53))="",FALSE,IF(ISERROR('Customers revenue and run costs'!B5>='Model inputs'!B53),'Customers revenue and run costs'!B5>='Model inputs'!B53,IF(OR('Customers revenue and run costs'!B5="",'Model inputs'!B53=""),"",'Customers revenue and run costs'!B5>='Model inputs'!B53))),1,0)) -> 1 | C6: ='Model inputs'!B45*IF(IF(IF(IF(ISERROR('Customers revenue and run costs'!C5>='Model inputs'!B53),'Customers revenue and run costs'!C5>='Model inputs'!B53,IF(OR('Customers revenue and run costs'!C5="",'Model inputs'!B53=""),"",'Customers revenue and run costs'!C5>='Model inputs'!B53))="",FALSE,IF(ISERROR('Customers revenue and run costs'!C5>='Model inputs'!B53),'Customers revenue and run costs'!C5>='Model inputs'!B53,IF(OR('Customers revenue and run costs'!C5="",'Model inputs'!B53=""),"",'Customers revenue and run costs'!C5>='Model inputs'!B53))),1,0)="",0,IF(IF(IF(ISERROR('Customers revenue and run costs'!C5>='Model inputs'!B53),'Customers revenue and run costs'!C5>='Model inputs'!B53,IF(OR('Customers revenue and run costs'!C5="",'Model inputs'!B53=""),"",'Customers revenue and run costs'!C5>='Model inputs'!B53))="",FALSE,IF(ISERROR('Customers revenue and run costs'!C5>='Model inputs'!B53),'Customers revenue and run costs'!C5>='Model inputs'!B53,IF(OR('Customers revenue and run costs'!C5="",'Model inputs'!B53=""),"",'Customers revenue and run costs'!C5>='Model inputs'!B53))),1,0)) -> 1 | D6: ='Model inputs'!B45*IF(IF(IF(IF(ISERROR('Customers revenue and run costs'!D5>='Model inputs'!B53),'Customers revenue and run costs'!D5>='Model inputs'!B53,IF(OR('Customers revenue and run costs'!D5="",'Model inputs'!B53=""),"",'Customers revenue and run costs'!D5>='Model inputs'!B53))="",FALSE,IF(ISERROR('Customers revenue and run costs'!D5>='Model inputs'!B53),'Customers revenue and run costs'!D5>='Model inputs'!B53,IF(OR('Customers revenue and run costs'!D5="",'Model inputs'!B53=""),"",'Customers revenue and run costs'!D5>='Model inputs'!B53))),1,0)="",0,IF(IF(IF(ISERROR('Customers revenue and run costs'!D5>='Model inputs'!B53),'Customers revenue and run costs'!D5>='Model inputs'!B53,IF(OR('Customers revenue and run costs'!D5="",'Model inputs'!B53=""),"",'Customers revenue and run costs'!D5>='Model inputs'!B53))="",FALSE,IF(ISERROR('Customers revenue and run costs'!D5>='Model inputs'!B53),'Customers revenue and run costs'!D5>='Model inputs'!B53,IF(OR('Customers revenue and run costs'!D5="",'Model inputs'!B53=""),"",'Customers revenue and run costs'!D5>='Model inputs'!B53))),1,0)) -> 1 | E6: ='Model inputs'!B45*IF(IF(IF(IF(ISERROR('Customers revenue and run costs'!E5>='Model inputs'!B53),'Customers revenue and run costs'!E5>='Model inputs'!B53,IF(OR('Customers revenue and run costs'!E5="",'Model inputs'!B53=""),"",'Customers revenue and run costs'!E5>='Model inputs'!B53))="",FALSE,IF(ISERROR('Customers revenue and run costs'!E5>='Model inputs'!B53),'Customers revenue and run costs'!E5>='Model inputs'!B53,IF(OR('Customers revenue and run costs'!E5="",'Model inputs'!B53=""),"",'Customers revenue and run costs'!E5>='Model inputs'!B53))),1,0)="",0,IF(IF(IF(ISERROR('Customers revenue and run costs'!E5>='Model inputs'!B53),'Customers revenue and run costs'!E5>='Model inputs'!B53,IF(OR('Customers revenue and run costs'!E5="",'Model inputs'!B53=""),"",'Customers revenue and run costs'!E5>='Model inputs'!B53))="",FALSE,IF(ISERROR('Customers revenue and run costs'!E5>='Model inputs'!B53),'Customers revenue and run costs'!E5>='Model inputs'!B53,IF(OR('Customers revenue and run costs'!E5="",'Model inputs'!B53=""),"",'Customers revenue and run costs'!E5>='Model inputs'!B53))),1,0)) -> 1 | F6: ='Model inputs'!B45*IF(IF(IF(IF(ISERROR('Customers revenue and run costs'!F5>='Model inputs'!B53),'Customers revenue and run costs'!F5>='Model inputs'!B53,IF(OR('Customers revenue and run costs'!F5="",'Model inputs'!B53=""),"",'Customers revenue and run costs'!F5>='Model inputs'!B53))="",FALSE,IF(ISERROR('Customers revenue and run costs'!F5>='Model inputs'!B53),'Customers revenue and run costs'!F5>='Model inputs'!B53,IF(OR('Customers revenue and run costs'!F5="",'Model inputs'!B53=""),"",'Customers revenue and run costs'!F5>='Model inputs'!B53))),1,0)="",0,IF(IF(IF(ISERROR('Customers revenue and run costs'!F5>='Model inputs'!B53),'Customers revenue and run costs'!F5>='Model inputs'!B53,IF(OR('Customers revenue and run costs'!F5="",'Model inputs'!B53=""),"",'Customers revenue and run costs'!F5>='Model inputs'!B53))="",FALSE,IF(ISERROR('Customers revenue and run costs'!F5>='Model inputs'!B53),'Customers revenue and run costs'!F5>='Model inputs'!B53,IF(OR('Customers revenue and run costs'!F5="",'Model inputs'!B53=""),"",'Customers revenue and run costs'!F5>='Model inputs'!B53))),1,0)) -> 1 | G6: ='Model inputs'!B45*IF(IF(IF(IF(ISERROR('Customers revenue and run costs'!G5>='Model inputs'!B53),'Customers revenue and run costs'!G5>='Model inputs'!B53,IF(OR('Customers revenue and run costs'!G5="",'Model inputs'!B53=""),"",'Customers revenue and run costs'!G5>='Model inputs'!B53))="",FALSE,IF(ISERROR('Customers revenue and run costs'!G5>='Model inputs'!B53),'Customers revenue and run costs'!G5>='Model inputs'!B53,IF(OR('Customers revenue and run costs'!G5="",'Model inputs'!B53=""),"",'Customers revenue and run costs'!G5>='Model inputs'!B53))),1,0)="",0,IF(IF(IF(ISERROR('Customers revenue and run costs'!G5>='Model inputs'!B53),'Customers revenue and run costs'!G5>='Model inputs'!B53,IF(OR('Customers revenue and run costs'!G5="",'Model inputs'!B53=""),"",'Customers revenue and run costs'!G5>='Model inputs'!B53))="",FALSE,IF(ISERROR('Customers revenue and run costs'!G5>='Model inputs'!B53),'Customers revenue and run costs'!G5>='Model inputs'!B53,IF(OR('Customers revenue and run costs'!G5="",'Model inputs'!B53=""),"",'Customers revenue and run costs'!G5>='Model inputs'!B53))),1,0)) -> 1 | H6: ='Model inputs'!B45*IF(IF(IF(IF(ISERROR('Customers revenue and run costs'!H5>='Model inputs'!B53),'Customers revenue and run costs'!H5>='Model inputs'!B53,IF(OR('Customers revenue and run costs'!H5="",'Model inputs'!B53=""),"",'Customers revenue and run costs'!H5>='Model inputs'!B53))="",FALSE,IF(ISERROR('Customers revenue and run costs'!H5>='Model inputs'!B53),'Customers revenue and run costs'!H5>='Model inputs'!B53,IF(OR('Customers revenue and run costs'!H5="",'Model inputs'!B53=""),"",'Customers revenue and run costs'!H5>='Model inputs'!B53))),1,0)="",0,IF(IF(IF(ISERROR('Customers revenue and run costs'!H5>='Model inputs'!B53),'Customers revenue and run costs'!H5>='Model inputs'!B53,IF(OR('Customers revenue and run costs'!H5="",'Model inputs'!B53=""),"",'Customers revenue and run costs'!H5>='Model inputs'!B53))="",FALSE,IF(ISERROR('Customers revenue and run costs'!H5>='Model inputs'!B53),'Customers revenue and run costs'!H5>='Model inputs'!B53,IF(OR('Customers revenue and run costs'!H5="",'Model inputs'!B53=""),"",'Customers revenue and run costs'!H5>='Model inputs'!B53))),1,0)) -> 1 | I6: ='Model inputs'!B45*IF(IF(IF(IF(ISERROR('Customers revenue and run costs'!I5>='Model inputs'!B53),'Customers revenue and run costs'!I5>='Model inputs'!B53,IF(OR('Customers revenue and run costs'!I5="",'Model inputs'!B53=""),"",'Customers revenue and run costs'!I5>='Model inputs'!B53))="",FALSE,IF(ISERROR('Customers revenue and run costs'!I5>='Model inputs'!B53),'Customers revenue and run costs'!I5>='Model inputs'!B53,IF(OR('Customers revenue and run costs'!I5="",'Model inputs'!B53=""),"",'Customers revenue and run costs'!I5>='Model inputs'!B53))),1,0)="",0,IF(IF(IF(ISERROR('Customers revenue and run costs'!I5>='Model inputs'!B53),'Customers revenue and run costs'!I5>='Model inputs'!B53,IF(OR('Customers revenue and run costs'!I5="",'Model inputs'!B53=""),"",'Customers revenue and run costs'!I5>='Model inputs'!B53))="",FALSE,IF(ISERROR('Customers revenue and run costs'!I5>='Model inputs'!B53),'Customers revenue and run costs'!I5>='Model inputs'!B53,IF(OR('Customers revenue and run costs'!I5="",'Model inputs'!B53=""),"",'Customers revenue and run costs'!I5>='Model inputs'!B53))),1,0)) -> 1 | J6: ='Model inputs'!B45*IF(IF(IF(IF(ISERROR('Customers revenue and run costs'!J5>='Model inputs'!B53),'Customers revenue and run costs'!J5>='Model inputs'!B53,IF(OR('Customers revenue and run costs'!J5="",'Model inputs'!B53=""),"",'Customers revenue and run costs'!J5>='Model inputs'!B53))="",FALSE,IF(ISERROR('Customers revenue and run costs'!J5>='Model inputs'!B53),'Customers revenue and run costs'!J5>='Model inputs'!B53,IF(OR('Customers revenue and run costs'!J5="",'Model inputs'!B53=""),"",'Customers revenue and run costs'!J5>='Model inputs'!B53))),1,0)="",0,IF(IF(IF(ISERROR('Customers revenue and run costs'!J5>='Model inputs'!B53),'Customers revenue and run costs'!J5>='Model inputs'!B53,IF(OR('Customers revenue and run costs'!J5="",'Model inputs'!B53=""),"",'Customers revenue and run costs'!J5>='Model inputs'!B53))="",FALSE,IF(ISERROR('Customers revenue and run costs'!J5>='Model inputs'!B53),'Customers revenue and run costs'!J5>='Model inputs'!B53,IF(OR('Customers revenue and run costs'!J5="",'Model inputs'!B53=""),"",'Customers revenue and run costs'!J5>='Model inputs'!B53))),1,0)) -> 1 | K6: ='Model inputs'!B45*IF(IF(IF(IF(ISERROR('Customers revenue and run costs'!K5>='Model inputs'!B53),'Customers revenue and run costs'!K5>='Model inputs'!B53,IF(OR('Customers revenue and run costs'!K5="",'Model inputs'!B53=""),"",'Customers revenue and run costs'!K5>='Model inputs'!B53))="",FALSE,IF(ISERROR('Customers revenue and run costs'!K5>='Model inputs'!B53),'Customers revenue and run costs'!K5>='Model inputs'!B53,IF(OR('Customers revenue and run costs'!K5="",'Model inputs'!B53=""),"",'Customers revenue and run costs'!K5>='Model inputs'!B53))),1,0)="",0,IF(IF(IF(ISERROR('Customers revenue and run costs'!K5>='Model inputs'!B53),'Customers revenue and run costs'!K5>='Model inputs'!B53,IF(OR('Customers revenue and run costs'!K5="",'Model inputs'!B53=""),"",'Customers revenue and run costs'!K5>='Model inputs'!B53))="",FALSE,IF(ISERROR('Customers revenue and run costs'!K5>='Model inputs'!B53),'Customers revenue and run costs'!K5>='Model inputs'!B53,IF(OR('Customers revenue and run costs'!K5="",'Model inputs'!B53=""),"",'Customers revenue and run costs'!K5>='Model inputs'!B53))),1,0)) -> 1 | L6: ='Model inputs'!B45*IF(IF(IF(IF(ISERROR('Customers revenue and run costs'!L5>='Model inputs'!B53),'Customers revenue and run costs'!L5>='Model inputs'!B53,IF(OR('Customers revenue and run costs'!L5="",'Model inputs'!B53=""),"",'Customers revenue and run costs'!L5>='Model inputs'!B53))="",FALSE,IF(ISERROR('Customers revenue and run costs'!L5>='Model inputs'!B53),'Customers revenue and run costs'!L5>='Model inputs'!B53,IF(OR('Customers revenue and run costs'!L5="",'Model inputs'!B53=""),"",'Customers revenue and run costs'!L5>='Model inputs'!B53))),1,0)="",0,IF(IF(IF(ISERROR('Customers revenue and run costs'!L5>='Model inputs'!B53),'Customers revenue and run costs'!L5>='Model inputs'!B53,IF(OR('Customers revenue and run costs'!L5="",'Model inputs'!B53=""),"",'Customers revenue and run costs'!L5>='Model inputs'!B53))="",FALSE,IF(ISERROR('Customers revenue and run costs'!L5>='Model inputs'!B53),'Customers revenue and run costs'!L5>='Model inputs'!B53,IF(OR('Customers revenue and run costs'!L5="",'Model inputs'!B53=""),"",'Customers revenue and run costs'!L5>='Model inputs'!B53))),1,0)) -> 1 | M6: ='Model inputs'!B45*IF(IF(IF(IF(ISERROR('Customers revenue and run costs'!M5>='Model inputs'!B53),'Customers revenue and run costs'!M5>='Model inputs'!B53,IF(OR('Customers revenue and run costs'!M5="",'Model inputs'!B53=""),"",'Customers revenue and run costs'!M5>='Model inputs'!B53))="",FALSE,IF(ISERROR('Customers revenue and run costs'!M5>='Model inputs'!B53),'Customers revenue and run costs'!M5>='Model inputs'!B53,IF(OR('Customers revenue and run costs'!M5="",'Model inputs'!B53=""),"",'Customers revenue and run costs'!M5>='Model inputs'!B53))),1,0)="",0,IF(IF(IF(ISERROR('Customers revenue and run costs'!M5>='Model inputs'!B53),'Customers revenue and run costs'!M5>='Model inputs'!B53,IF(OR('Customers revenue and run costs'!M5="",'Model inputs'!B53=""),"",'Customers revenue and run costs'!M5>='Model inputs'!B53))="",FALSE,IF(ISERROR('Customers revenue and run costs'!M5>='Model inputs'!B53),'Customers revenue and run costs'!M5>='Model inputs'!B53,IF(OR('Customers revenue and run costs'!M5="",'Model inputs'!B53=""),"",'Customers revenue and run costs'!M5>='Model inputs'!B53))),1,0)) -> 1
A7: Founder 2 | B7: ='Model inputs'!B46*IF(IF(IF(IF(ISERROR('Customers revenue and run costs'!B5>='Model inputs'!B54),'Customers revenue and run costs'!B5>='Model inputs'!B54,IF(OR('Customers revenue and run costs'!B5="",'Model inputs'!B54=""),"",'Customers revenue and run costs'!B5>='Model inputs'!B54))="",FALSE,IF(ISERROR('Customers revenue and run costs'!B5>='Model inputs'!B54),'Customers revenue and run costs'!B5>='Model inputs'!B54,IF(OR('Customers revenue and run costs'!B5="",'Model inputs'!B54=""),"",'Customers revenue and run costs'!B5>='Model inputs'!B54))),1,0)="",0,IF(IF(IF(ISERROR('Customers revenue and run costs'!B5>='Model inputs'!B54),'Customers revenue and run costs'!B5>='Model inputs'!B54,IF(OR('Customers revenue and run costs'!B5="",'Model inputs'!B54=""),"",'Customers revenue and run costs'!B5>='Model inputs'!B54))="",FALSE,IF(ISERROR('Customers revenue and run costs'!B5>='Model inputs'!B54),'Customers revenue and run costs'!B5>='Model inputs'!B54,IF(OR('Customers revenue and run costs'!B5="",'Model inputs'!B54=""),"",'Customers revenue and run costs'!B5>='Model inputs'!B54))),1,0)) -> 1 | C7: ='Model inputs'!B46*IF(IF(IF(IF(ISERROR('Customers revenue and run costs'!C5>='Model inputs'!B54),'Customers revenue and run costs'!C5>='Model inputs'!B54,IF(OR('Customers revenue and run costs'!C5="",'Model inputs'!B54=""),"",'Customers revenue and run costs'!C5>='Model inputs'!B54))="",FALSE,IF(ISERROR('Customers revenue and run costs'!C5>='Model inputs'!B54),'Customers revenue and run costs'!C5>='Model inputs'!B54,IF(OR('Customers revenue and run costs'!C5="",'Model inputs'!B54=""),"",'Customers revenue and run costs'!C5>='Model inputs'!B54))),1,0)="",0,IF(IF(IF(ISERROR('Customers revenue and run costs'!C5>='Model inputs'!B54),'Customers revenue and run costs'!C5>='Model inputs'!B54,IF(OR('Customers revenue and run costs'!C5="",'Model inputs'!B54=""),"",'Customers revenue and run costs'!C5>='Model inputs'!B54))="",FALSE,IF(ISERROR('Customers revenue and run costs'!C5>='Model inputs'!B54),'Customers revenue and run costs'!C5>='Model inputs'!B54,IF(OR('Customers revenue and run costs'!C5="",'Model inputs'!B54=""),"",'Customers revenue and run costs'!C5>='Model inputs'!B54))),1,0)) -> 1 | D7: ='Model inputs'!B46*IF(IF(IF(IF(ISERROR('Customers revenue and run costs'!D5>='Model inputs'!B54),'Customers revenue and run costs'!D5>='Model inputs'!B54,IF(OR('Customers revenue and run costs'!D5="",'Model inputs'!B54=""),"",'Customers revenue and run costs'!D5>='Model inputs'!B54))="",FALSE,IF(ISERROR('Customers revenue and run costs'!D5>='Model inputs'!B54),'Customers revenue and run costs'!D5>='Model inputs'!B54,IF(OR('Customers revenue and run costs'!D5="",'Model inputs'!B54=""),"",'Customers revenue and run costs'!D5>='Model inputs'!B54))),1,0)="",0,IF(IF(IF(ISERROR('Customers revenue and run costs'!D5>='Model inputs'!B54),'Customers revenue and run costs'!D5>='Model inputs'!B54,IF(OR('Customers revenue and run costs'!D5="",'Model inputs'!B54=""),"",'Customers revenue and run costs'!D5>='Model inputs'!B54))="",FALSE,IF(ISERROR('Customers revenue and run costs'!D5>='Model inputs'!B54),'Customers revenue and run costs'!D5>='Model inputs'!B54,IF(OR('Customers revenue and run costs'!D5="",'Model inputs'!B54=""),"",'Customers revenue and run costs'!D5>='Model inputs'!B54))),1,0)) -> 1 | E7: ='Model inputs'!B46*IF(IF(IF(IF(ISERROR('Customers revenue and run costs'!E5>='Model inputs'!B54),'Customers revenue and run costs'!E5>='Model inputs'!B54,IF(OR('Customers revenue and run costs'!E5="",'Model inputs'!B54=""),"",'Customers revenue and run costs'!E5>='Model inputs'!B54))="",FALSE,IF(ISERROR('Customers revenue and run costs'!E5>='Model inputs'!B54),'Customers revenue and run costs'!E5>='Model inputs'!B54,IF(OR('Customers revenue and run costs'!E5="",'Model inputs'!B54=""),"",'Customers revenue and run costs'!E5>='Model inputs'!B54))),1,0)="",0,IF(IF(IF(ISERROR('Customers revenue and run costs'!E5>='Model inputs'!B54),'Customers revenue and run costs'!E5>='Model inputs'!B54,IF(OR('Customers revenue and run costs'!E5="",'Model inputs'!B54=""),"",'Customers revenue and run costs'!E5>='Model inputs'!B54))="",FALSE,IF(ISERROR('Customers revenue and run costs'!E5>='Model inputs'!B54),'Customers revenue and run costs'!E5>='Model inputs'!B54,IF(OR('Customers revenue and run costs'!E5="",'Model inputs'!B54=""),"",'Customers revenue and run costs'!E5>='Model inputs'!B54))),1,0)) -> 1 | F7: ='Model inputs'!B46*IF(IF(IF(IF(ISERROR('Customers revenue and run costs'!F5>='Model inputs'!B54),'Customers revenue and run costs'!F5>='Model inputs'!B54,IF(OR('Customers revenue and run costs'!F5="",'Model inputs'!B54=""),"",'Customers revenue and run costs'!F5>='Model inputs'!B54))="",FALSE,IF(ISERROR('Customers revenue and run costs'!F5>='Model inputs'!B54),'Customers revenue and run costs'!F5>='Model inputs'!B54,IF(OR('Customers revenue and run costs'!F5="",'Model inputs'!B54=""),"",'Customers revenue and run costs'!F5>='Model inputs'!B54))),1,0)="",0,IF(IF(IF(ISERROR('Customers revenue and run costs'!F5>='Model inputs'!B54),'Customers revenue and run costs'!F5>='Model inputs'!B54,IF(OR('Customers revenue and run costs'!F5="",'Model inputs'!B54=""),"",'Customers revenue and run costs'!F5>='Model inputs'!B54))="",FALSE,IF(ISERROR('Customers revenue and run costs'!F5>='Model inputs'!B54),'Customers revenue and run costs'!F5>='Model inputs'!B54,IF(OR('Customers revenue and run costs'!F5="",'Model inputs'!B54=""),"",'Customers revenue and run costs'!F5>='Model inputs'!B54))),1,0)) -> 1 | G7: ='Model inputs'!B46*IF(IF(IF(IF(ISERROR('Customers revenue and run costs'!G5>='Model inputs'!B54),'Customers revenue and run costs'!G5>='Model inputs'!B54,IF(OR('Customers revenue and run costs'!G5="",'Model inputs'!B54=""),"",'Customers revenue and run costs'!G5>='Model inputs'!B54))="",FALSE,IF(ISERROR('Customers revenue and run costs'!G5>='Model inputs'!B54),'Customers revenue and run costs'!G5>='Model inputs'!B54,IF(OR('Customers revenue and run costs'!G5="",'Model inputs'!B54=""),"",'Customers revenue and run costs'!G5>='Model inputs'!B54))),1,0)="",0,IF(IF(IF(ISERROR('Customers revenue and run costs'!G5>='Model inputs'!B54),'Customers revenue and run costs'!G5>='Model inputs'!B54,IF(OR('Customers revenue and run costs'!G5="",'Model inputs'!B54=""),"",'Customers revenue and run costs'!G5>='Model inputs'!B54))="",FALSE,IF(ISERROR('Customers revenue and run costs'!G5>='Model inputs'!B54),'Customers revenue and run costs'!G5>='Model inputs'!B54,IF(OR('Customers revenue and run costs'!G5="",'Model inputs'!B54=""),"",'Customers revenue and run costs'!G5>='Model inputs'!B54))),1,0)) -> 1 | H7: ='Model inputs'!B46*IF(IF(IF(IF(ISERROR('Customers revenue and run costs'!H5>='Model inputs'!B54),'Customers revenue and run costs'!H5>='Model inputs'!B54,IF(OR('Customers revenue and run costs'!H5="",'Model inputs'!B54=""),"",'Customers revenue and run costs'!H5>='Model inputs'!B54))="",FALSE,IF(ISERROR('Customers revenue and run costs'!H5>='Model inputs'!B54),'Customers revenue and run costs'!H5>='Model inputs'!B54,IF(OR('Customers revenue and run costs'!H5="",'Model inputs'!B54=""),"",'Customers revenue and run costs'!H5>='Model inputs'!B54))),1,0)="",0,IF(IF(IF(ISERROR('Customers revenue and run costs'!H5>='Model inputs'!B54),'Customers revenue and run costs'!H5>='Model inputs'!B54,IF(OR('Customers revenue and run costs'!H5="",'Model inputs'!B54=""),"",'Customers revenue and run costs'!H5>='Model inputs'!B54))="",FALSE,IF(ISERROR('Customers revenue and run costs'!H5>='Model inputs'!B54),'Customers revenue and run costs'!H5>='Model inputs'!B54,IF(OR('Customers revenue and run costs'!H5="",'Model inputs'!B54=""),"",'Customers revenue and run costs'!H5>='Model inputs'!B54))),1,0)) -> 1 | I7: ='Model inputs'!B46*IF(IF(IF(IF(ISERROR('Customers revenue and run costs'!I5>='Model inputs'!B54),'Customers revenue and run costs'!I5>='Model inputs'!B54,IF(OR('Customers revenue and run costs'!I5="",'Model inputs'!B54=""),"",'Customers revenue and run costs'!I5>='Model inputs'!B54))="",FALSE,IF(ISERROR('Customers revenue and run costs'!I5>='Model inputs'!B54),'Customers revenue and run costs'!I5>='Model inputs'!B54,IF(OR('Customers revenue and run costs'!I5="",'Model inputs'!B54=""),"",'Customers revenue and run costs'!I5>='Model inputs'!B54))),1,0)="",0,IF(IF(IF(ISERROR('Customers revenue and run costs'!I5>='Model inputs'!B54),'Customers revenue and run costs'!I5>='Model inputs'!B54,IF(OR('Customers revenue and run costs'!I5="",'Model inputs'!B54=""),"",'Customers revenue and run costs'!I5>='Model inputs'!B54))="",FALSE,IF(ISERROR('Customers revenue and run costs'!I5>='Model inputs'!B54),'Customers revenue and run costs'!I5>='Model inputs'!B54,IF(OR('Customers revenue and run costs'!I5="",'Model inputs'!B54=""),"",'Customers revenue and run costs'!I5>='Model inputs'!B54))),1,0)) -> 1 | J7: ='Model inputs'!B46*IF(IF(IF(IF(ISERROR('Customers revenue and run costs'!J5>='Model inputs'!B54),'Customers revenue and run costs'!J5>='Model inputs'!B54,IF(OR('Customers revenue and run costs'!J5="",'Model inputs'!B54=""),"",'Customers revenue and run costs'!J5>='Model inputs'!B54))="",FALSE,IF(ISERROR('Customers revenue and run costs'!J5>='Model inputs'!B54),'Customers revenue and run costs'!J5>='Model inputs'!B54,IF(OR('Customers revenue and run costs'!J5="",'Model inputs'!B54=""),"",'Customers revenue and run costs'!J5>='Model inputs'!B54))),1,0)="",0,IF(IF(IF(ISERROR('Customers revenue and run costs'!J5>='Model inputs'!B54),'Customers revenue and run costs'!J5>='Model inputs'!B54,IF(OR('Customers revenue and run costs'!J5="",'Model inputs'!B54=""),"",'Customers revenue and run costs'!J5>='Model inputs'!B54))="",FALSE,IF(ISERROR('Customers revenue and run costs'!J5>='Model inputs'!B54),'Customers revenue and run costs'!J5>='Model inputs'!B54,IF(OR('Customers revenue and run costs'!J5="",'Model inputs'!B54=""),"",'Customers revenue and run costs'!J5>='Model inputs'!B54))),1,0)) -> 1 | K7: ='Model inputs'!B46*IF(IF(IF(IF(ISERROR('Customers revenue and run costs'!K5>='Model inputs'!B54),'Customers revenue and run costs'!K5>='Model inputs'!B54,IF(OR('Customers revenue and run costs'!K5="",'Model inputs'!B54=""),"",'Customers revenue and run costs'!K5>='Model inputs'!B54))="",FALSE,IF(ISERROR('Customers revenue and run costs'!K5>='Model inputs'!B54),'Customers revenue and run costs'!K5>='Model inputs'!B54,IF(OR('Customers revenue and run costs'!K5="",'Model inputs'!B54=""),"",'Customers revenue and run costs'!K5>='Model inputs'!B54))),1,0)="",0,IF(IF(IF(ISERROR('Customers revenue and run costs'!K5>='Model inputs'!B54),'Customers revenue and run costs'!K5>='Model inputs'!B54,IF(OR('Customers revenue and run costs'!K5="",'Model inputs'!B54=""),"",'Customers revenue and run costs'!K5>='Model inputs'!B54))="",FALSE,IF(ISERROR('Customers revenue and run costs'!K5>='Model inputs'!B54),'Customers revenue and run costs'!K5>='Model inputs'!B54,IF(OR('Customers revenue and run costs'!K5="",'Model inputs'!B54=""),"",'Customers revenue and run costs'!K5>='Model inputs'!B54))),1,0)) -> 1 | L7: ='Model inputs'!B46*IF(IF(IF(IF(ISERROR('Customers revenue and run costs'!L5>='Model inputs'!B54),'Customers revenue and run costs'!L5>='Model inputs'!B54,IF(OR('Customers revenue and run costs'!L5="",'Model inputs'!B54=""),"",'Customers revenue and run costs'!L5>='Model inputs'!B54))="",FALSE,IF(ISERROR('Customers revenue and run costs'!L5>='Model inputs'!B54),'Customers revenue and run costs'!L5>='Model inputs'!B54,IF(OR('Customers revenue and run costs'!L5="",'Model inputs'!B54=""),"",'Customers revenue and run costs'!L5>='Model inputs'!B54))),1,0)="",0,IF(IF(IF(ISERROR('Customers revenue and run costs'!L5>='Model inputs'!B54),'Customers revenue and run costs'!L5>='Model inputs'!B54,IF(OR('Customers revenue and run costs'!L5="",'Model inputs'!B54=""),"",'Customers revenue and run costs'!L5>='Model inputs'!B54))="",FALSE,IF(ISERROR('Customers revenue and run costs'!L5>='Model inputs'!B54),'Customers revenue and run costs'!L5>='Model inputs'!B54,IF(OR('Customers revenue and run costs'!L5="",'Model inputs'!B54=""),"",'Customers revenue and run costs'!L5>='Model inputs'!B54))),1,0)) -> 1 | M7: ='Model inputs'!B46*IF(IF(IF(IF(ISERROR('Customers revenue and run costs'!M5>='Model inputs'!B54),'Customers revenue and run costs'!M5>='Model inputs'!B54,IF(OR('Customers revenue and run costs'!M5="",'Model inputs'!B54=""),"",'Customers revenue and run costs'!M5>='Model inputs'!B54))="",FALSE,IF(ISERROR('Customers revenue and run costs'!M5>='Model inputs'!B54),'Customers revenue and run costs'!M5>='Model inputs'!B54,IF(OR('Customers revenue and run costs'!M5="",'Model inputs'!B54=""),"",'Customers revenue and run costs'!M5>='Model inputs'!B54))),1,0)="",0,IF(IF(IF(ISERROR('Customers revenue and run costs'!M5>='Model inputs'!B54),'Customers revenue and run costs'!M5>='Model inputs'!B54,IF(OR('Customers revenue and run costs'!M5="",'Model inputs'!B54=""),"",'Customers revenue and run costs'!M5>='Model inputs'!B54))="",FALSE,IF(ISERROR('Customers revenue and run costs'!M5>='Model inputs'!B54),'Customers revenue and run costs'!M5>='Model inputs'!B54,IF(OR('Customers revenue and run costs'!M5="",'Model inputs'!B54=""),"",'Customers revenue and run costs'!M5>='Model inputs'!B54))),1,0)) -> 1
A8: Planned engineer | B8: ='Model inputs'!B47*IF(IF(IF(IF(ISERROR('Customers revenue and run costs'!B5>='Model inputs'!B55),'Customers revenue and run costs'!B5>='Model inputs'!B55,IF(OR('Customers revenue and run costs'!B5="",'Model inputs'!B55=""),"",'Customers revenue and run costs'!B5>='Model inputs'!B55))="",FALSE,IF(ISERROR('Customers revenue and run costs'!B5>='Model inputs'!B55),'Customers revenue and run costs'!B5>='Model inputs'!B55,IF(OR('Customers revenue and run costs'!B5="",'Model inputs'!B55=""),"",'Customers revenue and run costs'!B5>='Model inputs'!B55))),1,0)="",0,IF(IF(IF(ISERROR('Customers revenue and run costs'!B5>='Model inputs'!B55),'Customers revenue and run costs'!B5>='Model inputs'!B55,IF(OR('Customers revenue and run costs'!B5="",'Model inputs'!B55=""),"",'Customers revenue and run costs'!B5>='Model inputs'!B55))="",FALSE,IF(ISERROR('Customers revenue and run costs'!B5>='Model inputs'!B55),'Customers revenue and run costs'!B5>='Model inputs'!B55,IF(OR('Customers revenue and run costs'!B5="",'Model inputs'!B55=""),"",'Customers revenue and run costs'!B5>='Model inputs'!B55))),1,0)) -> 0 | C8: ='Model inputs'!B47*IF(IF(IF(IF(ISERROR('Customers revenue and run costs'!C5>='Model inputs'!B55),'Customers revenue and run costs'!C5>='Model inputs'!B55,IF(OR('Customers revenue and run costs'!C5="",'Model inputs'!B55=""),"",'Customers revenue and run costs'!C5>='Model inputs'!B55))="",FALSE,IF(ISERROR('Customers revenue and run costs'!C5>='Model inputs'!B55),'Customers revenue and run costs'!C5>='Model inputs'!B55,IF(OR('Customers revenue and run costs'!C5="",'Model inputs'!B55=""),"",'Customers revenue and run costs'!C5>='Model inputs'!B55))),1,0)="",0,IF(IF(IF(ISERROR('Customers revenue and run costs'!C5>='Model inputs'!B55),'Customers revenue and run costs'!C5>='Model inputs'!B55,IF(OR('Customers revenue and run costs'!C5="",'Model inputs'!B55=""),"",'Customers revenue and run costs'!C5>='Model inputs'!B55))="",FALSE,IF(ISERROR('Customers revenue and run costs'!C5>='Model inputs'!B55),'Customers revenue and run costs'!C5>='Model inputs'!B55,IF(OR('Customers revenue and run costs'!C5="",'Model inputs'!B55=""),"",'Customers revenue and run costs'!C5>='Model inputs'!B55))),1,0)) -> 0 | D8: ='Model inputs'!B47*IF(IF(IF(IF(ISERROR('Customers revenue and run costs'!D5>='Model inputs'!B55),'Customers revenue and run costs'!D5>='Model inputs'!B55,IF(OR('Customers revenue and run costs'!D5="",'Model inputs'!B55=""),"",'Customers revenue and run costs'!D5>='Model inputs'!B55))="",FALSE,IF(ISERROR('Customers revenue and run costs'!D5>='Model inputs'!B55),'Customers revenue and run costs'!D5>='Model inputs'!B55,IF(OR('Customers revenue and run costs'!D5="",'Model inputs'!B55=""),"",'Customers revenue and run costs'!D5>='Model inputs'!B55))),1,0)="",0,IF(IF(IF(ISERROR('Customers revenue and run costs'!D5>='Model inputs'!B55),'Customers revenue and run costs'!D5>='Model inputs'!B55,IF(OR('Customers revenue and run costs'!D5="",'Model inputs'!B55=""),"",'Customers revenue and run costs'!D5>='Model inputs'!B55))="",FALSE,IF(ISERROR('Customers revenue and run costs'!D5>='Model inputs'!B55),'Customers revenue and run costs'!D5>='Model inputs'!B55,IF(OR('Customers revenue and run costs'!D5="",'Model inputs'!B55=""),"",'Customers revenue and run costs'!D5>='Model inputs'!B55))),1,0)) -> 0 | E8: ='Model inputs'!B47*IF(IF(IF(IF(ISERROR('Customers revenue and run costs'!E5>='Model inputs'!B55),'Customers revenue and run costs'!E5>='Model inputs'!B55,IF(OR('Customers revenue and run costs'!E5="",'Model inputs'!B55=""),"",'Customers revenue and run costs'!E5>='Model inputs'!B55))="",FALSE,IF(ISERROR('Customers revenue and run costs'!E5>='Model inputs'!B55),'Customers revenue and run costs'!E5>='Model inputs'!B55,IF(OR('Customers revenue and run costs'!E5="",'Model inputs'!B55=""),"",'Customers revenue and run costs'!E5>='Model inputs'!B55))),1,0)="",0,IF(IF(IF(ISERROR('Customers revenue and run costs'!E5>='Model inputs'!B55),'Customers revenue and run costs'!E5>='Model inputs'!B55,IF(OR('Customers revenue and run costs'!E5="",'Model inputs'!B55=""),"",'Customers revenue and run costs'!E5>='Model inputs'!B55))="",FALSE,IF(ISERROR('Customers revenue and run costs'!E5>='Model inputs'!B55),'Customers revenue and run costs'!E5>='Model inputs'!B55,IF(OR('Customers revenue and run costs'!E5="",'Model inputs'!B55=""),"",'Customers revenue and run costs'!E5>='Model inputs'!B55))),1,0)) -> 0 | F8: ='Model inputs'!B47*IF(IF(IF(IF(ISERROR('Customers revenue and run costs'!F5>='Model inputs'!B55),'Customers revenue and run costs'!F5>='Model inputs'!B55,IF(OR('Customers revenue and run costs'!F5="",'Model inputs'!B55=""),"",'Customers revenue and run costs'!F5>='Model inputs'!B55))="",FALSE,IF(ISERROR('Customers revenue and run costs'!F5>='Model inputs'!B55),'Customers revenue and run costs'!F5>='Model inputs'!B55,IF(OR('Customers revenue and run costs'!F5="",'Model inputs'!B55=""),"",'Customers revenue and run costs'!F5>='Model inputs'!B55))),1,0)="",0,IF(IF(IF(ISERROR('Customers revenue and run costs'!F5>='Model inputs'!B55),'Customers revenue and run costs'!F5>='Model inputs'!B55,IF(OR('Customers revenue and run costs'!F5="",'Model inputs'!B55=""),"",'Customers revenue and run costs'!F5>='Model inputs'!B55))="",FALSE,IF(ISERROR('Customers revenue and run costs'!F5>='Model inputs'!B55),'Customers revenue and run costs'!F5>='Model inputs'!B55,IF(OR('Customers revenue and run costs'!F5="",'Model inputs'!B55=""),"",'Customers revenue and run costs'!F5>='Model inputs'!B55))),1,0)) -> 0 | G8: ='Model inputs'!B47*IF(IF(IF(IF(ISERROR('Customers revenue and run costs'!G5>='Model inputs'!B55),'Customers revenue and run costs'!G5>='Model inputs'!B55,IF(OR('Customers revenue and run costs'!G5="",'Model inputs'!B55=""),"",'Customers revenue and run costs'!G5>='Model inputs'!B55))="",FALSE,IF(ISERROR('Customers revenue and run costs'!G5>='Model inputs'!B55),'Customers revenue and run costs'!G5>='Model inputs'!B55,IF(OR('Customers revenue and run costs'!G5="",'Model inputs'!B55=""),"",'Customers revenue and run costs'!G5>='Model inputs'!B55))),1,0)="",0,IF(IF(IF(ISERROR('Customers revenue and run costs'!G5>='Model inputs'!B55),'Customers revenue and run costs'!G5>='Model inputs'!B55,IF(OR('Customers revenue and run costs'!G5="",'Model inputs'!B55=""),"",'Customers revenue and run costs'!G5>='Model inputs'!B55))="",FALSE,IF(ISERROR('Customers revenue and run costs'!G5>='Model inputs'!B55),'Customers revenue and run costs'!G5>='Model inputs'!B55,IF(OR('Customers revenue and run costs'!G5="",'Model inputs'!B55=""),"",'Customers revenue and run costs'!G5>='Model inputs'!B55))),1,0)) -> 0 | H8: ='Model inputs'!B47*IF(IF(IF(IF(ISERROR('Customers revenue and run costs'!H5>='Model inputs'!B55),'Customers revenue and run costs'!H5>='Model inputs'!B55,IF(OR('Customers revenue and run costs'!H5="",'Model inputs'!B55=""),"",'Customers revenue and run costs'!H5>='Model inputs'!B55))="",FALSE,IF(ISERROR('Customers revenue and run costs'!H5>='Model inputs'!B55),'Customers revenue and run costs'!H5>='Model inputs'!B55,IF(OR('Customers revenue and run costs'!H5="",'Model inputs'!B55=""),"",'Customers revenue and run costs'!H5>='Model inputs'!B55))),1,0)="",0,IF(IF(IF(ISERROR('Customers revenue and run costs'!H5>='Model inputs'!B55),'Customers revenue and run costs'!H5>='Model inputs'!B55,IF(OR('Customers revenue and run costs'!H5="",'Model inputs'!B55=""),"",'Customers revenue and run costs'!H5>='Model inputs'!B55))="",FALSE,IF(ISERROR('Customers revenue and run costs'!H5>='Model inputs'!B55),'Customers revenue and run costs'!H5>='Model inputs'!B55,IF(OR('Customers revenue and run costs'!H5="",'Model inputs'!B55=""),"",'Customers revenue and run costs'!H5>='Model inputs'!B55))),1,0)) -> 0 | I8: ='Model inputs'!B47*IF(IF(IF(IF(ISERROR('Customers revenue and run costs'!I5>='Model inputs'!B55),'Customers revenue and run costs'!I5>='Model inputs'!B55,IF(OR('Customers revenue and run costs'!I5="",'Model inputs'!B55=""),"",'Customers revenue and run costs'!I5>='Model inputs'!B55))="",FALSE,IF(ISERROR('Customers revenue and run costs'!I5>='Model inputs'!B55),'Customers revenue and run costs'!I5>='Model inputs'!B55,IF(OR('Customers revenue and run costs'!I5="",'Model inputs'!B55=""),"",'Customers revenue and run costs'!I5>='Model inputs'!B55))),1,0)="",0,IF(IF(IF(ISERROR('Customers revenue and run costs'!I5>='Model inputs'!B55),'Customers revenue and run costs'!I5>='Model inputs'!B55,IF(OR('Customers revenue and run costs'!I5="",'Model inputs'!B55=""),"",'Customers revenue and run costs'!I5>='Model inputs'!B55))="",FALSE,IF(ISERROR('Customers revenue and run costs'!I5>='Model inputs'!B55),'Customers revenue and run costs'!I5>='Model inputs'!B55,IF(OR('Customers revenue and run costs'!I5="",'Model inputs'!B55=""),"",'Customers revenue and run costs'!I5>='Model inputs'!B55))),1,0)) -> 0 | J8: ='Model inputs'!B47*IF(IF(IF(IF(ISERROR('Customers revenue and run costs'!J5>='Model inputs'!B55),'Customers revenue and run costs'!J5>='Model inputs'!B55,IF(OR('Customers revenue and run costs'!J5="",'Model inputs'!B55=""),"",'Customers revenue and run costs'!J5>='Model inputs'!B55))="",FALSE,IF(ISERROR('Customers revenue and run costs'!J5>='Model inputs'!B55),'Customers revenue and run costs'!J5>='Model inputs'!B55,IF(OR('Customers revenue and run costs'!J5="",'Model inputs'!B55=""),"",'Customers revenue and run costs'!J5>='Model inputs'!B55))),1,0)="",0,IF(IF(IF(ISERROR('Customers revenue and run costs'!J5>='Model inputs'!B55),'Customers revenue and run costs'!J5>='Model inputs'!B55,IF(OR('Customers revenue and run costs'!J5="",'Model inputs'!B55=""),"",'Customers revenue and run costs'!J5>='Model inputs'!B55))="",FALSE,IF(ISERROR('Customers revenue and run costs'!J5>='Model inputs'!B55),'Customers revenue and run costs'!J5>='Model inputs'!B55,IF(OR('Customers revenue and run costs'!J5="",'Model inputs'!B55=""),"",'Customers revenue and run costs'!J5>='Model inputs'!B55))),1,0)) -> 0 | K8: ='Model inputs'!B47*IF(IF(IF(IF(ISERROR('Customers revenue and run costs'!K5>='Model inputs'!B55),'Customers revenue and run costs'!K5>='Model inputs'!B55,IF(OR('Customers revenue and run costs'!K5="",'Model inputs'!B55=""),"",'Customers revenue and run costs'!K5>='Model inputs'!B55))="",FALSE,IF(ISERROR('Customers revenue and run costs'!K5>='Model inputs'!B55),'Customers revenue and run costs'!K5>='Model inputs'!B55,IF(OR('Customers revenue and run costs'!K5="",'Model inputs'!B55=""),"",'Customers revenue and run costs'!K5>='Model inputs'!B55))),1,0)="",0,IF(IF(IF(ISERROR('Customers revenue and run costs'!K5>='Model inputs'!B55),'Customers revenue and run costs'!K5>='Model inputs'!B55,IF(OR('Customers revenue and run costs'!K5="",'Model inputs'!B55=""),"",'Customers revenue and run costs'!K5>='Model inputs'!B55))="",FALSE,IF(ISERROR('Customers revenue and run costs'!K5>='Model inputs'!B55),'Customers revenue and run costs'!K5>='Model inputs'!B55,IF(OR('Customers revenue and run costs'!K5="",'Model inputs'!B55=""),"",'Customers revenue and run costs'!K5>='Model inputs'!B55))),1,0)) -> 0 | L8: ='Model inputs'!B47*IF(IF(IF(IF(ISERROR('Customers revenue and run costs'!L5>='Model inputs'!B55),'Customers revenue and run costs'!L5>='Model inputs'!B55,IF(OR('Customers revenue and run costs'!L5="",'Model inputs'!B55=""),"",'Customers revenue and run costs'!L5>='Model inputs'!B55))="",FALSE,IF(ISERROR('Customers revenue and run costs'!L5>='Model inputs'!B55),'Customers revenue and run costs'!L5>='Model inputs'!B55,IF(OR('Customers revenue and run costs'!L5="",'Model inputs'!B55=""),"",'Customers revenue and run costs'!L5>='Model inputs'!B55))),1,0)="",0,IF(IF(IF(ISERROR('Customers revenue and run costs'!L5>='Model inputs'!B55),'Customers revenue and run costs'!L5>='Model inputs'!B55,IF(OR('Customers revenue and run costs'!L5="",'Model inputs'!B55=""),"",'Customers revenue and run costs'!L5>='Model inputs'!B55))="",FALSE,IF(ISERROR('Customers revenue and run costs'!L5>='Model inputs'!B55),'Customers revenue and run costs'!L5>='Model inputs'!B55,IF(OR('Customers revenue and run costs'!L5="",'Model inputs'!B55=""),"",'Customers revenue and run costs'!L5>='Model inputs'!B55))),1,0)) -> 0 | M8: ='Model inputs'!B47*IF(IF(IF(IF(ISERROR('Customers revenue and run costs'!M5>='Model inputs'!B55),'Customers revenue and run costs'!M5>='Model inputs'!B55,IF(OR('Customers revenue and run costs'!M5="",'Model inputs'!B55=""),"",'Customers revenue and run costs'!M5>='Model inputs'!B55))="",FALSE,IF(ISERROR('Customers revenue and run costs'!M5>='Model inputs'!B55),'Customers revenue and run costs'!M5>='Model inputs'!B55,IF(OR('Customers revenue and run costs'!M5="",'Model inputs'!B55=""),"",'Customers revenue and run costs'!M5>='Model inputs'!B55))),1,0)="",0,IF(IF(IF(ISERROR('Customers revenue and run costs'!M5>='Model inputs'!B55),'Customers revenue and run costs'!M5>='Model inputs'!B55,IF(OR('Customers revenue and run costs'!M5="",'Model inputs'!B55=""),"",'Customers revenue and run costs'!M5>='Model inputs'!B55))="",FALSE,IF(ISERROR('Customers revenue and run costs'!M5>='Model inputs'!B55),'Customers revenue and run costs'!M5>='Model inputs'!B55,IF(OR('Customers revenue and run costs'!M5="",'Model inputs'!B55=""),"",'Customers revenue and run costs'!M5>='Model inputs'!B55))),1,0)) -> 0
A9: Forecast salaries | B9: =SUM('Monthly headcount and payroll'!B10,'Monthly headcount and payroll'!B11,'Monthly headcount and payroll'!B12) -> 0 | C9: =SUM('Monthly headcount and payroll'!C10,'Monthly headcount and payroll'!C11,'Monthly headcount and payroll'!C12) -> 0 | D9: =SUM('Monthly headcount and payroll'!D10,'Monthly headcount and payroll'!D11,'Monthly headcount and payroll'!D12) -> 0 | E9: =SUM('Monthly headcount and payroll'!E10,'Monthly headcount and payroll'!E11,'Monthly headcount and payroll'!E12) -> 0 | F9: =SUM('Monthly headcount and payroll'!F10,'Monthly headcount and payroll'!F11,'Monthly headcount and payroll'!F12) -> 0 | G9: =SUM('Monthly headcount and payroll'!G10,'Monthly headcount and payroll'!G11,'Monthly headcount and payroll'!G12) -> 0 | H9: =SUM('Monthly headcount and payroll'!H10,'Monthly headcount and payroll'!H11,'Monthly headcount and payroll'!H12) -> 0 | I9: =SUM('Monthly headcount and payroll'!I10,'Monthly headcount and payroll'!I11,'Monthly headcount and payroll'!I12) -> 0 | ... M9: =SUM('Monthly headcount and payroll'!M10,'Monthly headcount and payroll'!M11,'Monthly headcount and payroll'!M12) -> 0
A10: Founder 1 | B10: ='Monthly headcount and payroll'!B6*'Model inputs'!B49 -> 0 | C10: ='Monthly headcount and payroll'!C6*'Model inputs'!B49 -> 0 | D10: ='Monthly headcount and payroll'!D6*'Model inputs'!B49 -> 0 | E10: ='Monthly headcount and payroll'!E6*'Model inputs'!B49 -> 0 | F10: ='Monthly headcount and payroll'!F6*'Model inputs'!B49 -> 0 | G10: ='Monthly headcount and payroll'!G6*'Model inputs'!B49 -> 0 | H10: ='Monthly headcount and payroll'!H6*'Model inputs'!B49 -> 0 | I10: ='Monthly headcount and payroll'!I6*'Model inputs'!B49 -> 0 | J10: ='Monthly headcount and payroll'!J6*'Model inputs'!B49 -> 0 | K10: ='Monthly headcount and payroll'!K6*'Model inputs'!B49 -> 0 | L10: ='Monthly headcount and payroll'!L6*'Model inputs'!B49 -> 0 | M10: ='Monthly headcount and payroll'!M6*'Model inputs'!B49 -> 0
A11: Founder 2 | B11: ='Monthly headcount and payroll'!B7*'Model inputs'!B50 -> 0 | C11: ='Monthly headcount and payroll'!C7*'Model inputs'!B50 -> 0 | D11: ='Monthly headcount and payroll'!D7*'Model inputs'!B50 -> 0 | E11: ='Monthly headcount and payroll'!E7*'Model inputs'!B50 -> 0 | F11: ='Monthly headcount and payroll'!F7*'Model inputs'!B50 -> 0 | G11: ='Monthly headcount and payroll'!G7*'Model inputs'!B50 -> 0 | H11: ='Monthly headcount and payroll'!H7*'Model inputs'!B50 -> 0 | I11: ='Monthly headcount and payroll'!I7*'Model inputs'!B50 -> 0 | J11: ='Monthly headcount and payroll'!J7*'Model inputs'!B50 -> 0 | K11: ='Monthly headcount and payroll'!K7*'Model inputs'!B50 -> 0 | L11: ='Monthly headcount and payroll'!L7*'Model inputs'!B50 -> 0 | M11: ='Monthly headcount and payroll'!M7*'Model inputs'!B50 -> 0
A12: Planned engineer | B12: ='Monthly headcount and payroll'!B8*'Model inputs'!B51 -> 0 | C12: ='Monthly headcount and payroll'!C8*'Model inputs'!B51 -> 0 | D12: ='Monthly headcount and payroll'!D8*'Model inputs'!B51 -> 0 | E12: ='Monthly headcount and payroll'!E8*'Model inputs'!B51 -> 0 | F12: ='Monthly headcount and payroll'!F8*'Model inputs'!B51 -> 0 | G12: ='Monthly headcount and payroll'!G8*'Model inputs'!B51 -> 0 | H12: ='Monthly headcount and payroll'!H8*'Model inputs'!B51 -> 0 | I12: ='Monthly headcount and payroll'!I8*'Model inputs'!B51 -> 0 | J12: ='Monthly headcount and payroll'!J8*'Model inputs'!B51 -> 0 | K12: ='Monthly headcount and payroll'!K8*'Model inputs'!B51 -> 0 | L12: ='Monthly headcount and payroll'!L8*'Model inputs'!B51 -> 0 | M12: ='Monthly headcount and payroll'!M8*'Model inputs'!B51 -> 0

Sheet Model inputs
A1: Model inputs
A2: Integration values are aggregated snapshots; raw source records are not included.
A4: Variables
A5: Variable / segment | B5: Value | C5: 2026-09 | D5: 2026-10 | E5: 2026-11 | F5: 2026-12 | G5: 2027-01 | H5: 2027-02 | I5: 2027-03 | J5: 2027-04 | K5: 2027-05 | L5: 2027-06 | M5: 2027-07 | N5: 2027-08 | O5: 2027-09 | P5: 2027-10 | Q5: Value
A6: Closing customer count | B6: 0
A7: Closing customer count > Enterprise | B7: 0
A8: Closing customer count > Free | B8: =300 -> 300
A9: Closing customer count > Team | B9: =40 -> 40
A10: Enterprise signings · Customers revenue and run costs | C10: =0 -> 0 | D10: =0 -> 0 | E10: =0 -> 0 | F10: =0 -> 0 | G10: =0 -> 0 | H10: =0 -> 0 | I10: =0 -> 0 | J10: =0 -> 0 | ... L10: =0 -> 0 | M10: =1 -> 1 | N10: =0 -> 0 | O10: =0 -> 0 | P10: =0 -> 0
A11: Expected monthly runs | B11: 0
A12: Expected monthly runs > Enterprise | B12: =100 -> 100
A13: Expected monthly runs > Free | B13: =2 -> 2
A14: Expected monthly runs > Team | B14: =12 -> 12
A15: Fixed monthly overhead · Monthly revenue cost and runway | B15: ='Model inputs'!B76+'Model inputs'!B92+'Model inputs'!B93+'Model inputs'!B75+'Model inputs'!B88 -> 89
A16: Forecast cash balance · 12-month forecast summary · Susanoo — Base | C16: =IF(IF(IF(IF(ISERROR('Model inputs'!C61=1),'Model inputs'!C61=1,IF('Model inputs'!C61="","",'Model inputs'!C61=1))="",FALSE,IF(ISERROR('Model inputs'!C61=1),'Model inputs'!C61=1,IF('Model inputs'!C61="","",'Model inputs'!C61=1))),IF('Model inputs'!B40="","",'Model inputs'!B40),"")="",0,IF(IF(IF(ISERROR('Model inputs'!C61=1),'Model inputs'!C61=1,IF('Model inputs'!C61="","",'Model inputs'!C61=1))="",FALSE,IF(ISERROR('Model inputs'!C61=1),'Model inputs'!C61=1,IF('Model inputs'!C61="","",'Model inputs'!C61=1))),IF('Model inputs'!B40="","",'Model inputs'!B40),""))+'Model inputs'!C70 -> #VALUE! | D16: =IF(IF(IF(IF(ISERROR('Model inputs'!D61=1),'Model inputs'!D61=1,IF('Model inputs'!D61="","",'Model inputs'!D61=1))="",FALSE,IF(ISERROR('Model inputs'!D61=1),'Model inputs'!D61=1,IF('Model inputs'!D61="","",'Model inputs'!D61=1))),IF('Model inputs'!B40="","",'Model inputs'!B40),IF('Model inputs'!C16="","",'Model inputs'!C16))="",0,IF(IF(IF(ISERROR('Model inputs'!D61=1),'Model inputs'!D61=1,IF('Model inputs'!D61="","",'Model inputs'!D61=1))="",FALSE,IF(ISERROR('Model inputs'!D61=1),'Model inputs'!D61=1,IF('Model inputs'!D61="","",'Model inputs'!D61=1))),IF('Model inputs'!B40="","",'Model inputs'!B40),IF('Model inputs'!C16="","",'Model inputs'!C16)))+'Model inputs'!D70 -> #VALUE! | E16: =IF(IF(IF(IF(ISERROR('Model inputs'!E61=1),'Model inputs'!E61=1,IF('Model inputs'!E61="","",'Model inputs'!E61=1))="",FALSE,IF(ISERROR('Model inputs'!E61=1),'Model inputs'!E61=1,IF('Model inputs'!E61="","",'Model inputs'!E61=1))),IF('Model inputs'!B40="","",'Model inputs'!B40),IF('Model inputs'!D16="","",'Model inputs'!D16))="",0,IF(IF(IF(ISERROR('Model inputs'!E61=1),'Model inputs'!E61=1,IF('Model inputs'!E61="","",'Model inputs'!E61=1))="",FALSE,IF(ISERROR('Model inputs'!E61=1),'Model inputs'!E61=1,IF('Model inputs'!E61="","",'Model inputs'!E61=1))),IF('Model inputs'!B40="","",'Model inputs'!B40),IF('Model inputs'!D16="","",'Model inputs'!D16)))+'Model inputs'!E70 -> -45.7 | F16: =IF(IF(IF(IF(ISERROR('Model inputs'!F61=1),'Model inputs'!F61=1,IF('Model inputs'!F61="","",'Model inputs'!F61=1))="",FALSE,IF(ISERROR('Model inputs'!F61=1),'Model inputs'!F61=1,IF('Model inputs'!F61="","",'Model inputs'!F61=1))),IF('Model inputs'!B40="","",'Model inputs'!B40),IF('Model inputs'!E16="","",'Model inputs'!E16))="",0,IF(IF(IF(ISERROR('Model inputs'!F61=1),'Model inputs'!F61=1,IF('Model inputs'!F61="","",'Model inputs'!F61=1))="",FALSE,IF(ISERROR('Model inputs'!F61=1),'Model inputs'!F61=1,IF('Model inputs'!F61="","",'Model inputs'!F61=1))),IF('Model inputs'!B40="","",'Model inputs'!B40),IF('Model inputs'!E16="","",'Model inputs'!E16)))+'Model inputs'!F70 -> 39.754545 | G16: =IF(IF(IF(IF(ISERROR('Model inputs'!G61=1),'Model inputs'!G61=1,IF('Model inputs'!G61="","",'Model inputs'!G61=1))="",FALSE,IF(ISERROR('Model inputs'!G61=1),'Model inputs'!G61=1,IF('Model inputs'!G61="","",'Model inputs'!G61=1))),IF('Model inputs'!B40="","",'Model inputs'!B40),IF('Model inputs'!F16="","",'Model inputs'!F16))="",0,IF(IF(IF(ISERROR('Model inputs'!G61=1),'Model inputs'!G61=1,IF('Model inputs'!G61="","",'Model inputs'!G61=1))="",FALSE,IF(ISERROR('Model inputs'!G61=1),'Model inputs'!G61=1,IF('Model inputs'!G61="","",'Model inputs'!G61=1))),IF('Model inputs'!B40="","",'Model inputs'!B40),IF('Model inputs'!F16="","",'Model inputs'!F16)))+'Model inputs'!G70 -> 256.36364 | H16: =IF(IF(IF(IF(ISERROR('Model inputs'!H61=1),'Model inputs'!H61=1,IF('Model inputs'!H61="","",'Model inputs'!H61=1))="",FALSE,IF(ISERROR('Model inputs'!H61=1),'Model inputs'!H61=1,IF('Model inputs'!H61="","",'Model inputs'!H61=1))),IF('Model inputs'!B40="","",'Model inputs'!B40),IF('Model inputs'!G16="","",'Model inputs'!G16))="",0,IF(IF(IF(ISERROR('Model inputs'!H61=1),'Model inputs'!H61=1,IF('Model inputs'!H61="","",'Model inputs'!H61=1))="",FALSE,IF(ISERROR('Model inputs'!H61=1),'Model inputs'!H61=1,IF('Model inputs'!H61="","",'Model inputs'!H61=1))),IF('Model inputs'!B40="","",'Model inputs'!B40),IF('Model inputs'!G16="","",'Model inputs'!G16)))+'Model inputs'!H70 -> 604.12727 | I16: =IF(IF(IF(IF(ISERROR('Model inputs'!I61=1),'Model inputs'!I61=1,IF('Model inputs'!I61="","",'Model inputs'!I61=1))="",FALSE,IF(ISERROR('Model inputs'!I61=1),'Model inputs'!I61=1,IF('Model inputs'!I61="","",'Model inputs'!I61=1))),IF('Model inputs'!B40="","",'Model inputs'!B40),IF('Model inputs'!H16="","",'Model inputs'!H16))="",0,IF(IF(IF(ISERROR('Model inputs'!I61=1),'Model inputs'!I61=1,IF('Model inputs'!I61="","",'Model inputs'!I61=1))="",FALSE,IF(ISERROR('Model inputs'!I61=1),'Model inputs'!I61=1,IF('Model inputs'!I61="","",'Model inputs'!I61=1))),IF('Model inputs'!B40="","",'Model inputs'!B40),IF('Model inputs'!H16="","",'Model inputs'!H16)))+'Model inputs'!I70 -> 1083.0455 | J16: =IF(IF(IF(IF(ISERROR('Model inputs'!J61=1),'Model inputs'!J61=1,IF('Model inputs'!J61="","",'Model inputs'!J61=1))="",FALSE,IF(ISERROR('Model inputs'!J61=1),'Model inputs'!J61=1,IF('Model inputs'!J61="","",'Model inputs'!J61=1))),IF('Model inputs'!B40="","",'Model inputs'!B40),IF('Model inputs'!I16="","",'Model inputs'!I16))="",0,IF(IF(IF(ISERROR('Model inputs'!J61=1),'Model inputs'!J61=1,IF('Model inputs'!J61="","",'Model inputs'!J61=1))="",FALSE,IF(ISERROR('Model inputs'!J61=1),'Model inputs'!J61=1,IF('Model inputs'!J61="","",'Model inputs'!J61=1))),IF('Model inputs'!B40="","",'Model inputs'!B40),IF('Model inputs'!I16="","",'Model inputs'!I16)))+'Model inputs'!J70 -> 1693.1182 | K16: =IF(IF(IF(IF(ISERROR('Model inputs'!K61=1),'Model inputs'!K61=1,IF('Model inputs'!K61="","",'Model inputs'!K61=1))="",FALSE,IF(ISERROR('Model inputs'!K61=1),'Model inputs'!K61=1,IF('Model inputs'!K61="","",'Model inputs'!K61=1))),IF('Model inputs'!B40="","",'Model inputs'!B40),IF('Model inputs'!J16="","",'Model inputs'!J16))="",0,IF(IF(IF(ISERROR('Model inputs'!K61=1),'Model inputs'!K61=1,IF('Model inputs'!K61="","",'Model inputs'!K61=1))="",FALSE,IF(ISERROR('Model inputs'!K61=1),'Model inputs'!K61=1,IF('Model inputs'!K61="","",'Model inputs'!K61=1))),IF('Model inputs'!B40="","",'Model inputs'!B40),IF('Model inputs'!J16="","",'Model inputs'!J16)))+'Model inputs'!K70 -> 2434.3455 | L16: =IF(IF(IF(IF(ISERROR('Model inputs'!L61=1),'Model inputs'!L61=1,IF('Model inputs'!L61="","",'Model inputs'!L61=1))="",FALSE,IF(ISERROR('Model inputs'!L61=1),'Model inputs'!L61=1,IF('Model inputs'!L61="","",'Model inputs'!L61=1))),IF('Model inputs'!B40="","",'Model inputs'!B40),IF('Model inputs'!K16="","",'Model inputs'!K16))="",0,IF(IF(IF(ISERROR('Model inputs'!L61=1),'Model inputs'!L61=1,IF('Model inputs'!L61="","",'Model inputs'!L61=1))="",FALSE,IF(ISERROR('Model inputs'!L61=1),'Model inputs'!L61=1,IF('Model inputs'!L61="","",'Model inputs'!L61=1))),IF('Model inputs'!B40="","",'Model inputs'!B40),IF('Model inputs'!K16="","",'Model inputs'!K16)))+'Model inputs'!L70 -> 3306.7273 | M16: =IF(IF(IF(IF(ISERROR('Model inputs'!M61=1),'Model inputs'!M61=1,IF('Model inputs'!M61="","",'Model inputs'!M61=1))="",FALSE,IF(ISERROR('Model inputs'!M61=1),'Model inputs'!M61=1,IF('Model inputs'!M61="","",'Model inputs'!M61=1))),IF('Model inputs'!B40="","",'Model inputs'!B40),IF('Model inputs'!L16="","",'Model inputs'!L16))="",0,IF(IF(IF(ISERROR('Model inputs'!M61=1),'Model inputs'!M61=1,IF('Model inputs'!M61="","",'Model inputs'!M61=1))="",FALSE,IF(ISERROR('Model inputs'!M61=1),'Model inputs'!M61=1,IF('Model inputs'!M61="","",'Model inputs'!M61=1))),IF('Model inputs'!B40="","",'Model inputs'!B40),IF('Model inputs'!L16="","",'Model inputs'!L16)))+'Model inputs'!M70 -> 5655.2636 | N16: =IF(IF(IF(IF(ISERROR('Model inputs'!N61=1),'Model inputs'!N61=1,IF('Model inputs'!N61="","",'Model inputs'!N61=1))="",FALSE,IF(ISERROR('Model inputs'!N61=1),'Model inputs'!N61=1,IF('Model inputs'!N61="","",'Model inputs'!N61=1))),IF('Model inputs'!B40="","",'Model inputs'!B40),IF('Model inputs'!M16="","",'Model inputs'!M16))="",0,IF(IF(IF(ISERROR('Model inputs'!N61=1),'Model inputs'!N61=1,IF('Model inputs'!N61="","",'Model inputs'!N61=1))="",FALSE,IF(ISERROR('Model inputs'!N61=1),'Model inputs'!N61=1,IF('Model inputs'!N61="","",'Model inputs'!N61=1))),IF('Model inputs'!B40="","",'Model inputs'!B40),IF('Model inputs'!M16="","",'Model inputs'!M16)))+'Model inputs'!N70 -> 8134.9545 | O16: =IF(IF(IF(IF(ISERROR('Model inputs'!O61=1),'Model inputs'!O61=1,IF('Model inputs'!O61="","",'Model inputs'!O61=1))="",FALSE,IF(ISERROR('Model inputs'!O61=1),'Model inputs'!O61=1,IF('Model inputs'!O61="","",'Model inputs'!O61=1))),IF('Model inputs'!B40="","",'Model inputs'!B40),IF('Model inputs'!N16="","",'Model inputs'!N16))="",0,IF(IF(IF(ISERROR('Model inputs'!O61=1),'Model inputs'!O61=1,IF('Model inputs'!O61="","",'Model inputs'!O61=1))="",FALSE,IF(ISERROR('Model inputs'!O61=1),'Model inputs'!O61=1,IF('Model inputs'!O61="","",'Model inputs'!O61=1))),IF('Model inputs'!B40="","",'Model inputs'!B40),IF('Model inputs'!N16="","",'Model inputs'!N16)))+'Model inputs'!O70 -> 10745.8 | P16: =IF(IF(IF(IF(ISERROR('Model inputs'!P61=1),'Model inputs'!P61=1,IF('Model inputs'!P61="","",'Model inputs'!P61=1))="",FALSE,IF(ISERROR('Model inputs'!P61=1),'Model inputs'!P61=1,IF('Model inputs'!P61="","",'Model inputs'!P61=1))),IF('Model inputs'!B40="","",'Model inputs'!B40),IF('Model inputs'!O16="","",'Model inputs'!O16))="",0,IF(IF(IF(ISERROR('Model inputs'!P61=1),'Model inputs'!P61=1,IF('Model inputs'!P61="","",'Model inputs'!P61=1))="",FALSE,IF(ISERROR('Model inputs'!P61=1),'Model inputs'!P61=1,IF('Model inputs'!P61="","",'Model inputs'!P61=1))),IF('Model inputs'!B40="","",'Model inputs'!B40),IF('Model inputs'!O16="","",'Model inputs'!O16)))+'Model inputs'!P70 -> 13487.8
A17: Forecast cash balance · Susanoo — Growth | D17: =IF(IF(IF(IF(ISERROR('Model inputs'!D79=1),'Model inputs'!D79=1,IF('Model inputs'!D79="","",'Model inputs'!D79=1))="",FALSE,IF(ISERROR('Model inputs'!D79=1),'Model inputs'!D79=1,IF('Model inputs'!D79="","",'Model inputs'!D79=1))),IF('Model inputs'!B91="","",'Model inputs'!B91),IF('Model inputs'!C77="","",'Model inputs'!C77))="",0,IF(IF(IF(ISERROR('Model inputs'!D79=1),'Model inputs'!D79=1,IF('Model inputs'!D79="","",'Model inputs'!D79=1))="",FALSE,IF(ISERROR('Model inputs'!D79=1),'Model inputs'!D79=1,IF('Model inputs'!D79="","",'Model inputs'!D79=1))),IF('Model inputs'!B91="","",'Model inputs'!B91),IF('Model inputs'!C77="","",'Model inputs'!C77)))+'Model inputs'!D89 -> #VALUE! | E17: =IF(IF(IF(IF(ISERROR('Model inputs'!E79=1),'Model inputs'!E79=1,IF('Model inputs'!E79="","",'Model inputs'!E79=1))="",FALSE,IF(ISERROR('Model inputs'!E79=1),'Model inputs'!E79=1,IF('Model inputs'!E79="","",'Model inputs'!E79=1))),IF('Model inputs'!B91="","",'Model inputs'!B91),IF('Model inputs'!D17="","",'Model inputs'!D17))="",0,IF(IF(IF(ISERROR('Model inputs'!E79=1),'Model inputs'!E79=1,IF('Model inputs'!E79="","",'Model inputs'!E79=1))="",FALSE,IF(ISERROR('Model inputs'!E79=1),'Model inputs'!E79=1,IF('Model inputs'!E79="","",'Model inputs'!E79=1))),IF('Model inputs'!B91="","",'Model inputs'!B91),IF('Model inputs'!D17="","",'Model inputs'!D17)))+'Model inputs'!E89 -> -120.25 | F17: =IF(IF(IF(IF(ISERROR('Model inputs'!F79=1),'Model inputs'!F79=1,IF('Model inputs'!F79="","",'Model inputs'!F79=1))="",FALSE,IF(ISERROR('Model inputs'!F79=1),'Model inputs'!F79=1,IF('Model inputs'!F79="","",'Model inputs'!F79=1))),IF('Model inputs'!B91="","",'Model inputs'!B91),IF('Model inputs'!E17="","",'Model inputs'!E17))="",0,IF(IF(IF(ISERROR('Model inputs'!F79=1),'Model inputs'!F79=1,IF('Model inputs'!F79="","",'Model inputs'!F79=1))="",FALSE,IF(ISERROR('Model inputs'!F79=1),'Model inputs'!F79=1,IF('Model inputs'!F79="","",'Model inputs'!F79=1))),IF('Model inputs'!B91="","",'Model inputs'!B91),IF('Model inputs'!E17="","",'Model inputs'!E17)))+'Model inputs'!F89 -> 99.840909 | G17: =IF(IF(IF(IF(ISERROR('Model inputs'!G79=1),'Model inputs'!G79=1,IF('Model inputs'!G79="","",'Model inputs'!G79=1))="",FALSE,IF(ISERROR('Model inputs'!G79=1),'Model inputs'!G79=1,IF('Model inputs'!G79="","",'Model inputs'!G79=1))),IF('Model inputs'!B91="","",'Model inputs'!B91),IF('Model inputs'!F17="","",'Model inputs'!F17))="",0,IF(IF(IF(ISERROR('Model inputs'!G79=1),'Model inputs'!G79=1,IF('Model inputs'!G79="","",'Model inputs'!G79=1))="",FALSE,IF(ISERROR('Model inputs'!G79=1),'Model inputs'!G79=1,IF('Model inputs'!G79="","",'Model inputs'!G79=1))),IF('Model inputs'!B91="","",'Model inputs'!B91),IF('Model inputs'!F17="","",'Model inputs'!F17)))+'Model inputs'!G89 -> 660.27273 | H17: =IF(IF(IF(IF(ISERROR('Model inputs'!H79=1),'Model inputs'!H79=1,IF('Model inputs'!H79="","",'Model inputs'!H79=1))="",FALSE,IF(ISERROR('Model inputs'!H79=1),'Model inputs'!H79=1,IF('Model inputs'!H79="","",'Model inputs'!H79=1))),IF('Model inputs'!B91="","",'Model inputs'!B91),IF('Model inputs'!G17="","",'Model inputs'!G17))="",0,IF(IF(IF(ISERROR('Model inputs'!H79=1),'Model inputs'!H79=1,IF('Model inputs'!H79="","",'Model inputs'!H79=1))="",FALSE,IF(ISERROR('Model inputs'!H79=1),'Model inputs'!H79=1,IF('Model inputs'!H79="","",'Model inputs'!H79=1))),IF('Model inputs'!B91="","",'Model inputs'!B91),IF('Model inputs'!G17="","",'Model inputs'!G17)))+'Model inputs'!H89 -> 1561.0455 | I17: =IF(IF(IF(IF(ISERROR('Model inputs'!I79=1),'Model inputs'!I79=1,IF('Model inputs'!I79="","",'Model inputs'!I79=1))="",FALSE,IF(ISERROR('Model inputs'!I79=1),'Model inputs'!I79=1,IF('Model inputs'!I79="","",'Model inputs'!I79=1))),IF('Model inputs'!B91="","",'Model inputs'!B91),IF('Model inputs'!H17="","",'Model inputs'!H17))="",0,IF(IF(IF(ISERROR('Model inputs'!I79=1),'Model inputs'!I79=1,IF('Model inputs'!I79="","",'Model inputs'!I79=1))="",FALSE,IF(ISERROR('Model inputs'!I79=1),'Model inputs'!I79=1,IF('Model inputs'!I79="","",'Model inputs'!I79=1))),IF('Model inputs'!B91="","",'Model inputs'!B91),IF('Model inputs'!H17="","",'Model inputs'!H17)))+'Model inputs'!I89 -> 2802.1591 | J17: =IF(IF(IF(IF(ISERROR('Model inputs'!J79=1),'Model inputs'!J79=1,IF('Model inputs'!J79="","",'Model inputs'!J79=1))="",FALSE,IF(ISERROR('Model inputs'!J79=1),'Model inputs'!J79=1,IF('Model inputs'!J79="","",'Model inputs'!J79=1))),IF('Model inputs'!B91="","",'Model inputs'!B91),IF('Model inputs'!I17="","",'Model inputs'!I17))="",0,IF(IF(IF(ISERROR('Model inputs'!J79=1),'Model inputs'!J79=1,IF('Model inputs'!J79="","",'Model inputs'!J79=1))="",FALSE,IF(ISERROR('Model inputs'!J79=1),'Model inputs'!J79=1,IF('Model inputs'!J79="","",'Model inputs'!J79=1))),IF('Model inputs'!B91="","",'Model inputs'!B91),IF('Model inputs'!I17="","",'Model inputs'!I17)))+'Model inputs'!J89 -> -271.38636 | K17: =IF(IF(IF(IF(ISERROR('Model inputs'!K79=1),'Model inputs'!K79=1,IF('Model inputs'!K79="","",'Model inputs'!K79=1))="",FALSE,IF(ISERROR('Model inputs'!K79=1),'Model inputs'!K79=1,IF('Model inputs'!K79="","",'Model inputs'!K79=1))),IF('Model inputs'!B91="","",'Model inputs'!B91),IF('Model inputs'!J17="","",'Model inputs'!J17))="",0,IF(IF(IF(ISERROR('Model inputs'!K79=1),'Model inputs'!K79=1,IF('Model inputs'!K79="","",'Model inputs'!K79=1))="",FALSE,IF(ISERROR('Model inputs'!K79=1),'Model inputs'!K79=1,IF('Model inputs'!K79="","",'Model inputs'!K79=1))),IF('Model inputs'!B91="","",'Model inputs'!B91),IF('Model inputs'!J17="","",'Model inputs'!J17)))+'Model inputs'!K89 -> -3004.5909 | L17: =IF(IF(IF(IF(ISERROR('Model inputs'!L79=1),'Model inputs'!L79=1,IF('Model inputs'!L79="","",'Model inputs'!L79=1))="",FALSE,IF(ISERROR('Model inputs'!L79=1),'Model inputs'!L79=1,IF('Model inputs'!L79="","",'Model inputs'!L79=1))),IF('Model inputs'!B91="","",'Model inputs'!B91),IF('Model inputs'!K17="","",'Model inputs'!K17))="",0,IF(IF(IF(ISERROR('Model inputs'!L79=1),'Model inputs'!L79=1,IF('Model inputs'!L79="","",'Model inputs'!L79=1))="",FALSE,IF(ISERROR('Model inputs'!L79=1),'Model inputs'!L79=1,IF('Model inputs'!L79="","",'Model inputs'!L79=1))),IF('Model inputs'!B91="","",'Model inputs'!B91),IF('Model inputs'!K17="","",'Model inputs'!K17)))+'Model inputs'!L89 -> -4052.4545 | M17: =IF(IF(IF(IF(ISERROR('Model inputs'!M79=1),'Model inputs'!M79=1,IF('Model inputs'!M79="","",'Model inputs'!M79=1))="",FALSE,IF(ISERROR('Model inputs'!M79=1),'Model inputs'!M79=1,IF('Model inputs'!M79="","",'Model inputs'!M79=1))),IF('Model inputs'!B91="","",'Model inputs'!B91),IF('Model inputs'!L17="","",'Model inputs'!L17))="",0,IF(IF(IF(ISERROR('Model inputs'!M79=1),'Model inputs'!M79=1,IF('Model inputs'!M79="","",'Model inputs'!M79=1))="",FALSE,IF(ISERROR('Model inputs'!M79=1),'Model inputs'!M79=1,IF('Model inputs'!M79="","",'Model inputs'!M79=1))),IF('Model inputs'!B91="","",'Model inputs'!B91),IF('Model inputs'!L17="","",'Model inputs'!L17)))+'Model inputs'!M89 -> -4759.9773 | N17: =IF(IF(IF(IF(ISERROR('Model inputs'!N79=1),'Model inputs'!N79=1,IF('Model inputs'!N79="","",'Model inputs'!N79=1))="",FALSE,IF(ISERROR('Model inputs'!N79=1),'Model inputs'!N79=1,IF('Model inputs'!N79="","",'Model inputs'!N79=1))),IF('Model inputs'!B91="","",'Model inputs'!B91),IF('Model inputs'!M17="","",'Model inputs'!M17))="",0,IF(IF(IF(ISERROR('Model inputs'!N79=1),'Model inputs'!N79=1,IF('Model inputs'!N79="","",'Model inputs'!N79=1))="",FALSE,IF(ISERROR('Model inputs'!N79=1),'Model inputs'!N79=1,IF('Model inputs'!N79="","",'Model inputs'!N79=1))),IF('Model inputs'!B91="","",'Model inputs'!B91),IF('Model inputs'!M17="","",'Model inputs'!M17)))+'Model inputs'!N89 -> -3782.1591 | O17: =IF(IF(IF(IF(ISERROR('Model inputs'!O79=1),'Model inputs'!O79=1,IF('Model inputs'!O79="","",'Model inputs'!O79=1))="",FALSE,IF(ISERROR('Model inputs'!O79=1),'Model inputs'!O79=1,IF('Model inputs'!O79="","",'Model inputs'!O79=1))),IF('Model inputs'!B91="","",'Model inputs'!B91),IF('Model inputs'!N17="","",'Model inputs'!N17))="",0,IF(IF(IF(ISERROR('Model inputs'!O79=1),'Model inputs'!O79=1,IF('Model inputs'!O79="","",'Model inputs'!O79=1))="",FALSE,IF(ISERROR('Model inputs'!O79=1),'Model inputs'!O79=1,IF('Model inputs'!O79="","",'Model inputs'!O79=1))),IF('Model inputs'!B91="","",'Model inputs'!B91),IF('Model inputs'!N17="","",'Model inputs'!N17)))+'Model inputs'!O89 -> -2464 | P17: =IF(IF(IF(IF(ISERROR('Model inputs'!P79=1),'Model inputs'!P79=1,IF('Model inputs'!P79="","",'Model inputs'!P79=1))="",FALSE,IF(ISERROR('Model inputs'!P79=1),'Model inputs'!P79=1,IF('Model inputs'!P79="","",'Model inputs'!P79=1))),IF('Model inputs'!B91="","",'Model inputs'!B91),IF('Model inputs'!O17="","",'Model inputs'!O17))="",0,IF(IF(IF(ISERROR('Model inputs'!P79=1),'Model inputs'!P79=1,IF('Model inputs'!P79="","",'Model inputs'!P79=1))="",FALSE,IF(ISERROR('Model inputs'!P79=1),'Model inputs'!P79=1,IF('Model inputs'!P79="","",'Model inputs'!P79=1))),IF('Model inputs'!B91="","",'Model inputs'!B91),IF('Model inputs'!O17="","",'Model inputs'!O17)))+'Model inputs'!P89 -> 539.5
A18: Forecast length · 12-month forecast summary · Susanoo — Base | Q18: =12 -> 12
A19: Forecast length · Customers revenue and run costs · Susanoo — Base | B19: =12 -> 12
A20: Forecast length · Susanoo — Growth | Q20: =12 -> 12
A21: Forecast start date · 12-month forecast summary · Susanoo — Base | Q21: =DATE(2026,11,1) -> 46327
A22: Forecast start date · Customers revenue and run costs · Susanoo — Base | B22: =DATE(2026,11,1) -> 46327
A23: Forecast start date · Susanoo — Growth | Q23: =DATE(2026,11,1) -> 46327
A24: Forecast subscription revenue · by · 12-month forecast summary · Susanoo — Base | C24: =SUM('Model inputs'!C26,'Model inputs'!C27,'Model inputs'!C28) -> #VALUE! | D24: =SUM('Model inputs'!D26,'Model inputs'!D27,'Model inputs'!D28) -> #VALUE! | E24: =SUM('Model inputs'!E26,'Model inputs'!E27,'Model inputs'!E28) -> 158 | F24: =SUM('Model inputs'!F26,'Model inputs'!F27,'Model inputs'!F28) -> 430.90909 | G24: =SUM('Model inputs'!G26,'Model inputs'!G27,'Model inputs'!G28) -> 703.81818 | H24: =SUM('Model inputs'!H26,'Model inputs'!H27,'Model inputs'!H28) -> 976.72727 | I24: =SUM('Model inputs'!I26,'Model inputs'!I27,'Model inputs'!I28) -> 1249.6364 | J24: =SUM('Model inputs'!J26,'Model inputs'!J27,'Model inputs'!J28) -> 1522.5455 | ... P24: =SUM('Model inputs'!P26,'Model inputs'!P27,'Model inputs'!P28) -> 4660
A25: Forecast subscription revenue | C25: =IF('Model inputs'!C24="","",'Model inputs'!C24) -> #VALUE! | D25: =IF('Model inputs'!D24="","",'Model inputs'!D24) -> #VALUE! | E25: =IF('Model inputs'!E24="","",'Model inputs'!E24) -> 158 | F25: =IF('Model inputs'!F24="","",'Model inputs'!F24) -> 430.90909 | G25: =IF('Model inputs'!G24="","",'Model inputs'!G24) -> 703.81818 | H25: =IF('Model inputs'!H24="","",'Model inputs'!H24) -> 976.72727 | I25: =IF('Model inputs'!I24="","",'Model inputs'!I24) -> 1249.6364 | J25: =IF('Model inputs'!J24="","",'Model inputs'!J24) -> 1522.5455 | ... P25: =IF('Model inputs'!P24="","",'Model inputs'!P24) -> 4660
A26: Forecast subscription revenue > Enterprise | C26: ='Model inputs'!C57*'Model inputs'!B33 -> #VALUE! | D26: ='Model inputs'!D57*'Model inputs'!B33 -> #VALUE! | E26: ='Model inputs'!E57*'Model inputs'!B33 -> 0 | F26: ='Model inputs'!F57*'Model inputs'!B33 -> 0 | G26: ='Model inputs'!G57*'Model inputs'!B33 -> 0 | H26: ='Model inputs'!H57*'Model inputs'!B33 -> 0 | I26: ='Model inputs'!I57*'Model inputs'!B33 -> 0 | J26: ='Model inputs'!J57*'Model inputs'!B33 -> 0 | K26: ='Model inputs'!K57*'Model inputs'!B33 -> 0 | L26: ='Model inputs'!L57*'Model inputs'!B33 -> 0 | M26: ='Model inputs'!M57*'Model inputs'!B33 -> 1500 | N26: ='Model inputs'!N57*'Model inputs'!B33 -> 1500 | O26: ='Model inputs'!O57*'Model inputs'!B33 -> 1500 | P26: ='Model inputs'!P57*'Model inputs'!B33 -> 1500
A27: Forecast subscription revenue > Free | C27: ='Model inputs'!C58*'Model inputs'!B34 -> #VALUE! | D27: ='Model inputs'!D58*'Model inputs'!B34 -> #VALUE! | E27: ='Model inputs'!E58*'Model inputs'!B34 -> 0 | F27: ='Model inputs'!F58*'Model inputs'!B34 -> 0 | G27: ='Model inputs'!G58*'Model inputs'!B34 -> 0 | H27: ='Model inputs'!H58*'Model inputs'!B34 -> 0 | I27: ='Model inputs'!I58*'Model inputs'!B34 -> 0 | J27: ='Model inputs'!J58*'Model inputs'!B34 -> 0 | K27: ='Model inputs'!K58*'Model inputs'!B34 -> 0 | L27: ='Model inputs'!L58*'Model inputs'!B34 -> 0 | M27: ='Model inputs'!M58*'Model inputs'!B34 -> 0 | N27: ='Model inputs'!N58*'Model inputs'!B34 -> 0 | O27: ='Model inputs'!O58*'Model inputs'!B34 -> 0 | P27: ='Model inputs'!P58*'Model inputs'!B34 -> 0
A28: Forecast subscription revenue > Team | C28: ='Model inputs'!C59*'Model inputs'!B35 -> #VALUE! | D28: ='Model inputs'!D59*'Model inputs'!B35 -> #VALUE! | E28: ='Model inputs'!E59*'Model inputs'!B35 -> 158 | F28: ='Model inputs'!F59*'Model inputs'!B35 -> 430.90909 | G28: ='Model inputs'!G59*'Model inputs'!B35 -> 703.81818 | H28: ='Model inputs'!H59*'Model inputs'!B35 -> 976.72727 | I28: ='Model inputs'!I59*'Model inputs'!B35 -> 1249.6364 | J28: ='Model inputs'!J59*'Model inputs'!B35 -> 1522.5455 | K28: ='Model inputs'!K59*'Model inputs'!B35 -> 1795.4545 | L28: ='Model inputs'!L59*'Model inputs'!B35 -> 2068.3636 | M28: ='Model inputs'!M59*'Model inputs'!B35 -> 2341.2727 | N28: ='Model inputs'!N59*'Model inputs'!B35 -> 2614.1818 | O28: ='Model inputs'!O59*'Model inputs'!B35 -> 2887.0909 | P28: ='Model inputs'!P59*'Model inputs'!B35 -> 3160
A29: Forecast subscription revenue · Susanoo — Growth | D29: =SUM('Model inputs'!D83,'Model inputs'!D84,'Model inputs'!D85) -> #VALUE! | E29: =SUM('Model inputs'!E83,'Model inputs'!E84,'Model inputs'!E85) -> 395 | F29: =SUM('Model inputs'!F83,'Model inputs'!F84,'Model inputs'!F85) -> 1436.3636 | G29: =SUM('Model inputs'!G83,'Model inputs'!G84,'Model inputs'!G85) -> 2477.7273 | H29: =SUM('Model inputs'!H83,'Model inputs'!H84,'Model inputs'!H85) -> 3519.0909 | I29: =SUM('Model inputs'!I83,'Model inputs'!I84,'Model inputs'!I85) -> 4560.4545 | J29: =SUM('Model inputs'!J83,'Model inputs'!J84,'Model inputs'!J85) -> 7101.8182 | K29: =SUM('Model inputs'!K83,'Model inputs'!K84,'Model inputs'!K85) -> 8143.1818 | ... P29: =SUM('Model inputs'!P83,'Model inputs'!P84,'Model inputs'!P85) -> 17850
A30: Funding needed to date · 12-month forecast summary · Susanoo — Base | C30: =MAX(IF(IF(IF(ISERROR('Model inputs'!C61=1),'Model inputs'!C61=1,IF('Model inputs'!C61="","",'Model inputs'!C61=1))="",FALSE,IF(ISERROR('Model inputs'!C61=1),'Model inputs'!C61=1,IF('Model inputs'!C61="","",'Model inputs'!C61=1))),0,""),MAX(-'Model inputs'!C16,0)) -> #VALUE! | D30: =MAX(IF(IF(IF(ISERROR('Model inputs'!D61=1),'Model inputs'!D61=1,IF('Model inputs'!D61="","",'Model inputs'!D61=1))="",FALSE,IF(ISERROR('Model inputs'!D61=1),'Model inputs'!D61=1,IF('Model inputs'!D61="","",'Model inputs'!D61=1))),0,IF('Model inputs'!C30="","",'Model inputs'!C30)),MAX(-'Model inputs'!D16,0)) -> #VALUE! | E30: =MAX(IF(IF(IF(ISERROR('Model inputs'!E61=1),'Model inputs'!E61=1,IF('Model inputs'!E61="","",'Model inputs'!E61=1))="",FALSE,IF(ISERROR('Model inputs'!E61=1),'Model inputs'!E61=1,IF('Model inputs'!E61="","",'Model inputs'!E61=1))),0,IF('Model inputs'!D30="","",'Model inputs'!D30)),MAX(-'Model inputs'!E16,0)) -> 45.7 | F30: =MAX(IF(IF(IF(ISERROR('Model inputs'!F61=1),'Model inputs'!F61=1,IF('Model inputs'!F61="","",'Model inputs'!F61=1))="",FALSE,IF(ISERROR('Model inputs'!F61=1),'Model inputs'!F61=1,IF('Model inputs'!F61="","",'Model inputs'!F61=1))),0,IF('Model inputs'!E30="","",'Model inputs'!E30)),MAX(-'Model inputs'!F16,0)) -> 45.7 | G30: =MAX(IF(IF(IF(ISERROR('Model inputs'!G61=1),'Model inputs'!G61=1,IF('Model inputs'!G61="","",'Model inputs'!G61=1))="",FALSE,IF(ISERROR('Model inputs'!G61=1),'Model inputs'!G61=1,IF('Model inputs'!G61="","",'Model inputs'!G61=1))),0,IF('Model inputs'!F30="","",'Model inputs'!F30)),MAX(-'Model inputs'!G16,0)) -> 45.7 | H30: =MAX(IF(IF(IF(ISERROR('Model inputs'!H61=1),'Model inputs'!H61=1,IF('Model inputs'!H61="","",'Model inputs'!H61=1))="",FALSE,IF(ISERROR('Model inputs'!H61=1),'Model inputs'!H61=1,IF('Model inputs'!H61="","",'Model inputs'!H61=1))),0,IF('Model inputs'!G30="","",'Model inputs'!G30)),MAX(-'Model inputs'!H16,0)) -> 45.7 | I30: =MAX(IF(IF(IF(ISERROR('Model inputs'!I61=1),'Model inputs'!I61=1,IF('Model inputs'!I61="","",'Model inputs'!I61=1))="",FALSE,IF(ISERROR('Model inputs'!I61=1),'Model inputs'!I61=1,IF('Model inputs'!I61="","",'Model inputs'!I61=1))),0,IF('Model inputs'!H30="","",'Model inputs'!H30)),MAX(-'Model inputs'!I16,0)) -> 45.7 | J30: =MAX(IF(IF(IF(ISERROR('Model inputs'!J61=1),'Model inputs'!J61=1,IF('Model inputs'!J61="","",'Model inputs'!J61=1))="",FALSE,IF(ISERROR('Model inputs'!J61=1),'Model inputs'!J61=1,IF('Model inputs'!J61="","",'Model inputs'!J61=1))),0,IF('Model inputs'!I30="","",'Model inputs'!I30)),MAX(-'Model inputs'!J16,0)) -> 45.7 | K30: =MAX(IF(IF(IF(ISERROR('Model inputs'!K61=1),'Model inputs'!K61=1,IF('Model inputs'!K61="","",'Model inputs'!K61=1))="",FALSE,IF(ISERROR('Model inputs'!K61=1),'Model inputs'!K61=1,IF('Model inputs'!K61="","",'Model inputs'!K61=1))),0,IF('Model inputs'!J30="","",'Model inputs'!J30)),MAX(-'Model inputs'!K16,0)) -> 45.7 | ... P30: =MAX(IF(IF(IF(ISERROR('Model inputs'!P61=1),'Model inputs'!P61=1,IF('Model inputs'!P61="","",'Model inputs'!P61=1))="",FALSE,IF(ISERROR('Model inputs'!P61=1),'Model inputs'!P61=1,IF('Model inputs'!P61="","",'Model inputs'!P61=1))),0,IF('Model inputs'!O30="","",'Model inputs'!O30)),MAX(-'Model inputs'!P16,0)) -> 45.7
A31: Funding needed to date · Susanoo — Growth | D31: =MAX(IF(IF(IF(ISERROR('Model inputs'!D79=1),'Model inputs'!D79=1,IF('Model inputs'!D79="","",'Model inputs'!D79=1))="",FALSE,IF(ISERROR('Model inputs'!D79=1),'Model inputs'!D79=1,IF('Model inputs'!D79="","",'Model inputs'!D79=1))),0,IF('Model inputs'!C86="","",'Model inputs'!C86)),MAX(-'Model inputs'!D17,0)) -> #VALUE! | E31: =MAX(IF(IF(IF(ISERROR('Model inputs'!E79=1),'Model inputs'!E79=1,IF('Model inputs'!E79="","",'Model inputs'!E79=1))="",FALSE,IF(ISERROR('Model inputs'!E79=1),'Model inputs'!E79=1,IF('Model inputs'!E79="","",'Model inputs'!E79=1))),0,IF('Model inputs'!D31="","",'Model inputs'!D31)),MAX(-'Model inputs'!E17,0)) -> 120.25 | F31: =MAX(IF(IF(IF(ISERROR('Model inputs'!F79=1),'Model inputs'!F79=1,IF('Model inputs'!F79="","",'Model inputs'!F79=1))="",FALSE,IF(ISERROR('Model inputs'!F79=1),'Model inputs'!F79=1,IF('Model inputs'!F79="","",'Model inputs'!F79=1))),0,IF('Model inputs'!E31="","",'Model inputs'!E31)),MAX(-'Model inputs'!F17,0)) -> 120.25 | G31: =MAX(IF(IF(IF(ISERROR('Model inputs'!G79=1),'Model inputs'!G79=1,IF('Model inputs'!G79="","",'Model inputs'!G79=1))="",FALSE,IF(ISERROR('Model inputs'!G79=1),'Model inputs'!G79=1,IF('Model inputs'!G79="","",'Model inputs'!G79=1))),0,IF('Model inputs'!F31="","",'Model inputs'!F31)),MAX(-'Model inputs'!G17,0)) -> 120.25 | H31: =MAX(IF(IF(IF(ISERROR('Model inputs'!H79=1),'Model inputs'!H79=1,IF('Model inputs'!H79="","",'Model inputs'!H79=1))="",FALSE,IF(ISERROR('Model inputs'!H79=1),'Model inputs'!H79=1,IF('Model inputs'!H79="","",'Model inputs'!H79=1))),0,IF('Model inputs'!G31="","",'Model inputs'!G31)),MAX(-'Model inputs'!H17,0)) -> 120.25 | I31: =MAX(IF(IF(IF(ISERROR('Model inputs'!I79=1),'Model inputs'!I79=1,IF('Model inputs'!I79="","",'Model inputs'!I79=1))="",FALSE,IF(ISERROR('Model inputs'!I79=1),'Model inputs'!I79=1,IF('Model inputs'!I79="","",'Model inputs'!I79=1))),0,IF('Model inputs'!H31="","",'Model inputs'!H31)),MAX(-'Model inputs'!I17,0)) -> 120.25 | J31: =MAX(IF(IF(IF(ISERROR('Model inputs'!J79=1),'Model inputs'!J79=1,IF('Model inputs'!J79="","",'Model inputs'!J79=1))="",FALSE,IF(ISERROR('Model inputs'!J79=1),'Model inputs'!J79=1,IF('Model inputs'!J79="","",'Model inputs'!J79=1))),0,IF('Model inputs'!I31="","",'Model inputs'!I31)),MAX(-'Model inputs'!J17,0)) -> 271.38636 | K31: =MAX(IF(IF(IF(ISERROR('Model inputs'!K79=1),'Model inputs'!K79=1,IF('Model inputs'!K79="","",'Model inputs'!K79=1))="",FALSE,IF(ISERROR('Model inputs'!K79=1),'Model inputs'!K79=1,IF('Model inputs'!K79="","",'Model inputs'!K79=1))),0,IF('Model inputs'!J31="","",'Model inputs'!J31)),MAX(-'Model inputs'!K17,0)) -> 3004.5909 | L31: =MAX(IF(IF(IF(ISERROR('Model inputs'!L79=1),'Model inputs'!L79=1,IF('Model inputs'!L79="","",'Model inputs'!L79=1))="",FALSE,IF(ISERROR('Model inputs'!L79=1),'Model inputs'!L79=1,IF('Model inputs'!L79="","",'Model inputs'!L79=1))),0,IF('Model inputs'!K31="","",'Model inputs'!K31)),MAX(-'Model inputs'!L17,0)) -> 4052.4545 | ... P31: =MAX(IF(IF(IF(ISERROR('Model inputs'!P79=1),'Model inputs'!P79=1,IF('Model inputs'!P79="","",'Model inputs'!P79=1))="",FALSE,IF(ISERROR('Model inputs'!P79=1),'Model inputs'!P79=1,IF('Model inputs'!P79="","",'Model inputs'!P79=1))),0,IF('Model inputs'!O31="","",'Model inputs'!O31)),MAX(-'Model inputs'!P17,0)) -> 4759.9773
A32: Monthly subscription price | B32: 0
A33: Monthly subscription price > Enterprise | B33: =1500 -> 1500
A34: Monthly subscription price > Free | B34: =0 -> 0
A35: Monthly subscription price > Team | B35: =79 -> 79
A36: Opening customer count | B36: 0
A37: Opening customer count > Enterprise | B37: 0
A38: Opening customer count > Free | B38: =25 -> 25
A39: Opening customer count > Team | B39: =2 -> 2
A40: Starting forecast cash · Monthly revenue cost and runway | B40: =0 -> 0
A41: Total cost per run · Customers revenue and run costs | B41: ='Model inputs'!B87+'Model inputs'!B90 -> 1.55
A42: Total forecast costs · 12-month forecast summary · Susanoo — Base | C42: ='Model inputs'!C62+'Model inputs'!C60+'Model inputs'!C66 -> #VALUE! | D42: ='Model inputs'!D62+'Model inputs'!D60+'Model inputs'!D66 -> #VALUE! | E42: ='Model inputs'!E62+'Model inputs'!E60+'Model inputs'!E66 -> 203.7 | F42: ='Model inputs'!F62+'Model inputs'!F60+'Model inputs'!F66 -> 345.45455 | G42: ='Model inputs'!G62+'Model inputs'!G60+'Model inputs'!G66 -> 487.20909 | H42: ='Model inputs'!H62+'Model inputs'!H60+'Model inputs'!H66 -> 628.96364 | I42: ='Model inputs'!I62+'Model inputs'!I60+'Model inputs'!I66 -> 770.71818 | J42: ='Model inputs'!J62+'Model inputs'!J60+'Model inputs'!J66 -> 912.47273 | ... P42: ='Model inputs'!P62+'Model inputs'!P60+'Model inputs'!P66 -> 1918
A43: Total forecast costs · Susanoo — Growth | D43: ='Model inputs'!D80+'Model inputs'!D78+'Model inputs'!D81 -> #VALUE! | E43: ='Model inputs'!E80+'Model inputs'!E78+'Model inputs'!E81 -> 515.25 | F43: ='Model inputs'!F80+'Model inputs'!F78+'Model inputs'!F81 -> 1216.2727 | G43: ='Model inputs'!G80+'Model inputs'!G78+'Model inputs'!G81 -> 1917.2955 | H43: ='Model inputs'!H80+'Model inputs'!H78+'Model inputs'!H81 -> 2618.3182 | I43: ='Model inputs'!I80+'Model inputs'!I78+'Model inputs'!I81 -> 3319.3409 | J43: ='Model inputs'!J80+'Model inputs'!J78+'Model inputs'!J81 -> 10175.364 | K43: ='Model inputs'!K80+'Model inputs'!K78+'Model inputs'!K81 -> 10876.386 | ... P43: ='Model inputs'!P80+'Model inputs'!P78+'Model inputs'!P81 -> 14846.5
A44: Worker included in plan | B44: 0
A45: Worker included in plan > Founder 1 | B45: =1 -> 1
A46: Worker included in plan > Founder 2 | B46: =1 -> 1
A47: Worker included in plan > Planned engineer | B47: =0 -> 0
A48: Worker monthly salary | B48: 0
A49: Worker monthly salary > Founder 1 | B49: =0 -> 0
A50: Worker monthly salary > Founder 2 | B50: =0 -> 0
A51: Worker monthly salary > Planned engineer | B51: =6000 -> 6000
A52: Worker start month | B52: 0
A53: Worker start month > Founder 1 | B53: =1 -> 1
A54: Worker start month > Founder 2 | B54: =1 -> 1
A55: Worker start month > Planned engineer | B55: =6 -> 6
A56: Forecast customers | C56: =SUM('Model inputs'!C57,'Model inputs'!C58,'Model inputs'!C59) -> #VALUE! | D56: =SUM('Model inputs'!D57,'Model inputs'!D58,'Model inputs'!D59) -> #VALUE! | E56: =SUM('Model inputs'!E57,'Model inputs'!E58,'Model inputs'!E59) -> 27 | F56: =SUM('Model inputs'!F57,'Model inputs'!F58,'Model inputs'!F59) -> 55.454545 | G56: =SUM('Model inputs'!G57,'Model inputs'!G58,'Model inputs'!G59) -> 83.909091 | H56: =SUM('Model inputs'!H57,'Model inputs'!H58,'Model inputs'!H59) -> 112.36364 | I56: =SUM('Model inputs'!I57,'Model inputs'!I58,'Model inputs'!I59) -> 140.81818 | J56: =SUM('Model inputs'!J57,'Model inputs'!J58,'Model inputs'!J59) -> 169.27273 | ... P56: =SUM('Model inputs'!P57,'Model inputs'!P58,'Model inputs'!P59) -> 341
